Workbook

Sheet Summary
A1: £000's | C1: FY24 | D1: FY25 | E1: FY26 | F1: FY27 | G1: FY28
A3: Screens
A4: ISP Owned | C4: ='KPI''s'!U7 -> 300 | D4: ='KPI''s'!AG7 -> 630 | E4: ='KPI''s'!AS7 -> 1062 | F4: ='KPI''s'!BE7 -> 1578 | G4: ='KPI''s'!BQ7 -> 2202
A5: In-home Media Owned | C5: ='KPI''s'!U8 -> 62 | D5: ='KPI''s'!AG8 -> 532 | E5: ='KPI''s'!AS8 -> 1108 | F5: ='KPI''s'!BE8 -> 1780 | G5: ='KPI''s'!BQ8 -> 2548
A6: Total | C6: =SUM(C4:C5) -> 362 | D6: =SUM(D4:D5) -> 1162 | E6: =SUM(E4:E5) -> 2170 | F6: =SUM(F4:F5) -> 3358 | G6: =SUM(G4:G5) -> 4750
A8: One off Revenue | C8: ='Financials Annual'!J7 -> 477408 | D8: ='Financials Annual'!K7 -> 806250 | E8: ='Financials Annual'!L7 -> 1152360 | F8: ='Financials Annual'!M7 -> 1509717 | G8: ='Financials Annual'!N7 -> 1813548
A9: Recurring Revenue | C9: ='Financials Annual'!J8 -> 225650 | D9: ='Financials Annual'!K8 -> 1927125 | E9: ='Financials Annual'!L8 -> 5115792 | F9: ='Financials Annual'!M8 -> 9517878.2 | G9: ='Financials Annual'!N8 -> 14098993
A10: Total Revenue | C10: =SUM(C8:C9) -> 703058 | D10: =SUM(D8:D9) -> 2733375 | E10: =SUM(E8:E9) -> 6268152 | F10: =SUM(F8:F9) -> 11027595 | G10: =SUM(G8:G9) -> 15912541
A12: Gross Profit | C12: ='Financials Annual'!J19 -> 296569 | D12: ='Financials Annual'!K19 -> 1055673 | E12: ='Financials Annual'!L19 -> 3423842.7 | F12: ='Financials Annual'!M19 -> 6828602.2 | G12: ='Financials Annual'!N19 -> 10155861
A13: Gross Margin | C13: ='Financials Annual'!J20 -> 0.42182722 | D13: ='Financials Annual'!K20 -> 0.38621594 | E13: ='Financials Annual'!L20 -> 0.5462284 | F13: ='Financials Annual'!M20 -> 0.61922859 | G13: ='Financials Annual'!N20 -> 0.63822999
A15: Administrative expenses | C15: ='Financials Annual'!J28 -> 453909.25 | D15: ='Financials Annual'!K28 -> 854359.5 | E15: ='Financials Annual'!L28 -> 964229.5 | F15: ='Financials Annual'!M28 -> 1077323.3 | G15: ='Financials Annual'!N28 -> 1213119.8
A17: EBITDA | C17: ='Financials Annual'!J30 -> -157340.25 | D17: ='Financials Annual'!K30 -> 201313.5 | E17: ='Financials Annual'!L30 -> 2459613.2 | F17: ='Financials Annual'!M30 -> 5751278.9 | G17: ='Financials Annual'!N30 -> 8942740.9
A18: EBITDA % | C18: ='Financials Annual'!J31 -> -0.22379413 | D18: ='Financials Annual'!K31 -> 0.073650158 | E18: ='Financials Annual'!L31 -> 0.39239846 | F18: ='Financials Annual'!M31 -> 0.52153519 | G18: ='Financials Annual'!N31 -> 0.56199328
A20: Cashflow | C20: ='Financials Annual'!J148 -> -250520.8 | D20: ='Financials Annual'!K148 -> -400123.85 | E20: ='Financials Annual'!L148 -> 1765344.1 | F20: ='Financials Annual'!M148 -> 4279997.6 | G20: ='Financials Annual'!N148 -> 6628536.2
A21: Closing Cash | C21: ='Financials Annual'!J150 -> -250520.8 | D21: ='Financials Annual'!K150 -> -650644.65 | E21: ='Financials Annual'!L150 -> 1114699.5 | F21: ='Financials Annual'!M150 -> 5394697.1 | G21: ='Financials Annual'!N150 -> 12023233
A23: Cash lowpoint | C23: =MIN('Financials Monthly'!J150:BQ150) -> -722826.32 | D23: ='Financials Monthly'!AD3 -> 45626
A24: Cash flow breakeven | D24: ='Financials Monthly'!AN3 -> 45930

Sheet KPI's
A1: Business 1
A2: KPI's | J2: =Timing!J2 -> 44986 | K2: =Timing!K2 -> 45017 | L2: =Timing!L2 -> 45047 | M2: =Timing!M2 -> 45078 | N2: =Timing!N2 -> 45108 | O2: =Timing!O2 -> 45139 | P2: =Timing!P2 -> 45170 | Q2: =Timing!Q2 -> 45200 | ... BQ2: =Timing!BQ2 -> 46784
J3: =Timing!J3 -> 45016 | K3: =Timing!K3 -> 45046 | L3: =Timing!L3 -> 45077 | M3: =Timing!M3 -> 45107 | N3: =Timing!N3 -> 45138 | O3: =Timing!O3 -> 45169 | P3: =Timing!P3 -> 45199 | Q3: =Timing!Q3 -> 45230 | ... BQ3: =Timing!BQ3 -> 46812
B6: Total Screens
B7: ISP Owned | J7: =Inputs!J33 -> 90 | K7: =Inputs!K33 -> 120 | L7: =Inputs!L33 -> 120 | M7: =Inputs!M33 -> 150 | N7: =Inputs!N33 -> 180 | O7: =Inputs!O33 -> 240 | P7: =Inputs!P33 -> 300 | Q7: =Inputs!Q33 -> 300 | ... BQ7: =Inputs!BQ33 -> 2202
B8: In-home Media Owned | J8: =Inputs!J37+Inputs!J41+Inputs!J45 -> 0 | K8: =Inputs!K37+Inputs!K41+Inputs!K45 -> 0 | L8: =Inputs!L37+Inputs!L41+Inputs!L45 -> 0 | M8: =Inputs!M37+Inputs!M41+Inputs!M45 -> 0 | N8: =Inputs!N37+Inputs!N41+Inputs!N45 -> 0 | O8: =Inputs!O37+Inputs!O41+Inputs!O45 -> 0 | P8: =Inputs!P37+Inputs!P41+Inputs!P45 -> 0 | Q8: =Inputs!Q37+Inputs!Q41+Inputs!Q45 -> 0 | ... BQ8: =Inputs!BQ37+Inputs!BQ41+Inputs!BQ45 -> 2548
B9: Total | J9: =SUM(J7:J8) -> 90 | K9: =SUM(K7:K8) -> 120 | L9: =SUM(L7:L8) -> 120 | M9: =SUM(M7:M8) -> 150 | N9: =SUM(N7:N8) -> 180 | O9: =SUM(O7:O8) -> 240 | P9: =SUM(P7:P8) -> 300 | Q9: =SUM(Q7:Q8) -> 300 | ... BQ9: =SUM(BQ7:BQ8) -> 4750
B12: Screens Added by Month
B13: ISP Owned | J13: =Inputs!J32 -> 30 | K13: =Inputs!K32 -> 30 | L13: =Inputs!L32 -> 0 | M13: =Inputs!M32 -> 30 | N13: =Inputs!N32 -> 30 | O13: =Inputs!O32 -> 30 | P13: =Inputs!P32 -> 60 | Q13: =Inputs!Q32 -> 0 | ... BQ13: =Inputs!BQ32 -> 52
B14: In-home Media Owned | J14: =Inputs!J36+Inputs!J40+Inputs!J44 -> 0 | K14: =Inputs!K36+Inputs!K40+Inputs!K44 -> 0 | L14: =Inputs!L36+Inputs!L40+Inputs!L44 -> 0 | M14: =Inputs!M36+Inputs!M40+Inputs!M44 -> 0 | N14: =Inputs!N36+Inputs!N40+Inputs!N44 -> 0 | O14: =Inputs!O36+Inputs!O40+Inputs!O44 -> 0 | P14: =Inputs!P36+Inputs!P40+Inputs!P44 -> 0 | Q14: =Inputs!Q36+Inputs!Q40+Inputs!Q44 -> 0 | ... BQ14: =Inputs!BQ36+Inputs!BQ40+Inputs!BQ44 -> 64
B15: Total | J15: =SUM(J13:J14) -> 30 | K15: =SUM(K13:K14) -> 30 | L15: =SUM(L13:L14) -> 0 | M15: =SUM(M13:M14) -> 30 | N15: =SUM(N13:N14) -> 30 | O15: =SUM(O13:O14) -> 30 | P15: =SUM(P13:P14) -> 60 | Q15: =SUM(Q13:Q14) -> 0 | ... BQ15: =SUM(BQ13:BQ14) -> 116

Sheet Financials Annual
A1: Business 1 | B1: Business 1
A2: Financials | B2: Financials -Annual
J3: FY24 | K3: FY25 | L3: FY26 | M3: FY27 | N3: FY28
B4: PROFIT & LOSS | J4: 45323 | K4: 45689 | L4: 46054 | M4: 46419 | N4: 46784
B6: Revenue
C7: One off Revenue | J7: =SUM('Financials Monthly'!J7:U7) -> 477408 | K7: =SUM('Financials Monthly'!V7:AG7) -> 806250 | L7: =SUM('Financials Monthly'!AH7:AS7) -> 1152360 | M7: =SUM('Financials Monthly'!AT7:BE7) -> 1509717 | N7: =SUM('Financials Monthly'!BF7:BQ7) -> 1813548
C8: Recurring Revenue | J8: =SUM('Financials Monthly'!J8:U8) -> 225650 | K8: =SUM('Financials Monthly'!V8:AG8) -> 1927125 | L8: =SUM('Financials Monthly'!AH8:AS8) -> 5115792 | M8: =SUM('Financials Monthly'!AT8:BE8) -> 9517878.2 | N8: =SUM('Financials Monthly'!BF8:BQ8) -> 14098993
C9: Other Revenue | J9: =SUM('Financials Monthly'!J9:U9) -> 0 | K9: =SUM('Financials Monthly'!V9:AG9) -> 0 | L9: =SUM('Financials Monthly'!AH9:AS9) -> 0 | M9: =SUM('Financials Monthly'!AT9:BE9) -> 0 | N9: =SUM('Financials Monthly'!AU9:BF9) -> 0
C10: Total | J10: =SUM('Financials Monthly'!J10:U10) -> 703058 | K10: =SUM('Financials Monthly'!V10:AG10) -> 2733375 | L10: =SUM('Financials Monthly'!AH10:AS10) -> 6268152 | M10: =SUM('Financials Monthly'!AT10:BE10) -> 11027595 | N10: =SUM('Financials Monthly'!BF10:BQ10) -> 15912541
B12: Cost of sales
C13: Cost of Sales | J13: =SUM('Financials Monthly'!J13:U13) -> 381414 | K13: =SUM('Financials Monthly'!V13:AG13) -> 1385652 | L13: =SUM('Financials Monthly'!AH13:AS13) -> 2486376 | M13: =SUM('Financials Monthly'!AT13:BE13) -> 3744693 | N13: =SUM('Financials Monthly'!BF13:BQ13) -> 5249280
C14: Gross Wages and Salaries (COS) | J14: =SUM('Financials Monthly'!J14:U14) -> 21250 | K14: =SUM('Financials Monthly'!V14:AG14) -> 247500 | L14: =SUM('Financials Monthly'!AH14:AS14) -> 303333.33 | M14: =SUM('Financials Monthly'!AT14:BE14) -> 385000 | N14: =SUM('Financials Monthly'!BF14:BQ14) -> 430000
C15: COS Ers NI | J15: =SUM('Financials Monthly'!J15:U15) -> 3187.5 | K15: =SUM('Financials Monthly'!V15:AG15) -> 37125 | L15: =SUM('Financials Monthly'!AH15:AS15) -> 45500 | M15: =SUM('Financials Monthly'!AT15:BE15) -> 57750 | N15: =SUM('Financials Monthly'!BF15:BQ15) -> 64500
C16: COS Ers Pension | J16: =SUM('Financials Monthly'!J16:U16) -> 637.5 | K16: =SUM('Financials Monthly'!V16:AG16) -> 7425 | L16: =SUM('Financials Monthly'!AH16:AS16) -> 9100 | M16: =SUM('Financials Monthly'!AT16:BE16) -> 11550 | N16: =SUM('Financials Monthly'!BF16:BQ16) -> 12900
C17: Total | J17: =SUM('Financials Monthly'!J17:U17) -> 406489 | K17: =SUM('Financials Monthly'!V17:AG17) -> 1677702 | L17: =SUM('Financials Monthly'!AH17:AS17) -> 2844309.3 | M17: =SUM('Financials Monthly'!AT17:BE17) -> 4198993 | N17: =SUM('Financials Monthly'!BF17:BQ17) -> 5756680
B19: Gross profit | J19: =J10-J17 -> 296569 | K19: =K10-K17 -> 1055673 | L19: =L10-L17 -> 3423842.7 | M19: =M10-M17 -> 6828602.2 | N19: =N10-N17 -> 10155861
C20: GP margin (%) | J20: =J19/J10 -> 0.42182722 | K20: =K19/K10 -> 0.38621594 | L20: =L19/L10 -> 0.5462284 | M20: =M19/M10 -> 0.61922859 | N20: =N19/N10 -> 0.63822999
B22: Administrative expenses
C23: Gross wages and Salaries (Admin Expenses) | J23: =SUM('Financials Monthly'!J23:U23) -> 37500 | K23: =SUM('Financials Monthly'!V23:AG23) -> 91250 | L23: =SUM('Financials Monthly'!AH23:AS23) -> 125000 | M23: =SUM('Financials Monthly'!AT23:BE23) -> 160000 | N23: =SUM('Financials Monthly'!BF23:BQ23) -> 195000
C24: Wages and Salaries Er's NI | J24: =SUM('Financials Monthly'!J24:U24) -> 1875 | K24: =SUM('Financials Monthly'!V24:AG24) -> 13687.5 | L24: =SUM('Financials Monthly'!AH24:AS24) -> 18750 | M24: =SUM('Financials Monthly'!AT24:BE24) -> 24000 | N24: =SUM('Financials Monthly'!BF24:BQ24) -> 29250
C25: Wages and Salaries Pension | J25: =SUM('Financials Monthly'!J25:U25) -> 375 | K25: =SUM('Financials Monthly'!V25:AG25) -> 2737.5 | L25: =SUM('Financials Monthly'!AH25:AS25) -> 3750 | M25: =SUM('Financials Monthly'!AT25:BE25) -> 4800 | N25: =SUM('Financials Monthly'!BF25:BQ25) -> 5850
C26: Directors wages and Salaries (Incl Ni and Pension) | J26: =SUM('Financials Monthly'!J26:U26) -> 0 | K26: =SUM('Financials Monthly'!V26:AG26) -> 453375 | L26: =SUM('Financials Monthly'!AH26:AS26) -> 526500 | M26: =SUM('Financials Monthly'!AT26:BE26) -> 526500 | N26: =SUM('Financials Monthly'!BF26:BQ26) -> 526500
C27: Other Administrative Expenses | J27: =SUM('Financials Monthly'!J27:U27) -> 414159.25 | K27: =SUM('Financials Monthly'!V27:AG27) -> 293309.5 | L27: =SUM('Financials Monthly'!AH27:AS27) -> 290229.5 | M27: =SUM('Financials Monthly'!AT27:BE27) -> 362023.25 | N27: =SUM('Financials Monthly'!BF27:BQ27) -> 456519.75
C28: Total | J28: =SUM('Financials Monthly'!J28:U28) -> 453909.25 | K28: =SUM('Financials Monthly'!V28:AG28) -> 854359.5 | L28: =SUM('Financials Monthly'!AH28:AS28) -> 964229.5 | M28: =SUM('Financials Monthly'!AT28:BE28) -> 1077323.3 | N28: =SUM('Financials Monthly'!BF28:BQ28) -> 1213119.8
C30: EBITDA | J30: =SUM('Financials Monthly'!J30:U30) -> -157340.25 | K30: =SUM('Financials Monthly'!V30:AG30) -> 201313.5 | L30: =SUM('Financials Monthly'!AH30:AS30) -> 2459613.2 | M30: =SUM('Financials Monthly'!AT30:BE30) -> 5751278.9 | N30: =SUM('Financials Monthly'!BF30:BQ30) -> 8942740.9
C31: EBITDA (%) | J31: =J30/J10 -> -0.22379413 | K31: =K30/K10 -> 0.073650158 | L31: =L30/L10 -> 0.39239846 | M31: =M30/M10 -> 0.52153519 | N31: =N30/N10 -> 0.56199328
B33: Non-Operational Costs
C34: Exceptional Costs | J34: =SUM('Financials Monthly'!J34:U34) -> 0 | K34: =SUM('Financials Monthly'!V34:AG34) -> 0 | L34: =SUM('Financials Monthly'!AH34:AS34) -> 0 | M34: =SUM('Financials Monthly'!AT34:BE34) -> 0 | N34: =SUM('Financials Monthly'!AU34:BF34) -> 0
C35: Investor Fees | J35: =SUM('Financials Monthly'!J35:U35) -> 0 | K35: =SUM('Financials Monthly'!V35:AG35) -> 0 | L35: =SUM('Financials Monthly'!AH35:AS35) -> 0 | M35: =SUM('Financials Monthly'!AT35:BE35) -> 0 | N35: =SUM('Financials Monthly'!AU35:BF35) -> 0
C36: Adjusted EBITDA | J36: =SUM('Financials Monthly'!J36:U36) -> -157340.25 | K36: =SUM('Financials Monthly'!V36:AG36) -> 201313.5 | L36: =SUM('Financials Monthly'!AH36:AS36) -> 2459613.2 | M36: =SUM('Financials Monthly'!AT36:BE36) -> 5751278.9 | N36: =SUM('Financials Monthly'!BF36:BQ36) -> 8942740.9
B38: Depreciation and amortisation
C39: Depreciation | J39: =SUM('Financials Monthly'!J39:U39) -> 1077.9167 | K39: =SUM('Financials Monthly'!V39:AG39) -> 46117.5 | L39: =SUM('Financials Monthly'!AH39:AS39) -> 130975 | M39: =SUM('Financials Monthly'!AT39:BE39) -> 229287.5 | N39: =SUM('Financials Monthly'!BF39:BQ39) -> 341055
C40: Total | J40: =SUM('Financials Monthly'!J40:U40) -> 1077.9167 | K40: =SUM('Financials Monthly'!V40:AG40) -> 46117.5 | L40: =SUM('Financials Monthly'!AH40:AS40) -> 130975 | M40: =SUM('Financials Monthly'!AT40:BE40) -> 229287.5 | N40: =SUM('Financials Monthly'!BF40:BQ40) -> 341055
C42: EBIT | J42: =SUM('Financials Monthly'!J42:U42) -> -158418.17 | K42: =SUM('Financials Monthly'!V42:AG42) -> 155196 | L42: =SUM('Financials Monthly'!AH42:AS42) -> 2328638.2 | M42: =SUM('Financials Monthly'!AT42:BE42) -> 5521991.4 | N42: =SUM('Financials Monthly'!BF42:BQ42) -> 8601685.9
C43: EBIT (%) | J43: =J42/J10 -> -0.22532731 | K43: =K42/K10 -> 0.056778159 | L43: =L42/L10 -> 0.37150314 | M43: =M42/M10 -> 0.50074303 | N43: =N42/N10 -> 0.54056018
B45: Interest chargeable and receivable
C47: Interest | J47: =SUM('Financials Monthly'!J47:U47) -> 0 | K47: =SUM('Financials Monthly'!V47:AG47) -> 0 | L47: =SUM('Financials Monthly'!AH47:AS47) -> 0 | M47: =SUM('Financials Monthly'!AT47:BE47) -> 0 | N47: =SUM('Financials Monthly'!AU47:BF47) -> 0
C48: Total | J48: =SUM('Financials Monthly'!J48:U48) -> -158418.17 | K48: =SUM('Financials Monthly'!V48:AG48) -> 155196 | L48: =SUM('Financials Monthly'!AH48:AS48) -> 2328638.2 | M48: =SUM('Financials Monthly'!AT48:BE48) -> 5521991.4 | N48: =SUM('Financials Monthly'!BF48:BQ48) -> 8601685.9
C50: Profit before Tax | J50: =SUM('Financials Monthly'!J50:U50) -> -158418.17 | K50: =SUM('Financials Monthly'!V50:AG50) -> 155196 | L50: =SUM('Financials Monthly'!AH50:AS50) -> 2328638.2 | M50: =SUM('Financials Monthly'!AT50:BE50) -> 5521991.4 | N50: =SUM('Financials Monthly'!BF50:BQ50) -> 8601685.9
C52: Deferred Tax | J52: =SUM('Financials Monthly'!J52:U52) -> 0 | K52: =SUM('Financials Monthly'!V52:AG52) -> 0 | L52: =SUM('Financials Monthly'!AH52:AS52) -> 0 | M52: =SUM('Financials Monthly'!AT52:BE52) -> 0 | N52: =SUM('Financials Monthly'!AU52:BF52) -> 0
C53: Tax Charge | J53: =SUM('Financials Monthly'!J53:U53) -> 0 | K53: =SUM('Financials Monthly'!V53:AG53) -> 0 | L53: =SUM('Financials Monthly'!AH53:AS53) -> 582159.54 | M53: =SUM('Financials Monthly'!AT53:BE53) -> 1380497.9 | N53: =SUM('Financials Monthly'!AU53:BF53) -> 1439725.7
C55: Profit after Tax | J55: =SUM('Financials Monthly'!J55:U55) -> -158418.17 | K55: =SUM('Financials Monthly'!V55:AG55) -> 155196 | L55: =SUM('Financials Monthly'!AH55:AS55) -> 1746478.6 | M55: =SUM('Financials Monthly'!AT55:BE55) -> 4141493.5 | N55: =SUM('Financials Monthly'!BF55:BQ55) -> 6451264.4
B57: Retained Earnings
C58: Retained Earnings b/f | J58: ='Financials Monthly'!J58 -> 0 | K58: =J61 -> -158418.17 | L58: =K61 -> -3222.1667 | M58: =L61 -> 1743256.5 | N58: =M61 -> 5884750
C59: Profit after tax | J59: =SUM('Financials Monthly'!J59:U59) -> -158418.17 | K59: =SUM('Financials Monthly'!V59:AG59) -> 155196 | L59: =SUM('Financials Monthly'!AH59:AS59) -> 1746478.6 | M59: =SUM('Financials Monthly'!AT59:BE59) -> 4141493.5 | N59: =SUM('Financials Monthly'!BF59:BQ59) -> 6451264.4
C60: =[1]Funding!C$35 -> Dividends Paid | J60: =SUM('Financials Monthly'!J60:U60) -> 0 | K60: =SUM('Financials Monthly'!V60:AG60) -> 0 | L60: =SUM('Financials Monthly'!AH60:AS60) -> 0 | M60: =SUM('Financials Monthly'!AT60:BE60) -> 0 | N60: =SUM('Financials Monthly'!AU60:BF60) -> 0
C61: Retained Earnings c/f | J61: =SUM(J58:J60) -> -158418.17 | K61: =SUM(K58:K60) -> -3222.1667 | L61: =SUM(L58:L60) -> 1743256.5 | M61: =SUM(M58:M60) -> 5884750 | N61: =SUM(N58:N60) -> 12336014
B64: BALANCE SHEET
B66: Fixed Assets
C67: Intangibe NBV | J67: ='Financials Monthly'!U67 -> 68906.25 | K67: ='Financials Monthly'!AG67 -> 121770.83 | L67: ='Financials Monthly'!AS67 -> 104270.83 | M67: ='Financials Monthly'!BE67 -> 86770.833 | N67: ='Financials Monthly'!BQ67 -> 69270.833
C68: Tangible NBV | J68: ='Financials Monthly'!U68 -> 29092.083 | K68: ='Financials Monthly'!AG68 -> 276024.58 | L68: ='Financials Monthly'!AS68 -> 509729.58 | M68: ='Financials Monthly'!BE68 -> 695402.08 | N68: ='Financials Monthly'!BQ68 -> 828587.08
C69: Total fixed assets | J69: ='Financials Monthly'!U69 -> 97998.333 | K69: ='Financials Monthly'!AG69 -> 397795.42 | L69: ='Financials Monthly'!AS69 -> 614000.42 | M69: ='Financials Monthly'!BE69 -> 782172.92 | N69: ='Financials Monthly'!BQ69 -> 897857.92
B71: Current assets
C72: Trade Debtors | J72: ='Financials Monthly'!U72 -> 95545.885 | K72: ='Financials Monthly'!AG72 -> 571619.35 | L72: ='Financials Monthly'!AS72 -> 1130503.5 | M72: ='Financials Monthly'!BE72 -> 1895428.1 | N72: ='Financials Monthly'!BQ72 -> 2664429.4
C73: Other Debtors | J73: ='Financials Monthly'!U73 -> 0 | K73: ='Financials Monthly'!AG73 -> 0 | L73: ='Financials Monthly'!AS73 -> 0 | M73: ='Financials Monthly'!BE73 -> 0 | N73: ='Financials Monthly'!BF73 -> 0
C74: Cash | J74: ='Financials Monthly'!U74 -> -250520.8 | K74: ='Financials Monthly'!AG74 -> -650644.65 | L74: ='Financials Monthly'!AS74 -> 1114699.5 | M74: ='Financials Monthly'!BE74 -> 5394697.1 | N74: ='Financials Monthly'!BQ74 -> 12023233
C75: Total current assets | J75: ='Financials Monthly'!U75 -> -154974.91 | K75: ='Financials Monthly'!AG75 -> -79025.293 | L75: ='Financials Monthly'!AS75 -> 2245203 | M75: ='Financials Monthly'!BE75 -> 7290125.1 | N75: ='Financials Monthly'!BQ75 -> 14687663
C77: Total Assets | J77: ='Financials Monthly'!U77 -> -56976.579 | K77: ='Financials Monthly'!AG77 -> 318770.12 | L77: ='Financials Monthly'!AS77 -> 2859203.4 | M77: ='Financials Monthly'!BE77 -> 8072298.1 | N77: ='Financials Monthly'!BQ77 -> 15585521
B79: Liabilities
C80: Trade Creditors | J80: ='Financials Monthly'!U80 -> 111612.64 | K80: ='Financials Monthly'!AG80 -> 234703.59 | L80: ='Financials Monthly'!AS80 -> 356632.14 | M80: ='Financials Monthly'!BE80 -> 502344.49 | N80: ='Financials Monthly'!BQ80 -> 675907.07
C81: Other Creditors | J81: ='Financials Monthly'!U81 -> 0 | K81: ='Financials Monthly'!AG81 -> 0 | L81: ='Financials Monthly'!AS81 -> 0 | M81: ='Financials Monthly'!BE81 -> 0 | N81: ='Financials Monthly'!BQ81 -> 0
C82: Corporate Tax | J82: ='Financials Monthly'!U82 -> 0 | K82: ='Financials Monthly'!AG82 -> 0 | L82: ='Financials Monthly'!AS82 -> 582159.54 | M82: ='Financials Monthly'!BE82 -> 1380497.9 | N82: ='Financials Monthly'!BQ82 -> 2150421.5
C83: Other Taxation and Social Security | J83: ='Financials Monthly'!U83 -> -10171.05 | K83: ='Financials Monthly'!AG83 -> 87288.7 | L83: ='Financials Monthly'!AS83 -> 177155.3 | M83: ='Financials Monthly'!BE83 -> 304705.7 | N83: ='Financials Monthly'!BQ83 -> 423177.62
C84: Accruals and deferred Income | J84: ='Financials Monthly'!U84 -> 0 | K84: ='Financials Monthly'!AG84 -> 0 | L84: ='Financials Monthly'!AS84 -> 0 | M84: ='Financials Monthly'!BE84 -> 0 | N84: ='Financials Monthly'!BQ84 -> 0
C85: Item 1 | J85: ='Financials Monthly'!U85 -> 0 | K85: ='Financials Monthly'!AG85 -> 0 | L85: ='Financials Monthly'!AS85 -> 0 | M85: ='Financials Monthly'!BE85 -> 0 | N85: ='Financials Monthly'!BQ85 -> 0
C86: Item 2 | J86: ='Financials Monthly'!U86 -> 0 | K86: ='Financials Monthly'!AG86 -> 0 | L86: ='Financials Monthly'!AS86 -> 0 | M86: ='Financials Monthly'!BE86 -> 0 | N86: ='Financials Monthly'!BQ86 -> 0
C87: Item 3 | J87: ='Financials Monthly'!U87 -> 0 | K87: ='Financials Monthly'!AG87 -> 0 | L87: ='Financials Monthly'!AS87 -> 0 | M87: ='Financials Monthly'!BE87 -> 0 | N87: ='Financials Monthly'!BQ87 -> 0
C88: Total current liabilities | J88: ='Financials Monthly'!U88 -> 101441.59 | K88: ='Financials Monthly'!AG88 -> 321992.29 | L88: ='Financials Monthly'!AS88 -> 1115947 | M88: ='Financials Monthly'!BE88 -> 2187548 | N88: ='Financials Monthly'!BQ88 -> 3249506.2
C90: Non-current liabilities
C91: Long term loan | J91: ='Financials Monthly'!U91 -> 0 | K91: ='Financials Monthly'!AG91 -> 0 | L91: ='Financials Monthly'!AS91 -> 0 | M91: ='Financials Monthly'!BE91 -> 0 | N91: ='Financials Monthly'!BQ91 -> 0
C92: Item 2 | J92: ='Financials Monthly'!U92 -> 0 | K92: ='Financials Monthly'!AG92 -> 0 | L92: ='Financials Monthly'!AS92 -> 0 | M92: ='Financials Monthly'!BE92 -> 0 | N92: ='Financials Monthly'!BQ92 -> 0
C93: Total non-current liabilities | J93: ='Financials Monthly'!U93 -> 0 | K93: ='Financials Monthly'!AG93 -> 0 | L93: ='Financials Monthly'!AS93 -> 0 | M93: ='Financials Monthly'!BE93 -> 0 | N93: ='Financials Monthly'!BQ93 -> 0
C95: Provision for Liabiities | J95: ='Financials Monthly'!U95 -> 0 | K95: ='Financials Monthly'!AG95 -> 0 | L95: ='Financials Monthly'!AS95 -> 0 | M95: ='Financials Monthly'!BE95 -> 0 | N95: ='Financials Monthly'!BQ95 -> 0
C97: Total Liabilities | J97: ='Financials Monthly'!U97 -> 101441.59 | K97: ='Financials Monthly'!AG97 -> 321992.29 | L97: ='Financials Monthly'!AS97 -> 1115947 | M97: ='Financials Monthly'!BE97 -> 2187548 | N97: ='Financials Monthly'!BQ97 -> 3249506.2
C99: Net Assets / (Liabilities) | J99: ='Financials Monthly'!U99 -> -158418.17 | K99: ='Financials Monthly'!AG99 -> -3222.1667 | L99: ='Financials Monthly'!AS99 -> 1743256.5 | M99: ='Financials Monthly'!BE99 -> 5884750 | N99: ='Financials Monthly'!BQ99 -> 12336014
C101: Share capital and reserves
C102: Ordinary Equity | J102: ='Financials Monthly'!U102 -> 0 | K102: ='Financials Monthly'!AG102 -> 0 | L102: ='Financials Monthly'!AS102 -> 0 | M102: ='Financials Monthly'!BE102 -> 0 | N102: ='Financials Monthly'!BF102 -> 0
C103: Retained Earnings | J103: ='Financials Monthly'!U103 -> -158418.17 | K103: ='Financials Monthly'!AG103 -> -3222.1667 | L103: ='Financials Monthly'!AS103 -> 1743256.5 | M103: ='Financials Monthly'!BE103 -> 5884750 | N103: ='Financials Monthly'!BQ103 -> 12336014
C104: Item 3 | J104: ='Financials Monthly'!U104 -> 0 | K104: ='Financials Monthly'!AG104 -> 0 | L104: ='Financials Monthly'!AS104 -> 0 | M104: ='Financials Monthly'!BE104 -> 0 | N104: ='Financials Monthly'!BF104 -> 0
C105: Total share capital and reserves | J105: ='Financials Monthly'!U105 -> -158418.17 | K105: ='Financials Monthly'!AG105 -> -3222.1667 | L105: ='Financials Monthly'!AS105 -> 1743256.5 | M105: ='Financials Monthly'!BE105 -> 5884750 | N105: ='Financials Monthly'!BQ105 -> 12336014
C107: Balance Check | J107: =J99-J105 -> 0 | K107: =K99-K105 -> -1.6007107e-10 | L107: =L99-L105 -> 0 | M107: =M99-M105 -> 0 | N107: =N99-N105 -> 0
C108: Balance Check - Forecast
B110: CF
B112: CASH GENERATED FROM OPERATIONS
B114: Operating profit | J114: =SUM('Financials Monthly'!J114:U114) -> -158418.17 | K114: =SUM('Financials Monthly'!V114:AG114) -> 155196 | L114: =SUM('Financials Monthly'!AH114:AS114) -> 2328638.2 | M114: =SUM('Financials Monthly'!AT114:BE114) -> 5521991.4 | N114: =SUM('Financials Monthly'!BF114:BQ114) -> 8601685.9
B116: Adjustments for:
B117: Depreciation charges | J117: =SUM('Financials Monthly'!J117:U117) -> 1077.9167 | K117: =SUM('Financials Monthly'!V117:AG117) -> 46117.5 | L117: =SUM('Financials Monthly'!AH117:AS117) -> 130975 | M117: =SUM('Financials Monthly'!AT117:BE117) -> 229287.5 | N117: =SUM('Financials Monthly'!BF117:BQ117) -> 341055
B118: Amortisation charges | J118: =SUM('Financials Monthly'!J118:U118) -> 1093.75 | K118: =SUM('Financials Monthly'!V118:AG118) -> 17135.417 | L118: =SUM('Financials Monthly'!AH118:AS118) -> 17500 | M118: =SUM('Financials Monthly'!AT118:BE118) -> 17500 | N118: =SUM('Financials Monthly'!BF118:BQ118) -> 17500
B119: (Profit) / loss on disposal of fixed assets | J119: =SUM('Financials Monthly'!J119:U119) -> 0 | K119: =SUM('Financials Monthly'!V119:AG119) -> 0 | L119: =SUM('Financials Monthly'!AH119:AS119) -> 0 | M119: =SUM('Financials Monthly'!AT119:BE119) -> 0 | N119: =SUM('Financials Monthly'!BF119:BQ119) -> 0
B120: Operating cash flow before changes in working capital | J120: =SUM('Financials Monthly'!J120:U120) -> -156246.5 | K120: =SUM('Financials Monthly'!V120:AG120) -> 218448.92 | L120: =SUM('Financials Monthly'!AH120:AS120) -> 2477113.2 | M120: =SUM('Financials Monthly'!AT120:BE120) -> 5768778.9 | N120: =SUM('Financials Monthly'!BF120:BQ120) -> 8960240.9
B122: Changes in working capital
B123: (Increase) / decrease in trade receivables | J123: =SUM('Financials Monthly'!J123:U123) -> -95545.885 | K123: =SUM('Financials Monthly'!V123:AG123) -> -476073.47 | L123: =SUM('Financials Monthly'!AH123:AS123) -> -558884.16 | M123: =SUM('Financials Monthly'!AT123:BE123) -> -764924.56 | N123: =SUM('Financials Monthly'!BF123:BQ123) -> -769001.3
B124: (Increase) / decrease in other receivables | J124: =SUM('Financials Monthly'!J124:U124) -> 0 | K124: =SUM('Financials Monthly'!V124:AG124) -> 0 | L124: =SUM('Financials Monthly'!AH124:AS124) -> 0 | M124: =SUM('Financials Monthly'!AT124:BE124) -> 0 | N124: =SUM('Financials Monthly'!AU124:BF124) -> 0
B125: (Decrease) / increase in trade payables | J125: =SUM('Financials Monthly'!J125:U125) -> 111612.64 | K125: =SUM('Financials Monthly'!V125:AG125) -> 123090.95 | L125: =SUM('Financials Monthly'!AH125:AS125) -> 121928.55 | M125: =SUM('Financials Monthly'!AT125:BE125) -> 145712.36 | N125: =SUM('Financials Monthly'!BF125:BQ125) -> 173562.58
B126: (Decrease) / increase in other payables | J126: =SUM('Financials Monthly'!J126:U126) -> -10171.05 | K126: =SUM('Financials Monthly'!V126:AG126) -> 97459.75 | L126: =SUM('Financials Monthly'!AH126:AS126) -> 89866.6 | M126: =SUM('Financials Monthly'!AT126:BE126) -> 127550.4 | N126: =SUM('Financials Monthly'!BF126:BQ126) -> 118471.91
B127: Cash generated from operations | J127: =SUM('Financials Monthly'!J127:U127) -> -150350.8 | K127: =SUM('Financials Monthly'!V127:AG127) -> -37073.849 | L127: =SUM('Financials Monthly'!AH127:AS127) -> 2130024.1 | M127: =SUM('Financials Monthly'!AT127:BE127) -> 5277117.1 | N127: =SUM('Financials Monthly'!BF127:BQ127) -> 8483274
B130: CONSOLIDATED STATEMENT OF CASH FLOWS
B132: Cash generated from operations
B133: Interest paid | J133: =SUM('Financials Monthly'!J133:U133) -> 0 | K133: =SUM('Financials Monthly'!V133:AG133) -> 0 | L133: =SUM('Financials Monthly'!AH133:AS133) -> 0 | M133: =SUM('Financials Monthly'!AT133:BE133) -> 0 | N133: =SUM('Financials Monthly'!BF133:BQ133) -> 0
B134: Tax recovered / (paid) | J134: =SUM('Financials Monthly'!J134:U134) -> 0 | K134: =SUM('Financials Monthly'!V134:AG134) -> 0 | L134: =SUM('Financials Monthly'!AH134:AS134) -> 0 | M134: =SUM('Financials Monthly'!AT134:BE134) -> -582159.54 | N134: =SUM('Financials Monthly'!BF134:BQ134) -> -1380497.9
...

Sheet Financials Monthly
A1: Business 1 | J1: Act | K1: Act | L1: Act | M1: Act | N1: Act | O1: Act | P1: Act | Q1: Act
A2: Financials - Monthly | J2: =Timing!J2 -> 44986 | K2: =Timing!K2 -> 45017 | L2: =Timing!L2 -> 45047 | M2: =Timing!M2 -> 45078 | N2: =Timing!N2 -> 45108 | O2: =Timing!O2 -> 45139 | P2: =Timing!P2 -> 45170 | Q2: =Timing!Q2 -> 45200 | ... BQ2: =Timing!BQ2 -> 46784
J3: =Timing!J3 -> 45016 | K3: =Timing!K3 -> 45046 | L3: =Timing!L3 -> 45077 | M3: =Timing!M3 -> 45107 | N3: =Timing!N3 -> 45138 | O3: =Timing!O3 -> 45169 | P3: =Timing!P3 -> 45199 | Q3: =Timing!Q3 -> 45230 | ... BQ3: =Timing!BQ3 -> 46812
B4: PROFIT & LOSS
B6: Revenue
C7: One off Revenue | J7: =Revenue!J15 -> 36800 | K7: =Revenue!K15 -> 41550 | L7: =Revenue!L15 -> 5620 | M7: =Revenue!M15 -> 49673 | N7: =Revenue!N15 -> 46274 | O7: =Revenue!O15 -> 144234 | P7: =Revenue!P15 -> 107457 | Q7: =Revenue!Q15 -> 17450 | ... BQ7: =Revenue!BQ15 -> 151129
C8: Recurring Revenue | J8: =Revenue!J31 -> 0 | K8: =Revenue!K31 -> 6750 | L8: =Revenue!L31 -> 9000 | M8: =Revenue!M31 -> 12750 | N8: =Revenue!N31 -> 13500 | O8: =Revenue!O31 -> 13500 | P8: =Revenue!P31 -> 16275 | Q8: =Revenue!Q31 -> 17175 | ... BQ8: =Revenue!BQ31 -> 1366543.8
C9: Other Revenue
C10: Total | J10: =SUM(J7:J9) -> 36800 | K10: =SUM(K7:K9) -> 48300 | L10: =SUM(L7:L9) -> 14620 | M10: =SUM(M7:M9) -> 62423 | N10: =SUM(N7:N9) -> 59774 | O10: =SUM(O7:O9) -> 157734 | P10: =SUM(P7:P9) -> 123732 | Q10: =SUM(Q7:Q9) -> 34625 | ... BQ10: =SUM(BQ7:BQ9) -> 1517672.8
B12: Cost of sales
C13: Cost of Sales | J13: ='COS and Overheads'!J25 -> 19425 | K13: ='COS and Overheads'!K25 -> 7364 | L13: ='COS and Overheads'!L25 -> 28805 | M13: ='COS and Overheads'!M25 -> 25039 | N13: ='COS and Overheads'!N25 -> 31307 | O13: ='COS and Overheads'!O25 -> 103407 | P13: ='COS and Overheads'!P25 -> 64290 | Q13: ='COS and Overheads'!Q25 -> 10629 | ... BQ13: ='COS and Overheads'!BQ25 -> 493111
C14: Gross Wages and Salaries (COS) | J14: ='Wages and Salaries'!J21 -> 0 | K14: ='Wages and Salaries'!K21 -> 0 | L14: ='Wages and Salaries'!L21 -> 0 | M14: ='Wages and Salaries'!M21 -> 0 | N14: ='Wages and Salaries'!N21 -> 0 | O14: ='Wages and Salaries'!O21 -> 0 | P14: ='Wages and Salaries'!P21 -> 0 | Q14: ='Wages and Salaries'!Q21 -> 0 | ... BQ14: ='Wages and Salaries'!BQ21 -> 35833.333
C15: COS Ers NI | J15: ='Wages and Salaries'!J24 -> 0 | K15: ='Wages and Salaries'!K24 -> 0 | L15: ='Wages and Salaries'!L24 -> 0 | M15: ='Wages and Salaries'!M24 -> 0 | N15: ='Wages and Salaries'!N24 -> 0 | O15: ='Wages and Salaries'!O24 -> 0 | P15: ='Wages and Salaries'!P24 -> 0 | Q15: ='Wages and Salaries'!Q24 -> 0 | ... BQ15: ='Wages and Salaries'!BQ24 -> 5375
C16: COS Ers Pension | J16: ='Wages and Salaries'!J25 -> 0 | K16: ='Wages and Salaries'!K25 -> 0 | L16: ='Wages and Salaries'!L25 -> 0 | M16: ='Wages and Salaries'!M25 -> 0 | N16: ='Wages and Salaries'!N25 -> 0 | O16: ='Wages and Salaries'!O25 -> 0 | P16: ='Wages and Salaries'!P25 -> 0 | Q16: ='Wages and Salaries'!Q25 -> 0 | ... BQ16: ='Wages and Salaries'!BQ25 -> 1075
C17: Total | J17: =SUM(J13:J16) -> 19425 | K17: =SUM(K13:K16) -> 7364 | L17: =SUM(L13:L16) -> 28805 | M17: =SUM(M13:M16) -> 25039 | N17: =SUM(N13:N16) -> 31307 | O17: =SUM(O13:O16) -> 103407 | P17: =SUM(P13:P16) -> 64290 | Q17: =SUM(Q13:Q16) -> 10629 | ... BQ17: =SUM(BQ13:BQ16) -> 535394.33
B19: Gross profit | J19: =J10-J17 -> 17375 | K19: =K10-K17 -> 40936 | L19: =L10-L17 -> -14185 | M19: =M10-M17 -> 37384 | N19: =N10-N17 -> 28467 | O19: =O10-O17 -> 54327 | P19: =P10-P17 -> 59442 | Q19: =Q10-Q17 -> 23996 | ... BQ19: =BQ10-BQ17 -> 982278.42
C20: GP margin (%) | J20: =J19/J10 -> 0.47214674 | K20: =K19/K10 -> 0.84753623 | L20: =L19/L10 -> -0.97024624 | M20: =M19/M10 -> 0.59888182 | N20: =N19/N10 -> 0.47624385 | O20: =O19/O10 -> 0.34442162 | P20: =P19/P10 -> 0.48040927 | Q20: =Q19/Q10 -> 0.69302527 | ... BQ20: =BQ19/BQ10 -> 0.64722676
B22: Administrative expenses
C23: Gross wages and Salaries (Admin Expenses) | J23: ='Wages and Salaries'!J47 -> 5000 | K23: ='Wages and Salaries'!K47 -> 0 | L23: ='Wages and Salaries'!L47 -> 5000 | M23: ='Wages and Salaries'!M47 -> 5000 | N23: ='Wages and Salaries'!N47 -> 5000 | O23: ='Wages and Salaries'!O47 -> 5000 | P23: ='Wages and Salaries'!P47 -> 0 | Q23: ='Wages and Salaries'!Q47 -> 0 | ... BQ23: ='Wages and Salaries'!BQ47 -> 16250
C24: Wages and Salaries Er's NI | J24: ='Wages and Salaries'!J50 -> 0 | K24: ='Wages and Salaries'!K50 -> 0 | L24: ='Wages and Salaries'!L50 -> 0 | M24: ='Wages and Salaries'!M50 -> 0 | N24: ='Wages and Salaries'!N50 -> 0 | O24: ='Wages and Salaries'!O50 -> 0 | P24: ='Wages and Salaries'!P50 -> 0 | Q24: ='Wages and Salaries'!Q50 -> 0 | ... BQ24: ='Wages and Salaries'!BQ50 -> 2437.5
C25: Wages and Salaries Pension | J25: ='Wages and Salaries'!J51 -> 0 | K25: ='Wages and Salaries'!K51 -> 0 | L25: ='Wages and Salaries'!L51 -> 0 | M25: ='Wages and Salaries'!M51 -> 0 | N25: ='Wages and Salaries'!N51 -> 0 | O25: ='Wages and Salaries'!O51 -> 0 | P25: ='Wages and Salaries'!P51 -> 0 | Q25: ='Wages and Salaries'!Q51 -> 0 | ... BQ25: ='Wages and Salaries'!BQ51 -> 487.5
C26: Directors wages and Salaries (Incl Ni and Pension) | J26: ='Wages and Salaries'!J73+'Wages and Salaries'!J76+'Wages and Salaries'!J77 -> 0 | K26: ='Wages and Salaries'!K73+'Wages and Salaries'!K76+'Wages and Salaries'!K77 -> 0 | L26: ='Wages and Salaries'!L73+'Wages and Salaries'!L76+'Wages and Salaries'!L77 -> 0 | M26: ='Wages and Salaries'!M73+'Wages and Salaries'!M76+'Wages and Salaries'!M77 -> 0 | N26: ='Wages and Salaries'!N73+'Wages and Salaries'!N76+'Wages and Salaries'!N77 -> 0 | O26: ='Wages and Salaries'!O73+'Wages and Salaries'!O76+'Wages and Salaries'!O77 -> 0 | P26: ='Wages and Salaries'!P73+'Wages and Salaries'!P76+'Wages and Salaries'!P77 -> 0 | Q26: ='Wages and Salaries'!Q73+'Wages and Salaries'!Q76+'Wages and Salaries'!Q77 -> 0 | ... BQ26: ='Wages and Salaries'!BQ73+'Wages and Salaries'!BQ76+'Wages and Salaries'!BQ77 -> 43875
C27: Other Administrative Expenses | J27: ='COS and Overheads'!J46 -> 3252 | K27: ='COS and Overheads'!K46 -> 2398 | L27: ='COS and Overheads'!L46 -> 16019 | M27: ='COS and Overheads'!M46 -> 35404 | N27: ='COS and Overheads'!N46 -> 33427 | O27: ='COS and Overheads'!O46 -> 31398 | P27: ='COS and Overheads'!P46 -> 31033 | Q27: ='COS and Overheads'!Q46 -> 66424 | ... BQ27: ='COS and Overheads'!BQ46 -> 38309.25
C28: Total | J28: =SUM(J23:J27) -> 8252 | K28: =SUM(K23:K27) -> 2398 | L28: =SUM(L23:L27) -> 21019 | M28: =SUM(M23:M27) -> 40404 | N28: =SUM(N23:N27) -> 38427 | O28: =SUM(O23:O27) -> 36398 | P28: =SUM(P23:P27) -> 31033 | Q28: =SUM(Q23:Q27) -> 66424 | ... BQ28: =SUM(BQ23:BQ27) -> 101359.25
C30: EBITDA | J30: =J19-J28 -> 9123 | K30: =K19-K28 -> 38538 | L30: =L19-L28 -> -35204 | M30: =M19-M28 -> -3020 | N30: =N19-N28 -> -9960 | O30: =O19-O28 -> 17929 | P30: =P19-P28 -> 28409 | Q30: =Q19-Q28 -> -42428 | ... BQ30: =BQ19-BQ28 -> 880919.17
C31: EBITDA (%) | J31: =J30/J10 -> 0.24790761 | K31: =K30/K10 -> 0.7978882 | L31: =L30/L10 -> -2.4079343 | M31: =M30/M10 -> -0.048379604 | N31: =N30/N10 -> -0.16662763 | O31: =O30/O10 -> 0.11366605 | P31: =P30/P10 -> 0.22960107 | Q31: =Q30/Q10 -> -1.2253574 | ... BQ31: =BQ30/BQ10 -> 0.58044079
B33: Non-Operational Costs
C34: Exceptional Costs | J34: ='COS and Overheads'!J245 -> 0 | K34: ='COS and Overheads'!K245 -> 0 | L34: ='COS and Overheads'!L245 -> 0 | M34: ='COS and Overheads'!M245 -> 0 | N34: ='COS and Overheads'!N245 -> 0 | O34: ='COS and Overheads'!O245 -> 0 | P34: ='COS and Overheads'!P245 -> 0 | Q34: ='COS and Overheads'!Q245 -> 0 | ... BQ34: ='COS and Overheads'!BQ245 -> 0
C35: Investor Fees | J35: ='COS and Overheads'!J252 -> 0 | K35: ='COS and Overheads'!K252 -> 0 | L35: ='COS and Overheads'!L252 -> 0 | M35: ='COS and Overheads'!M252 -> 0 | N35: ='COS and Overheads'!N252 -> 0 | O35: ='COS and Overheads'!O252 -> 0 | P35: ='COS and Overheads'!P252 -> 0 | Q35: ='COS and Overheads'!Q252 -> 0 | ... BQ35: ='COS and Overheads'!BQ252 -> 0
C36: Adjusted EBITDA | J36: =J30-J34-J35 -> 9123 | K36: =K30-K34-K35 -> 38538 | L36: =L30-L34-L35 -> -35204 | M36: =M30-M34-M35 -> -3020 | N36: =N30-N34-N35 -> -9960 | O36: =O30-O34-O35 -> 17929 | P36: =P30-P34-P35 -> 28409 | Q36: =Q30-Q34-Q35 -> -42428 | ... BQ36: =BQ30-BQ34-BQ35 -> 880919.17
B38: Depreciation and amortisation
C39: Depreciation | J39: ='Fixed Assets'!J73 -> 0 | K39: ='Fixed Assets'!K73 -> 0 | L39: ='Fixed Assets'!L73 -> 0 | M39: ='Fixed Assets'!M73 -> 0 | N39: ='Fixed Assets'!N73 -> 0 | O39: ='Fixed Assets'!O73 -> 0 | P39: ='Fixed Assets'!P73 -> 0 | Q39: ='Fixed Assets'!Q73 -> 0 | ... BQ39: ='Fixed Assets'!BQ73 -> 32949.583
C40: Total | J40: =SUM(J39) -> 0 | K40: =SUM(K39) -> 0 | L40: =SUM(L39) -> 0 | M40: =SUM(M39) -> 0 | N40: =SUM(N39) -> 0 | O40: =SUM(O39) -> 0 | P40: =SUM(P39) -> 0 | Q40: =SUM(Q39) -> 0 | ... BQ40: =SUM(BQ39) -> 32949.583
C42: EBIT | J42: =J36-J40 -> 9123 | K42: =K36-K40 -> 38538 | L42: =L36-L40 -> -35204 | M42: =M36-M40 -> -3020 | N42: =N36-N40 -> -9960 | O42: =O36-O40 -> 17929 | P42: =P36-P40 -> 28409 | Q42: =Q36-Q40 -> -42428 | ... BQ42: =BQ36-BQ40 -> 847969.58
C43: EBIT (%)
B45: Interest chargeable and receivable
C47: Interest
C48: Total | J48: =J42-J47 -> 9123 | K48: =K42-K47 -> 38538 | L48: =L42-L47 -> -35204 | M48: =M42-M47 -> -3020 | N48: =N42-N47 -> -9960 | O48: =O42-O47 -> 17929 | P48: =P42-P47 -> 28409 | Q48: =Q42-Q47 -> -42428 | ... BQ48: =BQ42-BQ47 -> 847969.58
C50: Profit before Tax | J50: =J48 -> 9123 | K50: =K48 -> 38538 | L50: =L48 -> -35204 | M50: =M48 -> -3020 | N50: =N48 -> -9960 | O50: =O48 -> 17929 | P50: =P48 -> 28409 | Q50: =Q48 -> -42428 | ... BQ50: =BQ48 -> 847969.58
C52: Deferred Tax
C53: Tax Charge | J53: ='Corporation tax'!J34 -> 2280.75 | K53: ='Corporation tax'!K34 -> 9634.5 | L53: ='Corporation tax'!L34 -> -8801 | M53: ='Corporation tax'!M34 -> -755 | N53: ='Corporation tax'!N34 -> -2359.25 | O53: ='Corporation tax'!O34 -> 4351.5 | P53: ='Corporation tax'!P34 -> 7102.25 | Q53: ='Corporation tax'!Q34 -> -10607 | ... BQ53: ='Corporation tax'!BQ34 -> 211992.4
C55: Profit after Tax | J55: =J50-J52-J53 -> 6842.25 | K55: =K50-K52-K53 -> 28903.5 | L55: =L50-L52-L53 -> -26403 | M55: =M50-M52-M53 -> -2265 | N55: =N50-N52-N53 -> -7600.75 | O55: =O50-O52-O53 -> 13577.5 | P55: =P50-P52-P53 -> 21306.75 | Q55: =Q50-Q52-Q53 -> -31821 | ... BQ55: =BQ50-BQ52-BQ53 -> 635977.19
B57: Retained Earnings
C58: Retained Earnings b/f | J58: 0 | K58: =J61 -> 6842.25 | L58: =K61 -> 35745.75 | M58: =L61 -> 9342.75 | N58: =M61 -> 7077.75 | O58: =N61 -> -523 | P58: =O61 -> 13054.5 | Q58: =P61 -> 34361.25 | R58: =Q61 -> 2540.25 | ... BQ58: =BP61 -> 11700037
C59: Profit after tax | J59: =J55 -> 6842.25 | K59: =K55 -> 28903.5 | L59: =L55 -> -26403 | M59: =M55 -> -2265 | N59: =N55 -> -7600.75 | O59: =O55 -> 13577.5 | P59: =P55 -> 21306.75 | Q59: =Q55 -> -31821 | ... BQ59: =BQ55 -> 635977.19
C60: =[1]Funding!C$35 -> Dividends Paid
C61: Retained Earnings c/f | J61: =J58+J59-J60 -> 6842.25 | K61: =K58+K59-K60 -> 35745.75 | L61: =L58+L59-L60 -> 9342.75 | M61: =M58+M59-M60 -> 7077.75 | N61: =N58+N59-N60 -> -523 | O61: =O58+O59-O60 -> 13054.5 | P61: =P58+P59-P60 -> 34361.25 | Q61: =Q58+Q59-Q60 -> 2540.25 | ... BQ61: =BQ58+BQ59-BQ60 -> 12336014
B64: BALANCE SHEET
B66: Fixed Assets
C67: Intangibe NBV | J67: ='Fixed Assets'!J19 -> 0 | K67: ='Fixed Assets'!K19 -> 0 | L67: ='Fixed Assets'!L19 -> 0 | M67: ='Fixed Assets'!M19 -> 0 | N67: ='Fixed Assets'!N19 -> 0 | O67: ='Fixed Assets'!O19 -> 0 | P67: ='Fixed Assets'!P19 -> 0 | Q67: ='Fixed Assets'!Q19 -> 0 | ... BQ67: ='Fixed Assets'!BQ19 -> 69270.833
C68: Tangible NBV | J68: ='Fixed Assets'!J77 -> 0 | K68: ='Fixed Assets'!K77 -> 0 | L68: ='Fixed Assets'!L77 -> 0 | M68: ='Fixed Assets'!M77 -> 0 | N68: ='Fixed Assets'!N77 -> 0 | O68: ='Fixed Assets'!O77 -> 0 | P68: ='Fixed Assets'!P77 -> 0 | Q68: ='Fixed Assets'!Q77 -> 0 | ... BQ68: ='Fixed Assets'!BQ77 -> 828587.08
C69: Total fixed assets | J69: =SUM(J67:J68) -> 0 | K69: =SUM(K67:K68) -> 0 | L69: =SUM(L67:L68) -> 0 | M69: =SUM(M67:M68) -> 0 | N69: =SUM(N67:N68) -> 0 | O69: =SUM(O67:O68) -> 0 | P69: =SUM(P67:P68) -> 0 | Q69: =SUM(Q67:Q68) -> 0 | ... BQ69: =SUM(BQ67:BQ68) -> 897857.92
B71: Current assets
C72: Trade Debtors | J72: ='Working Capital'!J12 -> 0 | K72: ='Working Capital'!K12 -> 40500 | L72: ='Working Capital'!L12 -> 17545 | M72: ='Working Capital'!M12 -> 92453 | N72: ='Working Capital'!N12 -> 93407 | O72: ='Working Capital'!O12 -> 220509 | P72: ='Working Capital'!P12 -> 297259.6 | Q72: ='Working Capital'!Q12 -> 76688.8 | ... BQ72: ='Working Capital'!BQ12 -> 2664429.4
C73: Other Debtors | J73: ='Working Capital'!J25 -> 0 | K73: ='Working Capital'!K25 -> 0 | L73: ='Working Capital'!L25 -> 0 | M73: ='Working Capital'!M25 -> 0 | N73: ='Working Capital'!N25 -> 0 | O73: ='Working Capital'!O25 -> 0 | P73: ='Working Capital'!P25 -> 0 | Q73: ='Working Capital'!Q25 -> 0 | ... BQ73: ='Working Capital'!BQ25 -> 0
C74: Cash | J74: =J150 -> 15755 | K74: =K150 -> 25215 | L74: =L150 -> 14112 | M74: =M150 -> 9474 | N74: =N150 -> 3542.48 | O74: =O150 -> 8489.78 | P74: =P150 -> -53.19 | Q74: =Q150 -> 78547.25 | ... BQ74: =BQ150 -> 12023233
C75: Total current assets | J75: =SUM(J72:J74) -> 15755 | K75: =SUM(K72:K74) -> 65715 | L75: =SUM(L72:L74) -> 31657 | M75: =SUM(M72:M74) -> 101927 | N75: =SUM(N72:N74) -> 96949.48 | O75: =SUM(O72:O74) -> 228998.78 | P75: =SUM(P72:P74) -> 297206.41 | Q75: =SUM(Q72:Q74) -> 155236.05 | ... BQ75: =SUM(BQ72:BQ74) -> 14687663
C77: Total Assets | J77: =J69+J75 -> 15755 | K77: =K69+K75 -> 65715 | L77: =L69+L75 -> 31657 | M77: =M69+M75 -> 101927 | N77: =N69+N75 -> 96949.48 | O77: =O69+O75 -> 228998.78 | P77: =P69+P75 -> 297206.41 | Q77: =Q69+Q75 -> 155236.05 | ... BQ77: =BQ69+BQ75 -> 15585521
B79: Liabilities
C80: Trade Creditors | J80: ='Working Capital'!J37 -> 3171.6 | K80: ='Working Capital'!K37 -> 6628.8 | L80: ='Working Capital'!L37 -> 11647 | M80: ='Working Capital'!M37 -> 79497 | N80: ='Working Capital'!N37 -> 55824.5 | O80: ='Working Capital'!O37 -> 21864.6 | P80: ='Working Capital'!P37 -> 42040.64 | Q80: ='Working Capital'!Q37 -> 65244.18 | ... BQ80: ='Working Capital'!BQ37 -> 675907.07
C81: Other Creditors | J81: ='Working Capital'!J43 -> 0 | K81: ='Working Capital'!K43 -> 0 | L81: ='Working Capital'!L43 -> 0 | M81: ='Working Capital'!M43 -> 0 | N81: ='Working Capital'!N43 -> 0 | O81: ='Working Capital'!O43 -> 0 | P81: ='Working Capital'!P43 -> 0 | Q81: ='Working Capital'!Q43 -> 0 | ... BQ81: ='Working Capital'!BQ43 -> 0
C82: Corporate Tax | J82: ='Working Capital'!J50 -> 2280.75 | K82: ='Working Capital'!K50 -> 11915.25 | L82: ='Working Capital'!L50 -> 3114.25 | M82: ='Working Capital'!M50 -> 2359.25 | N82: ='Working Capital'!N50 -> 0 | O82: ='Working Capital'!O50 -> 4351.5 | P82: ='Working Capital'!P50 -> 11453.75 | Q82: ='Working Capital'!Q50 -> 846.75 | ... BQ82: ='Working Capital'!BQ50 -> 2150421.5
C83: Other Taxation and Social Security | J83: ='Working Capital'!J69 -> 3460.4 | K83: ='Working Capital'!K69 -> 11425.2 | L83: ='Working Capital'!L69 -> 7553 | M83: ='Working Capital'!M69 -> 12993 | N83: ='Working Capital'!N69 -> 17147.98 | O83: ='Working Capital'!O69 -> 46741.15 | P83: ='Working Capital'!P69 -> 52686.59 | Q83: ='Working Capital'!Q69 -> 32914.87 | ... BQ83: ='Working Capital'!BQ69 -> 423177.62
C84: Accruals and deferred Income | J84: ='Working Capital'!J75 -> 0 | K84: ='Working Capital'!K75 -> 0 | L84: ='Working Capital'!L75 -> 0 | M84: ='Working Capital'!M75 -> 0 | N84: ='Working Capital'!N75 -> 24500 | O84: ='Working Capital'!O75 -> 142987.03 | P84: ='Working Capital'!P75 -> 156664.18 | Q84: ='Working Capital'!Q75 -> 53690 | ... BQ84: ='Working Capital'!BQ75 -> 0
C85: Item 1
C86: Item 2
C87: Item 3
C88: Total current liabilities | J88: =SUM(J80:J87) -> 8912.75 | K88: =SUM(K80:K87) -> 29969.25 | L88: =SUM(L80:L87) -> 22314.25 | M88: =SUM(M80:M87) -> 94849.25 | N88: =SUM(N80:N87) -> 97472.48 | O88: =SUM(O80:O87) -> 215944.28 | P88: =SUM(P80:P87) -> 262845.16 | Q88: =SUM(Q80:Q87) -> 152695.8 | ... BQ88: =SUM(BQ80:BQ87) -> 3249506.2
C90: Non-current liabilities
C91: Long term loan
C92: Item 2
C93: Total non-current liabilities | J93: =SUM(J91:J92) -> 0 | K93: =SUM(K91:K92) -> 0 | L93: =SUM(L91:L92) -> 0 | M93: =SUM(M91:M92) -> 0 | N93: =SUM(N91:N92) -> 0 | O93: =SUM(O91:O92) -> 0 | P93: =SUM(P91:P92) -> 0 | Q93: =SUM(Q91:Q92) -> 0 | ... BQ93: =SUM(BQ91:BQ92) -> 0
C95: Provision for Liabiities | J95: ='Working Capital'!J81 -> 0 | K95: ='Working Capital'!K81 -> 0 | L95: ='Working Capital'!L81 -> 0 | M95: ='Working Capital'!M81 -> 0 | N95: ='Working Capital'!N81 -> 0 | O95: ='Working Capital'!O81 -> 0 | P95: ='Working Capital'!P81 -> 0 | Q95: ='Working Capital'!Q81 -> 0 | ... BQ95: ='Working Capital'!BQ81 -> 0
C97: Total Liabilities | J97: =J88+J93+J95 -> 8912.75 | K97: =K88+K93+K95 -> 29969.25 | L97: =L88+L93+L95 -> 22314.25 | M97: =M88+M93+M95 -> 94849.25 | N97: =N88+N93+N95 -> 97472.48 | O97: =O88+O93+O95 -> 215944.28 | P97: =P88+P93+P95 -> 262845.16 | Q97: =Q88+Q93+Q95 -> 152695.8 | ... BQ97: =BQ88+BQ93+BQ95 -> 3249506.2
C99: Net Assets / (Liabilities) | J99: =J77-J97 -> 6842.25 | K99: =K77-K97 -> 35745.75 | L99: =L77-L97 -> 9342.75 | M99: =M77-M97 -> 7077.75 | N99: =N77-N97 -> -523 | O99: =O77-O97 -> 13054.5 | P99: =P77-P97 -> 34361.25 | Q99: =Q77-Q97 -> 2540.25 | ... BQ99: =BQ77-BQ97 -> 12336014
C101: Share capital and reserves
C102: Ordinary Equity
C103: Retained Earnings | J103: =J61 -> 6842.25 | K103: =K61 -> 35745.75 | L103: =L61 -> 9342.75 | M103: =M61 -> 7077.75 | N103: =N61 -> -523 | O103: =O61 -> 13054.5 | P103: =P61 -> 34361.25 | Q103: =Q61 -> 2540.25 | ... BQ103: =BQ61 -> 12336014
C104: Item 3
C105: Total share capital and reserves | J105: =SUM(J102:J104) -> 6842.25 | K105: =SUM(K102:K104) -> 35745.75 | L105: =SUM(L102:L104) -> 9342.75 | M105: =SUM(M102:M104) -> 7077.75 | N105: =SUM(N102:N104) -> -523 | O105: =SUM(O102:O104) -> 13054.5 | P105: =SUM(P102:P104) -> 34361.25 | Q105: =SUM(Q102:Q104) -> 2540.25 | ... BQ105: =SUM(BQ102:BQ104) -> 12336014
C107: Balance Check | J107: =J105-J99 -> 0 | K107: =K105-K99 -> 0 | L107: =L105-L99 -> 0 | M107: =M105-M99 -> 0 | N107: =N105-N99 -> 0 | O107: =O105-O99 -> 0 | P107: =P105-P99 -> 0 | Q107: =Q105-Q99 -> -2.910383e-11 | ... BQ107: =BQ105-BQ99 -> 0
C108: Balance Check - Forecast
B110: CF
B112: CASH GENERATED FROM OPERATIONS
B114: Operating profit | J114: =J42 -> 9123 | K114: =K42 -> 38538 | L114: =L42 -> -35204 | M114: =M42 -> -3020 | N114: =N42 -> -9960 | O114: =O42 -> 17929 | P114: =P42 -> 28409 | Q114: =Q42 -> -42428 | ... BQ114: =BQ42 -> 847969.58
B116: Adjustments for:
B117: Depreciation charges | J117: =J39 -> 0 | K117: =K39 -> 0 | L117: =L39 -> 0 | M117: =M39 -> 0 | N117: =N39 -> 0 | O117: =O39 -> 0 | P117: =P39 -> 0 | Q117: =Q39 -> 0 | ... BQ117: =BQ39 -> 32949.583
B118: Amortisation charges | S118: ='Fixed Assets'!S15 -> 0 | T118: ='Fixed Assets'!T15 -> 364.58333 | U118: ='Fixed Assets'!U15 -> 729.16667 | V118: ='Fixed Assets'!V15 -> 1093.75 | W118: ='Fixed Assets'!W15 -> 1458.3333 | X118: ='Fixed Assets'!X15 -> 1458.3333 | Y118: ='Fixed Assets'!Y15 -> 1458.3333 | Z118: ='Fixed Assets'!Z15 -> 1458.3333 | ... BQ118: ='Fixed Assets'!BQ15 -> 1458.3333
B119: (Profit) / loss on disposal of fixed assets
B120: Operating cash flow before changes in working capital | J120: =SUM(J114:J119) -> 9123 | K120: =SUM(K114:K119) -> 38538 | L120: =SUM(L114:L119) -> -35204 | M120: =SUM(M114:M119) -> -3020 | N120: =SUM(N114:N119) -> -9960 | O120: =SUM(O114:O119) -> 17929 | P120: =SUM(P114:P119) -> 28409 | Q120: =SUM(Q114:Q119) -> -42428 | ... BQ120: =SUM(BQ114:BQ119) -> 882377.5
B122: Changes in working capital
B123: (Increase) / decrease in trade receivables | J123: =-J72-I72 -> 0 | K123: =-K72+J72 -> -40500 | L123: =-L72+K72 -> 22955 | M123: =-M72+L72 -> -74908 | N123: =-N72+M72 -> -954 | O123: =-O72+N72 -> -127102 | P123: =-P72+O72 -> -76750.6 | Q123: =-Q72+P72 -> 220570.8 | R123: =-R72+Q72 -> 5935.9481 | ... BQ123: =-BQ72+BP72 -> -62486.971
B124: (Increase) / decrease in other receivables | J124: =-J73-I73 -> 0 | K124: =-K73+J73 -> 0 | L124: =-L73+K73 -> 0 | M124: =-M73+L73 -> 0 | N124: =-N73+M73 -> 0 | O124: =-O73+N73 -> 0 | P124: =-P73+O73 -> 0 | Q124: =-Q73+P73 -> 0 | R124: =-R73+Q73 -> 0 | ... BQ124: =-BQ73+BP73 -> 0
B125: (Decrease) / increase in trade payables | J125: =J80-I80 -> 3171.6 | K125: =K80-J80 -> 3457.2 | L125: =L80-K80 -> 5018.2 | M125: =M80-L80 -> 67850 | N125: =N80-M80 -> -23672.5 | O125: =O80-N80 -> -33959.9 | P125: =P80-O80 -> 20176.04 | Q125: =Q80-P80 -> 23203.54 | ... BQ125: =BQ80-BP80 -> 11978.573
B126: (Decrease) / increase in other payables | J126: =J81+J83+J84-I81-I83-I84 -> 3460.4 | K126: =K81+K83+K84-J81-J83-J84 -> 7964.8 | L126: =L81+L83+L84-K81-K83-K84 -> -3872.2 | M126: =M81+M83+M84-L81-L83-L84 -> 5440 | N126: =N81+N83+N84-M81-M83-M84 -> 28654.98 | O126: =O81+O83+O84-N81-N83-N84 -> 148080.2 | P126: =P81+P83+P84-O81-O83-O84 -> 19622.59 | Q126: =Q81+Q83+Q84-P81-P83-P84 -> -122745.9 | ... BQ126: =BQ81+BQ83+BQ84-BP81-BP83-BP84 -> -333623.58
B127: Cash generated from operations | J127: =SUM(J120:J126) -> 15755 | K127: =SUM(K120:K126) -> 9460 | L127: =SUM(L120:L126) -> -11103 | M127: =SUM(M120:M126) -> -4638 | N127: =SUM(N120:N126) -> -5931.52 | O127: =SUM(O120:O126) -> 4947.3 | P127: =SUM(P120:P126) -> -8542.97 | Q127: =SUM(Q120:Q126) -> 78600.44 | ... BQ127: =SUM(BQ120:BQ126) -> 498245.52
B130: CONSOLIDATED STATEMENT OF CASH FLOWS
B132: Cash generated from operations
B133: Interest paid | J133: =-J47 -> 0 | K133: =-K47 -> 0 | L133: =-L47 -> 0 | M133: =-M47 -> 0 | N133: =-N47 -> 0 | O133: =-O47 -> 0 | P133: =-P47 -> 0 | Q133: =-Q47 -> 0 | ... BQ133: =-BQ47 -> 0
B134: Tax recovered / (paid) | J134: ='Working Capital'!J49 -> 0 | K134: ='Working Capital'!K49 -> 0 | L134: ='Working Capital'!L49 -> 0 | M134: ='Working Capital'!M49 -> 0 | N134: ='Working Capital'!N49 -> 0 | O134: ='Working Capital'!O49 -> 0 | P134: ='Working Capital'!P49 -> 0 | Q134: ='Working Capital'!Q49 -> 0 | ... BQ134: ='Working Capital'!BQ49 -> 0
...

Sheet Timing
A1: Business 1
A2: Timing | J2: 44986 | K2: =EDATE(J2,1) -> 45017 | L2: =EDATE(K2,1) -> 45047 | M2: =EDATE(L2,1) -> 45078 | N2: =EDATE(M2,1) -> 45108 | O2: =EDATE(N2,1) -> 45139 | P2: =EDATE(O2,1) -> 45170 | Q2: =EDATE(P2,1) -> 45200 | R2: =EDATE(Q2,1) -> 45231 | ... BQ2: =EDATE(BP2,1) -> 46784
J3: =IF(EOMONTH(J2,0)>[1]Scen!$F$12,0,EOMONTH(J2,0)) -> 45016 | K3: =EDATE(J3,1) -> 45046 | L3: =IF(EOMONTH(L2,0)>[1]Scen!$F$12,0,EOMONTH(L2,0)) -> 45077 | M3: =IF(EOMONTH(M2,0)>[1]Scen!$F$12,0,EOMONTH(M2,0)) -> 45107 | N3: =IF(EOMONTH(N2,0)>[1]Scen!$F$12,0,EOMONTH(N2,0)) -> 45138 | O3: =IF(EOMONTH(O2,0)>[1]Scen!$F$12,0,EOMONTH(O2,0)) -> 45169 | P3: =IF(EOMONTH(P2,0)>[1]Scen!$F$12,0,EOMONTH(P2,0)) -> 45199 | Q3: =IF(EOMONTH(Q2,0)>[1]Scen!$F$12,0,EOMONTH(Q2,0)) -> 45230 | R3: =IF(EOMONTH(R2,0)>[1]Scen!$F$12,0,EOMONTH(R2,0)) -> 45260 | S3: =IF(EOMONTH(S2,0)>[1]Scen!$F$12,0,EOMONTH(S2,0)) -> 45291 | ... BQ3: =IF(EOMONTH(BQ2,0)>[1]Scen!$F$12,0,EOMONTH(BQ2,0)) -> 46812

Sheet Inputs
A1: Business 1
A2: Inputs | J2: =Timing!J2 -> 44986 | K2: =Timing!K2 -> 45017 | L2: =Timing!L2 -> 45047 | M2: =Timing!M2 -> 45078 | N2: =Timing!N2 -> 45108 | O2: =Timing!O2 -> 45139 | P2: =Timing!P2 -> 45170 | Q2: =Timing!Q2 -> 45200 | ... BQ2: =Timing!BQ2 -> 46784
J3: =Timing!J3 -> 45016 | K3: =Timing!K3 -> 45046 | L3: =Timing!L3 -> 45077 | M3: =Timing!M3 -> 45107 | N3: =Timing!N3 -> 45138 | O3: =Timing!O3 -> 45169 | P3: =Timing!P3 -> 45199 | Q3: =Timing!Q3 -> 45230 | ... BQ3: =Timing!BQ3 -> 46812
B7: Output Vat | J7: 0.2 | K7: 0.2 | L7: 0.2 | M7: 0.2 | N7: 0.2 | O7: 0.2 | P7: 0.2 | Q7: 0.2 | R7: 0.2 | S7: 0.2 | T7: 0.2 | U7: 0.2 | V7: 0.2 | W7: 0.2 | X7: 0.2 | Y7: 0.2 | Z7: 0.2 | AA7: 0.2 | AB7: 0.2 | AC7: 0.2 | AD7: 0.2 | AE7: 0.2 | AF7: 0.2 | AG7: 0.2 | AH7: 0.2 | AI7: 0.2 | AJ7: 0.2 | AK7: 0.2 | AL7: 0.2 | AM7: 0.2 | AN7: 0.2 | AO7: 0.2 | AP7: 0.2 | AQ7: 0.2 | AR7: 0.2 | AS7: 0.2 | AT7: 0.2 | AU7: 0.2 | AV7: 0.2 | AW7: 0.2 | AX7: 0.2 | AY7: 0.2 | AZ7: 0.2 | BA7: 0.2 | BB7: 0.2 | BC7: 0.2 | BD7: 0.2 | BE7: 0.2 | BF7: 0.2 | BG7: 0.2 | BH7: 0.2 | BI7: 0.2 | BJ7: 0.2 | BK7: 0.2 | BL7: 0.2 | BM7: 0.2 | BN7: 0.2 | BO7: 0.2 | BP7: 0.2 | BQ7: 0.2
B8: Input Vat | J8: 0.2 | K8: 0.2 | L8: 0.2 | M8: 0.2 | N8: 0.2 | O8: 0.2 | P8: 0.2 | Q8: 0.2 | R8: 0.2 | S8: 0.2 | T8: 0.2 | U8: 0.2 | V8: 0.2 | W8: 0.2 | X8: 0.2 | Y8: 0.2 | Z8: 0.2 | AA8: 0.2 | AB8: 0.2 | AC8: 0.2 | AD8: 0.2 | AE8: 0.2 | AF8: 0.2 | AG8: 0.2 | AH8: 0.2 | AI8: 0.2 | AJ8: 0.2 | AK8: 0.2 | AL8: 0.2 | AM8: 0.2 | AN8: 0.2 | AO8: 0.2 | AP8: 0.2 | AQ8: 0.2 | AR8: 0.2 | AS8: 0.2 | AT8: 0.2 | AU8: 0.2 | AV8: 0.2 | AW8: 0.2 | AX8: 0.2 | AY8: 0.2 | AZ8: 0.2 | BA8: 0.2 | BB8: 0.2 | BC8: 0.2 | BD8: 0.2 | BE8: 0.2 | BF8: 0.2 | BG8: 0.2 | BH8: 0.2 | BI8: 0.2 | BJ8: 0.2 | BK8: 0.2 | BL8: 0.2 | BM8: 0.2 | BN8: 0.2 | BO8: 0.2 | BP8: 0.2 | BQ8: 0.2
B9: Trade Debtor Days | J9: 45 | K9: 45 | L9: 45 | M9: 45 | N9: 45 | O9: 45 | P9: 45 | Q9: 45 | R9: 45 | S9: 45 | T9: 45 | U9: 45 | V9: 45 | W9: 45 | X9: 45 | Y9: 45 | Z9: 45 | AA9: 45 | AB9: 45 | AC9: 45 | AD9: 45 | AE9: 45 | AF9: 45 | AG9: 45 | AH9: 45 | AI9: 45 | AJ9: 45 | AK9: 45 | AL9: 45 | AM9: 45 | AN9: 45 | AO9: 45 | AP9: 45 | AQ9: 45 | AR9: 45 | AS9: 45 | AT9: 45 | AU9: 45 | AV9: 45 | AW9: 45 | AX9: 45 | AY9: 45 | AZ9: 45 | BA9: 45 | BB9: 45 | BC9: 45 | BD9: 45 | BE9: 45 | BF9: 45 | BG9: 45 | BH9: 45 | BI9: 45 | BJ9: 45 | BK9: 45 | BL9: 45 | BM9: 45 | BN9: 45 | BO9: 45 | BP9: 45 | BQ9: 45
B10: Trade Creditor Days | J10: 30 | K10: 30 | L10: 30 | M10: 30 | N10: 30 | O10: 30 | P10: 30 | Q10: 30 | R10: 30 | S10: 30 | T10: 30 | U10: 30 | V10: 30 | W10: 30 | X10: 30 | Y10: 30 | Z10: 30 | AA10: 30 | AB10: 30 | AC10: 30 | AD10: 30 | AE10: 30 | AF10: 30 | AG10: 30 | AH10: 30 | AI10: 30 | AJ10: 30 | AK10: 30 | AL10: 30 | AM10: 30 | AN10: 30 | AO10: 30 | AP10: 30 | AQ10: 30 | AR10: 30 | AS10: 30 | AT10: 30 | AU10: 30 | AV10: 30 | AW10: 30 | AX10: 30 | AY10: 30 | AZ10: 30 | BA10: 30 | BB10: 30 | BC10: 30 | BD10: 30 | BE10: 30 | BF10: 30 | BG10: 30 | BH10: 30 | BI10: 30 | BJ10: 30 | BK10: 30 | BL10: 30 | BM10: 30 | BN10: 30 | BO10: 30 | BP10: 30 | BQ10: 30
B12: Wages and Salaries PAYE | J12: 0.25 | K12: 0.25 | L12: 0.25 | M12: 0.25 | N12: 0.25 | O12: 0.25 | P12: 0.25 | Q12: 0.25 | R12: 0.25 | S12: 0.25 | T12: 0.25 | U12: 0.25 | V12: 0.25 | W12: 0.25 | X12: 0.25 | Y12: 0.25 | Z12: 0.25 | AA12: 0.25 | AB12: 0.25 | AC12: 0.25 | AD12: 0.25 | AE12: 0.25 | AF12: 0.25 | AG12: 0.25 | AH12: 0.25 | AI12: 0.25 | AJ12: 0.25 | AK12: 0.25 | AL12: 0.25 | AM12: 0.25 | AN12: 0.25 | AO12: 0.25 | AP12: 0.25 | AQ12: 0.25 | AR12: 0.25 | AS12: 0.25 | AT12: 0.25 | AU12: 0.25 | AV12: 0.25 | AW12: 0.25 | AX12: 0.25 | AY12: 0.25 | AZ12: 0.25 | BA12: 0.25 | BB12: 0.25 | BC12: 0.25 | BD12: 0.25 | BE12: 0.25 | BF12: 0.25 | BG12: 0.25 | BH12: 0.25 | BI12: 0.25 | BJ12: 0.25 | BK12: 0.25 | BL12: 0.25 | BM12: 0.25 | BN12: 0.25 | BO12: 0.25 | BP12: 0.25 | BQ12: 0.25
B13: Wages and Salaries Ees NIC | J13: 0.11 | K13: 0.11 | L13: 0.11 | M13: 0.11 | N13: 0.11 | O13: 0.11 | P13: 0.11 | Q13: 0.11 | R13: 0.11 | S13: 0.11 | T13: 0.11 | U13: 0.11 | V13: 0.11 | W13: 0.11 | X13: 0.11 | Y13: 0.11 | Z13: 0.11 | AA13: 0.11 | AB13: 0.11 | AC13: 0.11 | AD13: 0.11 | AE13: 0.11 | AF13: 0.11 | AG13: 0.11 | AH13: 0.11 | AI13: 0.11 | AJ13: 0.11 | AK13: 0.11 | AL13: 0.11 | AM13: 0.11 | AN13: 0.11 | AO13: 0.11 | AP13: 0.11 | AQ13: 0.11 | AR13: 0.11 | AS13: 0.11 | AT13: 0.11 | AU13: 0.11 | AV13: 0.11 | AW13: 0.11 | AX13: 0.11 | AY13: 0.11 | AZ13: 0.11 | BA13: 0.11 | BB13: 0.11 | BC13: 0.11 | BD13: 0.11 | BE13: 0.11 | BF13: 0.11 | BG13: 0.11 | BH13: 0.11 | BI13: 0.11 | BJ13: 0.11 | BK13: 0.11 | BL13: 0.11 | BM13: 0.11 | BN13: 0.11 | BO13: 0.11 | BP13: 0.11 | BQ13: 0.11
B14: Wages and Salaries Ers NIC | J14: 0.15 | K14: 0.15 | L14: 0.15 | M14: 0.15 | N14: 0.15 | O14: 0.15 | P14: 0.15 | Q14: 0.15 | R14: 0.15 | S14: 0.15 | T14: 0.15 | U14: 0.15 | V14: 0.15 | W14: 0.15 | X14: 0.15 | Y14: 0.15 | Z14: 0.15 | AA14: 0.15 | AB14: 0.15 | AC14: 0.15 | AD14: 0.15 | AE14: 0.15 | AF14: 0.15 | AG14: 0.15 | AH14: 0.15 | AI14: 0.15 | AJ14: 0.15 | AK14: 0.15 | AL14: 0.15 | AM14: 0.15 | AN14: 0.15 | AO14: 0.15 | AP14: 0.15 | AQ14: 0.15 | AR14: 0.15 | AS14: 0.15 | AT14: 0.15 | AU14: 0.15 | AV14: 0.15 | AW14: 0.15 | AX14: 0.15 | AY14: 0.15 | AZ14: 0.15 | BA14: 0.15 | BB14: 0.15 | BC14: 0.15 | BD14: 0.15 | BE14: 0.15 | BF14: 0.15 | BG14: 0.15 | BH14: 0.15 | BI14: 0.15 | BJ14: 0.15 | BK14: 0.15 | BL14: 0.15 | BM14: 0.15 | BN14: 0.15 | BO14: 0.15 | BP14: 0.15 | BQ14: 0.15
B15: Pension Contribution | J15: 0.03 | K15: 0.03 | L15: 0.03 | M15: 0.03 | N15: 0.03 | O15: 0.03 | P15: 0.03 | Q15: 0.03 | R15: 0.03 | S15: 0.03 | T15: 0.03 | U15: 0.03 | V15: 0.03 | W15: 0.03 | X15: 0.03 | Y15: 0.03 | Z15: 0.03 | AA15: 0.03 | AB15: 0.03 | AC15: 0.03 | AD15: 0.03 | AE15: 0.03 | AF15: 0.03 | AG15: 0.03 | AH15: 0.03 | AI15: 0.03 | AJ15: 0.03 | AK15: 0.03 | AL15: 0.03 | AM15: 0.03 | AN15: 0.03 | AO15: 0.03 | AP15: 0.03 | AQ15: 0.03 | AR15: 0.03 | AS15: 0.03 | AT15: 0.03 | AU15: 0.03 | AV15: 0.03 | AW15: 0.03 | AX15: 0.03 | AY15: 0.03 | AZ15: 0.03 | BA15: 0.03 | BB15: 0.03 | BC15: 0.03 | BD15: 0.03 | BE15: 0.03 | BF15: 0.03 | BG15: 0.03 | BH15: 0.03 | BI15: 0.03 | BJ15: 0.03 | BK15: 0.03 | BL15: 0.03 | BM15: 0.03 | BN15: 0.03 | BO15: 0.03 | BP15: 0.03 | BQ15: 0.03
B17: Directors PAYE | J17: 0.35 | K17: 0.35 | L17: 0.35 | M17: 0.35 | N17: 0.35 | O17: 0.35 | P17: 0.35 | Q17: 0.35 | R17: 0.35 | S17: 0.35 | T17: 0.35 | U17: 0.35 | V17: 0.35 | W17: 0.35 | X17: 0.35 | Y17: 0.35 | Z17: 0.35 | AA17: 0.35 | AB17: 0.35 | AC17: 0.35 | AD17: 0.35 | AE17: 0.35 | AF17: 0.35 | AG17: 0.35 | AH17: 0.35 | AI17: 0.35 | AJ17: 0.35 | AK17: 0.35 | AL17: 0.35 | AM17: 0.35 | AN17: 0.35 | AO17: 0.35 | AP17: 0.35 | AQ17: 0.35 | AR17: 0.35 | AS17: 0.35 | AT17: 0.35 | AU17: 0.35 | AV17: 0.35 | AW17: 0.35 | AX17: 0.35 | AY17: 0.35 | AZ17: 0.35 | BA17: 0.35 | BB17: 0.35 | BC17: 0.35 | BD17: 0.35 | BE17: 0.35 | BF17: 0.35 | BG17: 0.35 | BH17: 0.35 | BI17: 0.35 | BJ17: 0.35 | BK17: 0.35 | BL17: 0.35 | BM17: 0.35 | BN17: 0.35 | BO17: 0.35 | BP17: 0.35 | BQ17: 0.35
B18: Directors Ees NIC | J18: 0.05 | K18: 0.05 | L18: 0.05 | M18: 0.05 | N18: 0.05 | O18: 0.05 | P18: 0.05 | Q18: 0.05 | R18: 0.05 | S18: 0.05 | T18: 0.05 | U18: 0.05 | V18: 0.05 | W18: 0.05 | X18: 0.05 | Y18: 0.05 | Z18: 0.05 | AA18: 0.05 | AB18: 0.05 | AC18: 0.05 | AD18: 0.05 | AE18: 0.05 | AF18: 0.05 | AG18: 0.05 | AH18: 0.05 | AI18: 0.05 | AJ18: 0.05 | AK18: 0.05 | AL18: 0.05 | AM18: 0.05 | AN18: 0.05 | AO18: 0.05 | AP18: 0.05 | AQ18: 0.05 | AR18: 0.05 | AS18: 0.05 | AT18: 0.05 | AU18: 0.05 | AV18: 0.05 | AW18: 0.05 | AX18: 0.05 | AY18: 0.05 | AZ18: 0.05 | BA18: 0.05 | BB18: 0.05 | BC18: 0.05 | BD18: 0.05 | BE18: 0.05 | BF18: 0.05 | BG18: 0.05 | BH18: 0.05 | BI18: 0.05 | BJ18: 0.05 | BK18: 0.05 | BL18: 0.05 | BM18: 0.05 | BN18: 0.05 | BO18: 0.05 | BP18: 0.05 | BQ18: 0.05
B19: Directors Ers Nic | J19: 0.14 | K19: 0.14 | L19: 0.14 | M19: 0.14 | N19: 0.14 | O19: 0.14 | P19: 0.14 | Q19: 0.14 | R19: 0.14 | S19: 0.14 | T19: 0.14 | U19: 0.14 | V19: 0.14 | W19: 0.14 | X19: 0.14 | Y19: 0.14 | Z19: 0.14 | AA19: 0.14 | AB19: 0.14 | AC19: 0.14 | AD19: 0.14 | AE19: 0.14 | AF19: 0.14 | AG19: 0.14 | AH19: 0.14 | AI19: 0.14 | AJ19: 0.14 | AK19: 0.14 | AL19: 0.14 | AM19: 0.14 | AN19: 0.14 | AO19: 0.14 | AP19: 0.14 | AQ19: 0.14 | AR19: 0.14 | AS19: 0.14 | AT19: 0.14 | AU19: 0.14 | AV19: 0.14 | AW19: 0.14 | AX19: 0.14 | AY19: 0.14 | AZ19: 0.14 | BA19: 0.14 | BB19: 0.14 | BC19: 0.14 | BD19: 0.14 | BE19: 0.14 | BF19: 0.14 | BG19: 0.14 | BH19: 0.14 | BI19: 0.14 | BJ19: 0.14 | BK19: 0.14 | BL19: 0.14 | BM19: 0.14 | BN19: 0.14 | BO19: 0.14 | BP19: 0.14 | BQ19: 0.14
B20: Directors Pension | J20: 0.03 | K20: 0.03 | L20: 0.03 | M20: 0.03 | N20: 0.03 | O20: 0.03 | P20: 0.03 | Q20: 0.03 | R20: 0.03 | S20: 0.03 | T20: 0.03 | U20: 0.03 | V20: 0.03 | W20: 0.03 | X20: 0.03 | Y20: 0.03 | Z20: 0.03 | AA20: 0.03 | AB20: 0.03 | AC20: 0.03 | AD20: 0.03 | AE20: 0.03 | AF20: 0.03 | AG20: 0.03 | AH20: 0.03 | AI20: 0.03 | AJ20: 0.03 | AK20: 0.03 | AL20: 0.03 | AM20: 0.03 | AN20: 0.03 | AO20: 0.03 | AP20: 0.03 | AQ20: 0.03 | AR20: 0.03 | AS20: 0.03 | AT20: 0.03 | AU20: 0.03 | AV20: 0.03 | AW20: 0.03 | AX20: 0.03 | AY20: 0.03 | AZ20: 0.03 | BA20: 0.03 | BB20: 0.03 | BC20: 0.03 | BD20: 0.03 | BE20: 0.03 | BF20: 0.03 | BG20: 0.03 | BH20: 0.03 | BI20: 0.03 | BJ20: 0.03 | BK20: 0.03 | BL20: 0.03 | BM20: 0.03 | BN20: 0.03 | BO20: 0.03 | BP20: 0.03 | BQ20: 0.03
... B27: Corporation Tax | J27: 0.25 | K27: 0.25 | L27: 0.25 | M27: 0.25 | N27: 0.25 | O27: 0.25 | P27: 0.25 | Q27: 0.25 | R27: 0.25 | S27: 0.25 | T27: 0.25 | U27: 0.25 | V27: 0.25 | W27: 0.25 | X27: 0.25 | Y27: 0.25 | Z27: 0.25 | AA27: 0.25 | AB27: 0.25 | AC27: 0.25 | AD27: 0.25 | AE27: 0.25 | AF27: 0.25 | AG27: 0.25 | AH27: 0.25 | AI27: 0.25 | AJ27: 0.25 | AK27: 0.25 | AL27: 0.25 | AM27: 0.25 | AN27: 0.25 | AO27: 0.25 | AP27: 0.25 | AQ27: 0.25 | AR27: 0.25 | AS27: 0.25 | AT27: 0.25 | AU27: 0.25 | AV27: 0.25 | AW27: 0.25 | AX27: 0.25 | AY27: 0.25 | AZ27: 0.25 | BA27: 0.25 | BB27: 0.25 | BC27: 0.25 | BD27: 0.25 | BE27: 0.25 | BF27: 0.25 | BG27: 0.25 | BH27: 0.25 | BI27: 0.25 | BJ27: 0.25 | BK27: 0.25 | BL27: 0.25 | BM27: 0.25 | BN27: 0.25 | BO27: 0.25 | BP27: 0.25 | BQ27: 0.25
B29: Sales Forecast
B31: ISP Funds Capex
B32: New Screens | J32: 30 | K32: 30 | M32: 30 | N32: 30 | O32: 30 | P32: 60 | Q32: 0 | R32: 0 | S32: 0 | T32: 0 | U32: 0 | V32: 0 | W32: 30 | X32: 30 | Y32: 30 | Z32: 30 | AA32: 30 | AB32: 30 | AC32: 30 | AD32: 30 | AE32: 30 | AF32: 30 | AG32: 30 | AH32: 36 | AI32: 36 | AJ32: 36 | AK32: 36 | AL32: 36 | AM32: 36 | AN32: 36 | AO32: 36 | AP32: 36 | AQ32: 36 | AR32: 36 | AS32: 36 | AT32: 43 | AU32: 43 | AV32: 43 | AW32: 43 | AX32: 43 | AY32: 43 | AZ32: 43 | BA32: 43 | BB32: 43 | BC32: 43 | BD32: 43 | BE32: 43 | BF32: 52 | BG32: 52 | BH32: 52 | BI32: 52 | BJ32: 52 | BK32: 52 | BL32: 52 | BM32: 52 | BN32: 52 | BO32: 52 | BP32: 52 | BQ32: 52
B33: Live Screens | J33: 90 | K33: =J33+K32 -> 120 | L33: =K33+L32 -> 120 | M33: =L33+M32 -> 150 | N33: =M33+N32 -> 180 | O33: 240 | P33: =O33+P32 -> 300 | Q33: =P33+Q32 -> 300 | R33: =Q33+R32 -> 300 | S33: =R33+S32 -> 300 | T33: =S33+T32 -> 300 | U33: =T33+U32 -> 300 | V33: =U33+V32 -> 300 | W33: =V33+W32 -> 330 | ... BQ33: =BP33+BQ32 -> 2202
B35: SCCI
B36: New Screens | J36: 0 | K36: 0 | L36: 0 | M36: 0 | N36: 0 | O36: 0 | P36: 0 | Q36: 0 | R36: 0 | S36: 0 | T36: 20 | U36: 20 | V36: 20 | W36: 20 | X36: 20 | Y36: 20 | Z36: 20 | AA36: 20 | AB36: 20 | AC36: 20 | AD36: 20 | AE36: 20 | AF36: 20 | AG36: 20 | AH36: 24 | AI36: 24 | AJ36: 24 | AK36: 24 | AL36: 24 | AM36: 24 | AN36: 24 | AO36: 24 | AP36: 24 | AQ36: 24 | AR36: 24 | AS36: 24 | AT36: 28 | AU36: 28 | AV36: 28 | AW36: 28 | AX36: 28 | AY36: 28 | AZ36: 28 | BA36: 28 | BB36: 28 | BC36: 28 | BD36: 28 | BE36: 28 | BF36: 32 | BG36: 32 | BH36: 32 | BI36: 32 | BJ36: 32 | BK36: 32 | BL36: 32 | BM36: 32 | BN36: 32 | BO36: 32 | BP36: 32 | BQ36: 32
B37: Live Screens | J37: 0 | K37: =J37+K36 -> 0 | L37: =K37+L36 -> 0 | M37: =L37+M36 -> 0 | N37: =M37+N36 -> 0 | O37: =N37+O36 -> 0 | P37: =O37+P36 -> 0 | Q37: =P37+Q36 -> 0 | R37: =Q37+R36 -> 0 | ... BQ37: =BP37+BQ36 -> 1288
B39: ISP Funds £0 Capex
B40: New Screens | J40: 0 | K40: 0 | L40: 0 | M40: 0 | N40: 0 | O40: 0 | P40: 0 | Q40: 0 | R40: 0 | S40: 2 | T40: 10 | U40: 10 | V40: 10 | W40: 20 | X40: 20 | Y40: 20 | Z40: 20 | AA40: 20 | AB40: 20 | AC40: 20 | AD40: 20 | AE40: 20 | AF40: 20 | AG40: 20 | AH40: 24 | AI40: 24 | AJ40: 24 | AK40: 24 | AL40: 24 | AM40: 24 | AN40: 24 | AO40: 24 | AP40: 24 | AQ40: 24 | AR40: 24 | AS40: 24 | AT40: 28 | AU40: 28 | AV40: 28 | AW40: 28 | AX40: 28 | AY40: 28 | AZ40: 28 | BA40: 28 | BB40: 28 | BC40: 28 | BD40: 28 | BE40: 28 | BF40: 32 | BG40: 32 | BH40: 32 | BI40: 32 | BJ40: 32 | BK40: 32 | BL40: 32 | BM40: 32 | BN40: 32 | BO40: 32 | BP40: 32 | BQ40: 32
B41: Live Screens | J41: 0 | K41: =J41+K40 -> 0 | L41: =K41+L40 -> 0 | M41: =L41+M40 -> 0 | N41: =M41+N40 -> 0 | O41: =N41+O40 -> 0 | P41: =O41+P40 -> 0 | Q41: =P41+Q40 -> 0 | R41: =Q41+R40 -> 0 | ... BQ41: =BP41+BQ40 -> 1260
B43: Other
B44: New Screens | J44: 0 | K44: 0 | L44: 0 | M44: 0 | N44: 0 | O44: 0 | P44: 0 | Q44: 0 | R44: 0 | S44: 0 | T44: 0 | U44: 0 | V44: 0 | W44: 0 | X44: 0 | Y44: 0 | Z44: 0 | AA44: 0 | AB44: 0 | AC44: 0 | AD44: 0 | AE44: 0 | AF44: 0 | AG44: 0 | AH44: 0 | AI44: 0 | AJ44: 0 | AK44: 0 | AL44: 0 | AM44: 0 | AN44: 0 | AO44: 0 | AP44: 0 | AQ44: 0 | AR44: 0 | AS44: 0 | AT44: 0 | AU44: 0 | AV44: 0 | AW44: 0 | AX44: 0 | AY44: 0 | AZ44: 0 | BA44: 0 | BB44: 0 | BC44: 0 | BD44: 0 | BE44: 0 | BF44: 0 | BG44: 0 | BH44: 0 | BI44: 0 | BJ44: 0 | BK44: 0 | BL44: 0 | BM44: 0 | BN44: 0 | BO44: 0 | BP44: 0 | BQ44: 0
B45: Live Screens | J45: 0 | K45: =J45+K44 -> 0 | L45: =K45+L44 -> 0 | M45: =L45+M44 -> 0 | N45: =M45+N44 -> 0 | O45: =N45+O44 -> 0 | P45: =O45+P44 -> 0 | Q45: =P45+Q44 -> 0 | R45: =Q45+R44 -> 0 | ... BQ45: =BP45+BQ44 -> 0
B49: Sales Assumptions
B50: ISP Funds Capex - one off revenue
B51: Revenue - new screens | J51: 1000 | K51: 1000 | L51: 1000 | M51: 1000 | N51: 1000 | O51: 1000 | P51: 1000 | Q51: 1000 | R51: 1000 | S51: 1000 | T51: 1000 | U51: 1000 | V51: 1000 | W51: 1000 | X51: 1000 | Y51: 1000 | Z51: 1000 | AA51: 1000 | AB51: 1000 | AC51: 1000 | AD51: 1000 | AE51: 1000 | AF51: 1000 | AG51: 1000 | AH51: =AG51+10%*AG51 -> 1100 | AI51: =AH51 -> 1100 | AJ51: =AI51 -> 1100 | AK51: =AJ51 -> 1100 | AL51: =AK51 -> 1100 | AM51: =AL51 -> 1100 | AN51: =AM51 -> 1100 | AO51: =AN51 -> 1100 | AP51: =AO51 -> 1100 | ... AS51: =AR51 -> 1100 | AT51: =AS51+10%*AS51 -> 1210 | AU51: =AT51 -> 1210 | AV51: =AU51 -> 1210 | AW51: =AV51 -> 1210 | AX51: =AW51 -> 1210 | AY51: =AX51 -> 1210 | AZ51: =AY51 -> 1210 | BA51: =AZ51 -> 1210 | BB51: =BA51 -> 1210 | ... BQ51: =BP51 -> 1210
B52: Revenue - set up and installation | J52: 750 | K52: 750 | L52: 750 | M52: 750 | N52: 750 | O52: 750 | P52: 750 | Q52: 750 | R52: 750 | S52: 750 | T52: 750 | U52: 750 | V52: 750 | W52: 750 | X52: 750 | Y52: 750 | Z52: 750 | AA52: 750 | AB52: 750 | AC52: 750 | AD52: 750 | AE52: 750 | AF52: 750 | AG52: 750 | AH52: =AG52+10%*AG52 -> 825 | AI52: =AH52 -> 825 | AJ52: =AI52 -> 825 | AK52: =AJ52 -> 825 | AL52: =AK52 -> 825 | AM52: =AL52 -> 825 | AN52: =AM52 -> 825 | AO52: =AN52 -> 825 | AP52: =AO52 -> 825 | ... AS52: =AR52 -> 825 | AT52: =AS52+10%*AS52 -> 907.5 | AU52: =AT52 -> 907.5 | AV52: =AU52 -> 907.5 | AW52: =AV52 -> 907.5 | AX52: =AW52 -> 907.5 | AY52: =AX52 -> 907.5 | AZ52: =AY52 -> 907.5 | BA52: =AZ52 -> 907.5 | BB52: =BA52 -> 907.5 | ... BQ52: =BP52 -> 907.5
B53: Revenue - Survey | J53: 250 | K53: 250 | L53: 250 | M53: 250 | N53: 250 | O53: 250 | P53: 250 | Q53: 250 | R53: 250 | S53: 250 | T53: 250 | U53: 250 | V53: 250 | W53: 250 | X53: 250 | Y53: 250 | Z53: 250 | AA53: 250 | AB53: 250 | AC53: 250 | AD53: 250 | AE53: 250 | AF53: 250 | AG53: 250 | AH53: =AG53+10%*AG53 -> 275 | AI53: =AH53 -> 275 | AJ53: =AI53 -> 275 | AK53: =AJ53 -> 275 | AL53: =AK53 -> 275 | AM53: =AL53 -> 275 | AN53: =AM53 -> 275 | AO53: =AN53 -> 275 | AP53: =AO53 -> 275 | ... AS53: =AR53 -> 275 | AT53: =AS53+10%*AS53 -> 302.5 | AU53: =AT53 -> 302.5 | AV53: =AU53 -> 302.5 | AW53: =AV53 -> 302.5 | AX53: =AW53 -> 302.5 | AY53: =AX53 -> 302.5 | AZ53: =AY53 -> 302.5 | BA53: =AZ53 -> 302.5 | BB53: =BA53 -> 302.5 | ... BQ53: =BP53 -> 302.5
B54: Revenue - Wall Mount | J54: 75 | K54: 75 | L54: 75 | M54: 75 | N54: 75 | O54: 75 | P54: 75 | Q54: 75 | R54: 75 | S54: 75 | T54: 75 | U54: 75 | V54: 75 | W54: 75 | X54: 75 | Y54: 75 | Z54: 75 | AA54: 75 | AB54: 75 | AC54: 75 | AD54: 75 | AE54: 75 | AF54: 75 | AG54: 75 | AH54: =AG54+10%*AG54 -> 82.5 | AI54: =AH54 -> 82.5 | AJ54: =AI54 -> 82.5 | AK54: =AJ54 -> 82.5 | AL54: =AK54 -> 82.5 | AM54: =AL54 -> 82.5 | AN54: =AM54 -> 82.5 | AO54: =AN54 -> 82.5 | AP54: =AO54 -> 82.5 | ... AS54: =AR54 -> 82.5 | AT54: =AS54+10%*AS54 -> 90.75 | AU54: =AT54 -> 90.75 | AV54: =AU54 -> 90.75 | AW54: =AV54 -> 90.75 | AX54: =AW54 -> 90.75 | AY54: =AX54 -> 90.75 | AZ54: =AY54 -> 90.75 | BA54: =AZ54 -> 90.75 | BB54: =BA54 -> 90.75 | ... BQ54: =BP54 -> 90.75
B55: Revenue - Software Set Up | J55: 50 | K55: 50 | L55: 50 | M55: 50 | N55: 50 | O55: 50 | P55: 50 | Q55: 50 | R55: 50 | S55: 50 | T55: 50 | U55: 50 | V55: 50 | W55: 50 | X55: 50 | Y55: 50 | Z55: 50 | AA55: 50 | AB55: 50 | AC55: 50 | AD55: 50 | AE55: 50 | AF55: 50 | AG55: 50 | AH55: =AG55+10%*AG55 -> 55 | AI55: =AH55 -> 55 | AJ55: =AI55 -> 55 | AK55: =AJ55 -> 55 | AL55: =AK55 -> 55 | AM55: =AL55 -> 55 | AN55: =AM55 -> 55 | AO55: =AN55 -> 55 | AP55: =AO55 -> 55 | ... AS55: =AR55 -> 55 | AT55: =AS55+10%*AS55 -> 60.5 | AU55: =AT55 -> 60.5 | AV55: =AU55 -> 60.5 | AW55: =AV55 -> 60.5 | AX55: =AW55 -> 60.5 | AY55: =AX55 -> 60.5 | AZ55: =AY55 -> 60.5 | BA55: =AZ55 -> 60.5 | BB55: =BA55 -> 60.5 | ... BQ55: =BP55 -> 60.5
B56: Revenue - Other | J56: 0 | K56: 0 | L56: 0 | M56: 0 | N56: 0 | O56: 0 | P56: 0 | Q56: 0 | R56: 0 | S56: 0 | T56: 0 | U56: 0 | V56: 0 | W56: 0 | X56: 0 | Y56: 0 | Z56: 0 | AA56: 0 | AB56: 0 | AC56: 0 | AD56: 0 | AE56: 0 | AF56: 0 | AG56: 0 | AH56: =AG56+10%*AG56 -> 0 | AI56: =AH56 -> 0 | AJ56: =AI56 -> 0 | AK56: =AJ56 -> 0 | AL56: =AK56 -> 0 | AM56: =AL56 -> 0 | AN56: =AM56 -> 0 | AO56: =AN56 -> 0 | AP56: =AO56 -> 0 | ... AS56: =AR56 -> 0 | AT56: =AS56+10%*AS56 -> 0 | AU56: =AT56 -> 0 | AV56: =AU56 -> 0 | AW56: =AV56 -> 0 | AX56: =AW56 -> 0 | AY56: =AX56 -> 0 | AZ56: =AY56 -> 0 | BA56: =AZ56 -> 0 | BB56: =BA56 -> 0 | ... BQ56: =BP56 -> 0
B58: ISP Funds Capex - Recurring Revenue
B59: Revenue - Software | J59: 75 | K59: 75 | L59: 75 | M59: 75 | N59: 75 | O59: 75 | P59: 75 | Q59: 75 | R59: 75 | S59: 75 | T59: 75 | U59: 75 | V59: 75 | W59: 75 | X59: 75 | Y59: 75 | Z59: 75 | AA59: 75 | AB59: 75 | AC59: 75 | AD59: 75 | AE59: 75 | AF59: 75 | AG59: 75 | AH59: =AG59+10%*AG59 -> 82.5 | AI59: =AH59 -> 82.5 | AJ59: =AI59 -> 82.5 | AK59: =AJ59 -> 82.5 | AL59: =AK59 -> 82.5 | AM59: =AL59 -> 82.5 | AN59: =AM59 -> 82.5 | AO59: =AN59 -> 82.5 | AP59: =AO59 -> 82.5 | ... AS59: =AR59 -> 82.5 | AT59: =AS59+10%*AS59 -> 90.75 | AU59: =AT59 -> 90.75 | AV59: =AU59 -> 90.75 | AW59: =AV59 -> 90.75 | AX59: =AW59 -> 90.75 | AY59: =AX59 -> 90.75 | AZ59: =AY59 -> 90.75 | BA59: =AZ59 -> 90.75 | BB59: =BA59 -> 90.75 | ... BQ59: =BP59 -> 90.75
B60: Per Month Rental 50 or below | J60: 0 | K60: 0 | L60: 0 | M60: 0 | N60: 0 | O60: 0 | P60: 0 | Q60: 0 | R60: 0 | S60: 0 | T60: 25 | U60: 25 | V60: 25 | W60: 25 | X60: 25 | Y60: 25 | Z60: 25 | AA60: 25 | AB60: 25 | AC60: 25 | AD60: 25 | AE60: 25 | AF60: 25 | AG60: 25 | AH60: =AG60+10%*AG60 -> 27.5 | AI60: =AH60 -> 27.5 | AJ60: =AI60 -> 27.5 | AK60: =AJ60 -> 27.5 | AL60: =AK60 -> 27.5 | AM60: =AL60 -> 27.5 | AN60: =AM60 -> 27.5 | AO60: =AN60 -> 27.5 | AP60: =AO60 -> 27.5 | ... AS60: =AR60 -> 27.5 | AT60: =AS60+10%*AS60 -> 30.25 | AU60: =AT60 -> 30.25 | AV60: =AU60 -> 30.25 | AW60: =AV60 -> 30.25 | AX60: =AW60 -> 30.25 | AY60: =AX60 -> 30.25 | AZ60: =AY60 -> 30.25 | BA60: =AZ60 -> 30.25 | BB60: =BA60 -> 30.25 | ... BQ60: =BP60 -> 30.25
B61: Per Month Rental 50 or above | J61: 0 | K61: 0 | L61: 0 | M61: 0 | N61: 0 | O61: 0 | P61: 0 | Q61: 0 | R61: 0 | S61: 0 | T61: 50 | U61: 50 | V61: 50 | W61: 50 | X61: 50 | Y61: 50 | Z61: 50 | AA61: 50 | AB61: 50 | AC61: 50 | AD61: 50 | AE61: 50 | AF61: 50 | AG61: 50 | AH61: =AG61+10%*AG61 -> 55 | AI61: =AH61 -> 55 | AJ61: =AI61 -> 55 | AK61: =AJ61 -> 55 | AL61: =AK61 -> 55 | AM61: =AL61 -> 55 | AN61: =AM61 -> 55 | AO61: =AN61 -> 55 | AP61: =AO61 -> 55 | ... AS61: =AR61 -> 55 | AT61: =AS61+10%*AS61 -> 60.5 | AU61: =AT61 -> 60.5 | AV61: =AU61 -> 60.5 | AW61: =AV61 -> 60.5 | AX61: =AW61 -> 60.5 | AY61: =AX61 -> 60.5 | AZ61: =AY61 -> 60.5 | BA61: =AZ61 -> 60.5 | BB61: =BA61 -> 60.5 | ... BQ61: =BP61 -> 60.5
B62: Per Month Rental 50 or below % | J62: 0.7 | K62: 0.7 | L62: 0.7 | M62: 0.7 | N62: 0.7 | O62: 0.7 | P62: 0.7 | Q62: 0.7 | R62: 0.7 | S62: 0.7 | T62: 0.7 | U62: 0.7 | V62: 0.7 | W62: 0.7 | X62: 0.7 | Y62: 0.7 | Z62: 0.7 | AA62: 0.7 | AB62: 0.7 | AC62: 0.7 | AD62: 0.7 | AE62: 0.7 | AF62: 0.7 | AG62: 0.7 | AH62: 0.7 | AI62: 0.7 | AJ62: 0.7 | AK62: 0.7 | AL62: 0.7 | AM62: 0.7 | AN62: 0.7 | AO62: 0.7 | AP62: 0.7 | AQ62: 0.7 | AR62: 0.7 | AS62: 0.7 | AT62: 0.7 | AU62: 0.7 | AV62: 0.7 | AW62: 0.7 | AX62: 0.7 | AY62: 0.7 | AZ62: 0.7 | BA62: 0.7 | BB62: 0.7 | BC62: 0.7 | BD62: 0.7 | BE62: 0.7 | BF62: 0.7 | BG62: 0.7 | BH62: 0.7 | BI62: 0.7 | BJ62: 0.7 | BK62: 0.7 | BL62: 0.7 | BM62: 0.7 | BN62: 0.7 | BO62: 0.7 | BP62: 0.7 | BQ62: 0.7
B63: Per Month Rental 50 or above % | J63: 0.3 | K63: 0.3 | L63: 0.3 | M63: 0.3 | N63: 0.3 | O63: 0.3 | P63: 0.3 | Q63: 0.3 | R63: 0.3 | S63: 0.3 | T63: 0.3 | U63: 0.3 | V63: 0.3 | W63: 0.3 | X63: 0.3 | Y63: 0.3 | Z63: 0.3 | AA63: 0.3 | AB63: 0.3 | AC63: 0.3 | AD63: 0.3 | AE63: 0.3 | AF63: 0.3 | AG63: 0.3 | AH63: 0.3 | AI63: 0.3 | AJ63: 0.3 | AK63: 0.3 | AL63: 0.3 | AM63: 0.3 | AN63: 0.3 | AO63: 0.3 | AP63: 0.3 | AQ63: 0.3 | AR63: 0.3 | AS63: 0.3 | AT63: 0.3 | AU63: 0.3 | AV63: 0.3 | AW63: 0.3 | AX63: 0.3 | AY63: 0.3 | AZ63: 0.3 | BA63: 0.3 | BB63: 0.3 | BC63: 0.3 | BD63: 0.3 | BE63: 0.3 | BF63: 0.3 | BG63: 0.3 | BH63: 0.3 | BI63: 0.3 | BJ63: 0.3 | BK63: 0.3 | BL63: 0.3 | BM63: 0.3 | BN63: 0.3 | BO63: 0.3 | BP63: 0.3 | BQ63: 0.3
B64: Revenue - Media and Advertising | J64: 0 | K64: 0 | L64: 0 | M64: 0 | N64: 0 | O64: 0 | P64: 0 | Q64: 0 | R64: 0 | S64: 0 | T64: 0 | U64: 50 | V64: 50 | W64: 50 | X64: 75 | Y64: 75 | Z64: 75 | AA64: 75 | AB64: 75 | AC64: 75 | AD64: 75 | AE64: 75 | AF64: 75 | AG64: 75 | AH64: =AG64+10%*AG64 -> 82.5 | AI64: =AH64 -> 82.5 | AJ64: =AI64 -> 82.5 | AK64: =AJ64 -> 82.5 | AL64: =AK64 -> 82.5 | AM64: =AL64 -> 82.5 | AN64: =AM64 -> 82.5 | AO64: =AN64 -> 82.5 | AP64: =AO64 -> 82.5 | ... AS64: =AR64 -> 82.5 | AT64: =AS64+10%*AS64 -> 90.75 | AU64: =AT64 -> 90.75 | AV64: =AU64 -> 90.75 | AW64: =AV64 -> 90.75 | AX64: =AW64 -> 90.75 | AY64: =AX64 -> 90.75 | AZ64: =AY64 -> 90.75 | BA64: =AZ64 -> 90.75 | BB64: =BA64 -> 90.75 | ... BQ64: =BP64 -> 90.75
B65: Revenue - MA | L65: 0 | M65: 0 | N65: 0 | O65: 0 | P65: 0 | Q65: 0 | R65: 0 | S65: 0 | T65: 0 | U65: 0 | V65: 0 | W65: 0 | X65: 0 | Y65: 100 | Z65: 100 | AA65: 100 | AB65: 100 | AC65: 100 | AD65: 100 | AE65: 100 | AF65: 100 | AG65: 100 | AH65: =AG65+10%*AG65 -> 110 | AI65: =AH65 -> 110 | AJ65: =AI65 -> 110 | AK65: =AJ65 -> 110 | AL65: =AK65 -> 110 | AM65: =AL65 -> 110 | AN65: =AM65 -> 110 | AO65: =AN65 -> 110 | AP65: =AO65 -> 110 | ... AS65: =AR65 -> 110 | AT65: =AS65+10%*AS65 -> 121 | AU65: =AT65 -> 121 | AV65: =AU65 -> 121 | AW65: =AV65 -> 121 | AX65: =AW65 -> 121 | AY65: =AX65 -> 121 | AZ65: =AY65 -> 121 | BA65: =AZ65 -> 121 | BB65: =BA65 -> 121 | ... BQ65: =BP65 -> 121
B67: SCCI - one off revenue
B68: Revenue - SCCI initial set up | J68: 150 | K68: 150 | L68: 150 | M68: 150 | N68: 150 | O68: 150 | P68: 150 | Q68: 150 | R68: 150 | S68: 150 | T68: 150 | U68: 150 | V68: 150 | W68: 150 | X68: 150 | Y68: 150 | Z68: 150 | AA68: 150 | AB68: 150 | AC68: 150 | AD68: 150 | AE68: 150 | AF68: 150 | AG68: 150 | AH68: =AG68+10%*AG68 -> 165 | AI68: =AH68 -> 165 | AJ68: =AI68 -> 165 | AK68: =AJ68 -> 165 | AL68: =AK68 -> 165 | AM68: =AL68 -> 165 | AN68: =AM68 -> 165 | AO68: =AN68 -> 165 | AP68: =AO68 -> 165 | ... AS68: =AR68 -> 165 | AT68: =AS68+10%*AS68 -> 181.5 | AU68: =AT68 -> 181.5 | AV68: =AU68 -> 181.5 | AW68: =AV68 -> 181.5 | AX68: =AW68 -> 181.5 | AY68: =AX68 -> 181.5 | AZ68: =AY68 -> 181.5 | BA68: =AZ68 -> 181.5 | BB68: =BA68 -> 181.5 | ... BQ68: =BP68 -> 181.5
B70: SCCI - Recurring Revenue
B71: Revenue - SCCI Software rental | J71: 100 | K71: 100 | L71: 100 | M71: 100 | N71: 100 | O71: 100 | P71: 100 | Q71: 100 | R71: 100 | S71: 100 | T71: 100 | U71: 100 | V71: 100 | W71: 100 | X71: 100 | Y71: 100 | Z71: 100 | AA71: 100 | AB71: 100 | AC71: 100 | AD71: 100 | AE71: 100 | AF71: 100 | AG71: 100 | AH71: =AG71+10%*AG71 -> 110 | AI71: =AH71 -> 110 | AJ71: =AI71 -> 110 | AK71: =AJ71 -> 110 | AL71: =AK71 -> 110 | AM71: =AL71 -> 110 | AN71: =AM71 -> 110 | AO71: =AN71 -> 110 | AP71: =AO71 -> 110 | ... AS71: =AR71 -> 110 | AT71: =AS71+10%*AS71 -> 121 | AU71: =AT71 -> 121 | AV71: =AU71 -> 121 | AW71: =AV71 -> 121 | AX71: =AW71 -> 121 | AY71: =AX71 -> 121 | AZ71: =AY71 -> 121 | BA71: =AZ71 -> 121 | BB71: =BA71 -> 121 | ... BQ71: =BP71 -> 121
B72: Revenue - SCCI Media and Advertising | J72: 0 | K72: 0 | L72: 0 | M72: 0 | N72: 0 | O72: 0 | P72: 0 | Q72: 0 | R72: 0 | S72: 0 | T72: 0 | U72: 50 | V72: 50 | W72: 50 | X72: 50 | Y72: 50 | Z72: 50 | AA72: 50 | AB72: 50 | AC72: 50 | AD72: 50 | AE72: 50 | AF72: 50 | AG72: 50 | AH72: =AG72+10%*AG72 -> 55 | AI72: =AH72 -> 55 | AJ72: =AI72 -> 55 | AK72: =AJ72 -> 55 | AL72: =AK72 -> 55 | AM72: =AL72 -> 55 | AN72: =AM72 -> 55 | AO72: =AN72 -> 55 | AP72: =AO72 -> 55 | ... AS72: =AR72 -> 55 | AT72: =AS72+10%*AS72 -> 60.5 | AU72: =AT72 -> 60.5 | AV72: =AU72 -> 60.5 | AW72: =AV72 -> 60.5 | AX72: =AW72 -> 60.5 | AY72: =AX72 -> 60.5 | AZ72: =AY72 -> 60.5 | BA72: =AZ72 -> 60.5 | BB72: =BA72 -> 60.5 | ... BQ72: =BP72 -> 60.5
B74: ISP Funds £0 Capex - one off revenue
B75: Revenue - ISP £0 Capex initial set up | J75: 300 | K75: 300 | L75: 300 | M75: 300 | N75: 300 | O75: 300 | P75: 300 | Q75: 300 | R75: 300 | S75: 300 | T75: 300 | U75: 300 | V75: 300 | W75: 300 | X75: 300 | Y75: 300 | Z75: 300 | AA75: 300 | AB75: 300 | AC75: 300 | AD75: 300 | AE75: 300 | AF75: 300 | AG75: 300 | AH75: =AG75+10%*AG75 -> 330 | AI75: =AH75 -> 330 | AJ75: =AI75 -> 330 | AK75: =AJ75 -> 330 | AL75: =AK75 -> 330 | AM75: =AL75 -> 330 | AN75: =AM75 -> 330 | AO75: =AN75 -> 330 | AP75: =AO75 -> 330 | ... AS75: =AR75 -> 330 | AT75: =AS75+10%*AS75 -> 363 | AU75: =AT75 -> 363 | AV75: =AU75 -> 363 | AW75: =AV75 -> 363 | AX75: =AW75 -> 363 | AY75: =AX75 -> 363 | AZ75: =AY75 -> 363 | BA75: =AZ75 -> 363 | BB75: =BA75 -> 363 | ... BQ75: =BP75 -> 363
B77: ISP Funds £0 Capex - recurring revenue
B78: Revenue - ISP £0 Capex Software rental | J78: 125 | K78: 125 | L78: 125 | M78: 125 | N78: 125 | O78: 125 | P78: 125 | Q78: 125 | R78: 125 | S78: 125 | T78: 125 | U78: 125 | V78: 125 | W78: 125 | X78: 125 | Y78: 125 | Z78: 125 | AA78: 125 | AB78: 125 | AC78: 125 | AD78: 125 | AE78: 125 | AF78: 125 | AG78: 125 | AH78: =AG78+10%*AG78 -> 137.5 | AI78: =AH78 -> 137.5 | AJ78: =AI78 -> 137.5 | AK78: =AJ78 -> 137.5 | AL78: =AK78 -> 137.5 | AM78: =AL78 -> 137.5 | AN78: =AM78 -> 137.5 | AO78: =AN78 -> 137.5 | AP78: =AO78 -> 137.5 | ... AS78: =AR78 -> 137.5 | AT78: =AS78+10%*AS78 -> 151.25 | AU78: =AT78 -> 151.25 | AV78: =AU78 -> 151.25 | AW78: =AV78 -> 151.25 | AX78: =AW78 -> 151.25 | AY78: =AX78 -> 151.25 | AZ78: =AY78 -> 151.25 | BA78: =AZ78 -> 151.25 | BB78: =BA78 -> 151.25 | ... BQ78: =BP78 -> 151.25
B79: Revenue - ISP £0 Capex Media and Advertising | J79: 0 | K79: 0 | L79: 0 | M79: 0 | N79: 0 | O79: 0 | P79: 0 | Q79: 0 | R79: 0 | S79: 0 | T79: 50 | U79: 50 | V79: 50 | W79: 50 | X79: 75 | Y79: 75 | Z79: 75 | AA79: 75 | AB79: 75 | AC79: 75 | AD79: 75 | AE79: 75 | AF79: 75 | AG79: 75 | AH79: =AG79+10%*AG79 -> 82.5 | AI79: =AH79 -> 82.5 | AJ79: =AI79 -> 82.5 | AK79: =AJ79 -> 82.5 | AL79: =AK79 -> 82.5 | AM79: =AL79 -> 82.5 | AN79: =AM79 -> 82.5 | AO79: =AN79 -> 82.5 | AP79: =AO79 -> 82.5 | ... AS79: =AR79 -> 82.5 | AT79: =AS79+10%*AS79 -> 90.75 | AU79: =AT79 -> 90.75 | AV79: =AU79 -> 90.75 | AW79: =AV79 -> 90.75 | AX79: =AW79 -> 90.75 | AY79: =AX79 -> 90.75 | AZ79: =AY79 -> 90.75 | BA79: =AZ79 -> 90.75 | BB79: =BA79 -> 90.75 | ... BQ79: =BP79 -> 90.75
B80: Revenue - Managing Agent | L80: 0 | M80: 0 | N80: 0 | O80: 0 | P80: 0 | Q80: 0 | R80: 0 | S80: 0 | T80: 0 | U80: 0 | V80: 0 | W80: 0 | X80: 0 | Y80: 100 | Z80: 100 | AA80: 100 | AB80: 100 | AC80: 100 | AD80: 100 | AE80: 100 | AF80: 100 | AG80: 100 | AH80: =AG80+10%*AG80 -> 110 | AI80: =AH80 -> 110 | AJ80: =AI80 -> 110 | AK80: =AJ80 -> 110 | AL80: =AK80 -> 110 | AM80: =AL80 -> 110 | AN80: =AM80 -> 110 | AO80: =AN80 -> 110 | AP80: =AO80 -> 110 | ... AS80: =AR80 -> 110 | AT80: =AS80+10%*AS80 -> 121 | AU80: =AT80 -> 121 | AV80: =AU80 -> 121 | AW80: =AV80 -> 121 | AX80: =AW80 -> 121 | AY80: =AX80 -> 121 | AZ80: =AY80 -> 121 | BA80: =AZ80 -> 121 | BB80: =BA80 -> 121 | ... BQ80: =BP80 -> 121
B82: Other - recurring revenue
B83: Revenue - Other Media and Advertising | J83: 200 | K83: 200 | L83: 200 | M83: 200 | N83: 200 | O83: 200 | P83: 200 | Q83: 200 | R83: 200 | S83: 200 | T83: 200 | U83: 200 | V83: 200 | W83: 200 | X83: 200 | Y83: 200 | Z83: 200 | AA83: 200 | AB83: 200 | AC83: 200 | AD83: 200 | AE83: 200 | AF83: 200 | AG83: 200 | AH83: =AG83+10%*AG83 -> 220 | AI83: =AH83 -> 220 | AJ83: =AI83 -> 220 | AK83: =AJ83 -> 220 | AL83: =AK83 -> 220 | AM83: =AL83 -> 220 | AN83: =AM83 -> 220 | AO83: =AN83 -> 220 | AP83: =AO83 -> 220 | ... AS83: =AR83 -> 220 | AT83: =AS83+10%*AS83 -> 242 | AU83: =AT83 -> 242 | AV83: =AU83 -> 242 | AW83: =AV83 -> 242 | AX83: =AW83 -> 242 | AY83: =AX83 -> 242 | AZ83: =AY83 -> 242 | BA83: =AZ83 -> 242 | BB83: =BA83 -> 242 | ... BQ83: =BP83 -> 242
B87: Cost of Sales Assumptions
B88: ISP Funds Capex
B89: Cost of Screen | J89: 623 | K89: 623 | L89: 623 | M89: 623 | N89: 623 | O89: 623 | P89: 623 | Q89: 623 | R89: 623 | S89: 623 | T89: 623 | U89: 623 | V89: 623 | W89: 623 | X89: 623 | Y89: 623 | Z89: 623 | AA89: 623 | AB89: 623 | AC89: 623 | AD89: 623 | AE89: 623 | AF89: 623 | AG89: 623 | AH89: 623 | AI89: 623 | AJ89: 623 | AK89: 623 | AL89: 623 | AM89: 623 | AN89: 623 | AO89: 623 | AP89: 623 | AQ89: 623 | AR89: 623 | AS89: 623 | AT89: 623 | AU89: 623 | AV89: 623 | AW89: 623 | AX89: 623 | AY89: 623 | AZ89: 623 | BA89: 623 | BB89: 623 | BC89: 623 | BD89: 623 | BE89: 623 | BF89: 623 | BG89: 623 | BH89: 623 | BI89: 623 | BJ89: 623 | BK89: 623 | BL89: 623 | BM89: 623 | BN89: 623 | BO89: 623 | BP89: 623 | BQ89: 623
B90: Screen Set up and Installation | J90: 600 | K90: 600 | L90: 600 | M90: 600 | N90: 600 | O90: 600 | P90: 600 | Q90: 600 | R90: 600 | S90: 600 | T90: 600 | U90: 600 | V90: 600 | W90: 600 | X90: 600 | Y90: 600 | Z90: 600 | AA90: 600 | AB90: 600 | AC90: 600 | AD90: 600 | AE90: 600 | AF90: 600 | AG90: 600 | AH90: 600 | AI90: 600 | AJ90: 600 | AK90: 600 | AL90: 600 | AM90: 600 | AN90: 600 | AO90: 600 | AP90: 600 | AQ90: 600 | AR90: 600 | AS90: 600 | AT90: 600 | AU90: 600 | AV90: 600 | AW90: 600 | AX90: 600 | AY90: 600 | AZ90: 600 | BA90: 600 | BB90: 600 | BC90: 600 | BD90: 600 | BE90: 600 | BF90: 600 | BG90: 600 | BH90: 600 | BI90: 600 | BJ90: 600 | BK90: 600 | BL90: 600 | BM90: 600 | BN90: 600 | BO90: 600 | BP90: 600 | BQ90: 600
B91: Screen wall mount | J91: 48 | K91: 48 | L91: 48 | M91: 48 | N91: 48 | O91: 48 | P91: 48 | Q91: 48 | R91: 48 | S91: 48 | T91: 48 | U91: 48 | V91: 48 | W91: 48 | X91: 48 | Y91: 48 | Z91: 48 | AA91: 48 | AB91: 48 | AC91: 48 | AD91: 48 | AE91: 48 | AF91: 48 | AG91: 48 | AH91: 48 | AI91: 48 | AJ91: 48 | AK91: 48 | AL91: 48 | AM91: 48 | AN91: 48 | AO91: 48 | AP91: 48 | AQ91: 48 | AR91: 48 | AS91: 48 | AT91: 48 | AU91: 48 | AV91: 48 | AW91: 48 | AX91: 48 | AY91: 48 | AZ91: 48 | BA91: 48 | BB91: 48 | BC91: 48 | BD91: 48 | BE91: 48 | BF91: 48 | BG91: 48 | BH91: 48 | BI91: 48 | BJ91: 48 | BK91: 48 | BL91: 48 | BM91: 48 | BN91: 48 | BO91: 48 | BP91: 48 | BQ91: 48
B92: Screen Survey cost | J92: 200 | K92: 200 | L92: 200 | M92: 200 | N92: 200 | O92: 200 | P92: 200 | Q92: 200 | R92: 200 | S92: 200 | T92: 200 | U92: 200 | V92: 200 | W92: 200 | X92: 200 | Y92: 200 | Z92: 200 | AA92: 200 | AB92: 200 | AC92: 200 | AD92: 200 | AE92: 200 | AF92: 200 | AG92: 200 | AH92: 200 | AI92: 200 | AJ92: 200 | AK92: 200 | AL92: 200 | AM92: 200 | AN92: 200 | AO92: 200 | AP92: 200 | AQ92: 200 | AR92: 200 | AS92: 200 | AT92: 200 | AU92: 200 | AV92: 200 | AW92: 200 | AX92: 200 | AY92: 200 | AZ92: 200 | BA92: 200 | BB92: 200 | BC92: 200 | BD92: 200 | BE92: 200 | BF92: 200 | BG92: 200 | BH92: 200 | BI92: 200 | BJ92: 200 | BK92: 200 | BL92: 200 | BM92: 200 | BN92: 200 | BO92: 200 | BP92: 200 | BQ92: 200
B93: ISP - Software charge | J93: 22.5 | K93: 22.5 | L93: 22.5 | M93: 22.5 | N93: 22.5 | O93: 22.5 | P93: 22.5 | Q93: 22.5 | R93: 22.5 | S93: 22.5 | T93: 22.5 | U93: 22.5 | V93: 22.5 | W93: 22.5 | X93: 22.5 | Y93: 22.5 | Z93: 22.5 | AA93: 22.5 | AB93: 22.5 | AC93: 22.5 | AD93: 22.5 | AE93: 22.5 | AF93: 22.5 | AG93: 22.5 | AH93: 22.5 | AI93: 22.5 | AJ93: 22.5 | AK93: 22.5 | AL93: 22.5 | AM93: 22.5 | AN93: 22.5 | AO93: 22.5 | AP93: 22.5 | AQ93: 22.5 | AR93: 22.5 | AS93: 22.5 | AT93: 22.5 | AU93: 22.5 | AV93: 22.5 | AW93: 22.5 | AX93: 22.5 | AY93: 22.5 | AZ93: 22.5 | BA93: 22.5 | BB93: 22.5 | BC93: 22.5 | BD93: 22.5 | BE93: 22.5 | BF93: 22.5 | BG93: 22.5 | BH93: 22.5 | BI93: 22.5 | BJ93: 22.5 | BK93: 22.5 | BL93: 22.5 | BM93: 22.5 | BN93: 22.5 | BO93: 22.5 | BP93: 22.5 | BQ93: 22.5
B94: Other Costs | J94: 0 | K94: 0 | L94: 0 | M94: 0 | N94: 0 | O94: 0 | P94: 0 | Q94: 0 | R94: 0 | S94: 0 | T94: 0 | U94: 0 | V94: 0 | W94: 0 | X94: 0 | Y94: 0 | Z94: 0 | AA94: 0 | AB94: 0 | AC94: 0 | AD94: 0 | AE94: 0 | AF94: 0 | AG94: 0 | AH94: 0 | AI94: 0 | AJ94: 0 | AK94: 0 | AL94: 0 | AM94: 0 | AN94: 0 | AO94: 0 | AP94: 0 | AQ94: 0 | AR94: 0 | AS94: 0 | AT94: 0 | AU94: 0 | AV94: 0 | AW94: 0 | AX94: 0 | AY94: 0 | AZ94: 0 | BA94: 0 | BB94: 0 | BC94: 0 | BD94: 0 | BE94: 0 | BF94: 0 | BG94: 0 | BH94: 0 | BI94: 0 | BJ94: 0 | BK94: 0 | BL94: 0 | BM94: 0 | BN94: 0 | BO94: 0 | BP94: 0 | BQ94: 0
B95: Media and Advertising | J95: 0 | K95: 0 | L95: 0 | M95: 0 | N95: 0 | O95: 0 | P95: 0 | Q95: 0 | R95: 0 | S95: 0 | T95: 0 | U95: 0 | V95: 60 | W95: 60 | X95: 60 | Y95: 60 | Z95: 60 | AA95: 60 | AB95: 60 | AC95: 60 | AD95: 60 | AE95: 60 | AF95: 60 | AG95: 60 | AH95: 60 | AI95: 60 | AJ95: 60 | AK95: 60 | AL95: 60 | AM95: 60 | AN95: 60 | AO95: 60 | AP95: 60 | AQ95: 60 | AR95: 60 | AS95: 60 | AT95: 60 | AU95: 60 | AV95: 60 | AW95: 60 | AX95: 60 | AY95: 60 | AZ95: 60 | BA95: 60 | BB95: 60 | BC95: 60 | BD95: 60 | BE95: 60 | BF95: 60 | BG95: 60 | BH95: 60 | BI95: 60 | BJ95: 60 | BK95: 60 | BL95: 60 | BM95: 60 | BN95: 60 | BO95: 60 | BP95: 60 | BQ95: 60
B96: SCCI
B97: SCCI - Software charge | J97: 22.5 | K97: 22.5 | L97: 22.5 | M97: 22.5 | N97: 22.5 | O97: 22.5 | P97: 22.5 | Q97: 22.5 | R97: 22.5 | S97: 22.5 | T97: 22.5 | U97: 22.5 | V97: 22.5 | W97: 22.5 | X97: 22.5 | Y97: 22.5 | Z97: 22.5 | AA97: 22.5 | AB97: 22.5 | AC97: 22.5 | AD97: 22.5 | AE97: 22.5 | AF97: 22.5 | AG97: 22.5 | AH97: 22.5 | AI97: 22.5 | AJ97: 22.5 | AK97: 22.5 | AL97: 22.5 | AM97: 22.5 | AN97: 22.5 | AO97: 22.5 | AP97: 22.5 | AQ97: 22.5 | AR97: 22.5 | AS97: 22.5 | AT97: 22.5 | AU97: 22.5 | AV97: 22.5 | AW97: 22.5 | AX97: 22.5 | AY97: 22.5 | AZ97: 22.5 | BA97: 22.5 | BB97: 22.5 | BC97: 22.5 | BD97: 22.5 | BE97: 22.5 | BF97: 22.5 | BG97: 22.5 | BH97: 22.5 | BI97: 22.5 | BJ97: 22.5 | BK97: 22.5 | BL97: 22.5 | BM97: 22.5 | BN97: 22.5 | BO97: 22.5 | BP97: 22.5 | BQ97: 22.5
B98: SCCI - 5g ongoing cost | J98: 3 | K98: 3 | L98: 3 | M98: 3 | N98: 3 | O98: 3 | P98: 3 | Q98: 3 | R98: 3 | S98: 3 | T98: 3 | U98: 3 | V98: 3 | W98: 3 | X98: 3 | Y98: 3 | Z98: 3 | AA98: 3 | AB98: 3 | AC98: 3 | AD98: 3 | AE98: 3 | AF98: 3 | AG98: 3 | AH98: 3 | AI98: 3 | AJ98: 3 | AK98: 3 | AL98: 3 | AM98: 3 | AN98: 3 | AO98: 3 | AP98: 3 | AQ98: 3 | AR98: 3 | AS98: 3 | AT98: 3 | AU98: 3 | AV98: 3 | AW98: 3 | AX98: 3 | AY98: 3 | AZ98: 3 | BA98: 3 | BB98: 3 | BC98: 3 | BD98: 3 | BE98: 3 | BF98: 3 | BG98: 3 | BH98: 3 | BI98: 3 | BJ98: 3 | BK98: 3 | BL98: 3 | BM98: 3 | BN98: 3 | BO98: 3 | BP98: 3 | BQ98: 3
B99: ISP Funds £0 Capex
B100: ISP Funds £0 Capex - Software charge | J100: 22.5 | K100: 22.5 | L100: 22.5 | M100: 22.5 | N100: 22.5 | O100: 22.5 | P100: 22.5 | Q100: 22.5 | R100: 22.5 | S100: 22.5 | T100: 22.5 | U100: 22.5 | V100: 22.5 | W100: 22.5 | X100: 22.5 | Y100: 22.5 | Z100: 22.5 | AA100: 22.5 | AB100: 22.5 | AC100: 22.5 | AD100: 22.5 | AE100: 22.5 | AF100: 22.5 | AG100: 22.5 | AH100: 22.5 | AI100: 22.5 | AJ100: 22.5 | AK100: 22.5 | AL100: 22.5 | AM100: 22.5 | AN100: 22.5 | AO100: 22.5 | AP100: 22.5 | AQ100: 22.5 | AR100: 22.5 | AS100: 22.5 | AT100: 22.5 | AU100: 22.5 | AV100: 22.5 | AW100: 22.5 | AX100: 22.5 | AY100: 22.5 | AZ100: 22.5 | BA100: 22.5 | BB100: 22.5 | BC100: 22.5 | BD100: 22.5 | BE100: 22.5 | BF100: 22.5 | BG100: 22.5 | BH100: 22.5 | BI100: 22.5 | BJ100: 22.5 | BK100: 22.5 | BL100: 22.5 | BM100: 22.5 | BN100: 22.5 | BO100: 22.5 | BP100: 22.5 | BQ100: 22.5
B101: ISP Funds £0 Capex - 5g ongoing cost | J101: 3 | K101: 3 | L101: 3 | M101: 3 | N101: 3 | O101: 3 | P101: 3 | Q101: 3 | R101: 3 | S101: 3 | T101: 3 | U101: 3 | V101: 3 | W101: 3 | X101: 3 | Y101: 3 | Z101: 3 | AA101: 3 | AB101: 3 | AC101: 3 | AD101: 3 | AE101: 3 | AF101: 3 | AG101: 3 | AH101: 3 | AI101: 3 | AJ101: 3 | AK101: 3 | AL101: 3 | AM101: 3 | AN101: 3 | AO101: 3 | AP101: 3 | AQ101: 3 | AR101: 3 | AS101: 3 | AT101: 3 | AU101: 3 | AV101: 3 | AW101: 3 | AX101: 3 | AY101: 3 | AZ101: 3 | BA101: 3 | BB101: 3 | BC101: 3 | BD101: 3 | BE101: 3 | BF101: 3 | BG101: 3 | BH101: 3 | BI101: 3 | BJ101: 3 | BK101: 3 | BL101: 3 | BM101: 3 | BN101: 3 | BO101: 3 | BP101: 3 | BQ101: 3
B102: Other Costs
B103: Other - Software charge | J103: 32.5 | K103: 32.5 | L103: 32.5 | M103: 32.5 | N103: 32.5 | O103: 32.5 | P103: 32.5 | Q103: 32.5 | R103: 32.5 | S103: 32.5 | T103: 32.5 | U103: 32.5 | V103: 32.5 | W103: 32.5 | X103: 32.5 | Y103: 32.5 | Z103: 32.5 | AA103: 32.5 | AB103: 32.5 | AC103: 32.5 | AD103: 32.5 | AE103: 32.5 | AF103: 32.5 | AG103: 32.5 | AH103: 32.5 | AI103: 32.5 | AJ103: 32.5 | AK103: 32.5 | AL103: 32.5 | AM103: 32.5 | AN103: 32.5 | AO103: 32.5 | AP103: 32.5 | AQ103: 32.5 | AR103: 32.5 | AS103: 32.5 | AT103: 32.5 | AU103: 32.5 | AV103: 32.5 | AW103: 32.5 | AX103: 32.5 | AY103: 32.5 | AZ103: 32.5 | BA103: 32.5 | BB103: 32.5 | BC103: 32.5 | BD103: 32.5 | BE103: 32.5 | BF103: 32.5 | BG103: 32.5 | BH103: 32.5 | BI103: 32.5 | BJ103: 32.5 | BK103: 32.5 | BL103: 32.5 | BM103: 32.5 | BN103: 32.5 | BO103: 32.5 | BP103: 32.5 | BQ103: 32.5
B104: Other - 5g ongoing cost | J104: 3 | K104: 3 | L104: 3 | M104: 3 | N104: 3 | O104: 3 | P104: 3 | Q104: 3 | R104: 3 | S104: 3 | T104: 3 | U104: 3 | V104: 3 | W104: 3 | X104: 3 | Y104: 3 | Z104: 3 | AA104: 3 | AB104: 3 | AC104: 3 | AD104: 3 | AE104: 3 | AF104: 3 | AG104: 3 | AH104: 3 | AI104: 3 | AJ104: 3 | AK104: 3 | AL104: 3 | AM104: 3 | AN104: 3 | AO104: 3 | AP104: 3 | AQ104: 3 | AR104: 3 | AS104: 3 | AT104: 3 | AU104: 3 | AV104: 3 | AW104: 3 | AX104: 3 | AY104: 3 | AZ104: 3 | BA104: 3 | BB104: 3 | BC104: 3 | BD104: 3 | BE104: 3 | BF104: 3 | BG104: 3 | BH104: 3 | BI104: 3 | BJ104: 3 | BK104: 3 | BL104: 3 | BM104: 3 | BN104: 3 | BO104: 3 | BP104: 3 | BQ104: 3
B105: Other - Freeholder cost | J105: 0 | K105: 0 | L105: 0 | M105: 0 | N105: 0 | O105: 0 | P105: 0 | Q105: 0 | R105: 0 | S105: 0 | T105: 50 | U105: 50 | V105: 50 | W105: 50 | X105: 50 | Y105: 50 | Z105: 50 | AA105: 50 | AB105: 50 | AC105: 50 | AD105: 50 | AE105: 50 | AF105: 50 | AG105: 50 | AH105: 50 | AI105: 50 | AJ105: 50 | AK105: 50 | AL105: 50 | AM105: 50 | AN105: 50 | AO105: 50 | AP105: 50 | AQ105: 50 | AR105: 50 | AS105: 50 | AT105: 50 | AU105: 50 | AV105: 50 | AW105: 50 | AX105: 50 | AY105: 50 | AZ105: 50 | BA105: 50 | BB105: 50 | BC105: 50 | BD105: 50 | BE105: 50 | BF105: 50 | BG105: 50 | BH105: 50 | BI105: 50 | BJ105: 50 | BK105: 50 | BL105: 50 | BM105: 50 | BN105: 50 | BO105: 50 | BP105: 50 | BQ105: 50
B108: Capex Assumptions
B109: Capex BOM
B110: Survey cost | J110: 200 | K110: 200 | L110: 200 | M110: 200 | N110: 200 | O110: 200 | P110: 200 | Q110: 200 | R110: 200 | S110: 200 | T110: 200 | U110: 200 | V110: 200 | W110: 200 | X110: 200 | Y110: 200 | Z110: 200 | AA110: 200 | AB110: 200 | AC110: 200 | AD110: 200 | AE110: 200 | AF110: 200 | AG110: 200 | AH110: 200 | AI110: 200 | AJ110: 200 | AK110: 200 | AL110: 200 | AM110: 200 | AN110: 200 | AO110: 200 | AP110: 200 | AQ110: 200 | AR110: 200 | AS110: 200 | AT110: 200 | AU110: 200 | AV110: 200 | AW110: 200 | AX110: 200 | AY110: 200 | AZ110: 200 | BA110: 200 | BB110: 200 | BC110: 200 | BD110: 200 | BE110: 200 | BF110: 200 | BG110: 200 | BH110: 200 | BI110: 200 | BJ110: 200 | BK110: 200 | BL110: 200 | BM110: 200 | BN110: 200 | BO110: 200 | BP110: 200 | BQ110: 200
B111: Installation cost | J111: 400 | K111: 400 | L111: 400 | M111: 400 | N111: 400 | O111: 400 | P111: 400 | Q111: 400 | R111: 400 | S111: 400 | T111: 400 | U111: 400 | V111: 400 | W111: 400 | X111: 400 | Y111: 400 | Z111: 400 | AA111: 400 | AB111: 400 | AC111: 400 | AD111: 400 | AE111: 400 | AF111: 400 | AG111: 400 | AH111: 400 | AI111: 400 | AJ111: 400 | AK111: 400 | AL111: 400 | AM111: 400 | AN111: 400 | AO111: 400 | AP111: 400 | AQ111: 400 | AR111: 400 | AS111: 400 | AT111: 400 | AU111: 400 | AV111: 400 | AW111: 400 | AX111: 400 | AY111: 400 | AZ111: 400 | BA111: 400 | BB111: 400 | BC111: 400 | BD111: 400 | BE111: 400 | BF111: 400 | BG111: 400 | BH111: 400 | BI111: 400 | BJ111: 400 | BK111: 400 | BL111: 400 | BM111: 400 | BN111: 400 | BO111: 400 | BP111: 400 | BQ111: 400
B112: 5g router | J112: 35 | K112: 35 | L112: 35 | M112: 35 | N112: 35 | O112: 35 | P112: 35 | Q112: 35 | R112: 35 | S112: 35 | T112: 35 | U112: 35 | V112: 35 | W112: 35 | X112: 35 | Y112: 35 | Z112: 35 | AA112: 35 | AB112: 35 | AC112: 35 | AD112: 35 | AE112: 35 | AF112: 35 | AG112: 35 | AH112: 35 | AI112: 35 | AJ112: 35 | AK112: 35 | AL112: 35 | AM112: 35 | AN112: 35 | AO112: 35 | AP112: 35 | AQ112: 35 | AR112: 35 | AS112: 35 | AT112: 35 | AU112: 35 | AV112: 35 | AW112: 35 | AX112: 35 | AY112: 35 | AZ112: 35 | BA112: 35 | BB112: 35 | BC112: 35 | BD112: 35 | BE112: 35 | BF112: 35 | BG112: 35 | BH112: 35 | BI112: 35 | BJ112: 35 | BK112: 35 | BL112: 35 | BM112: 35 | BN112: 35 | BO112: 35 | BP112: 35 | BQ112: 35
B113: Screen cost | J113: 600 | K113: 600 | L113: 600 | M113: 600 | N113: 600 | O113: 600 | P113: 600 | Q113: 600 | R113: 600 | S113: 600 | T113: 600 | U113: 600 | V113: 600 | W113: 600 | X113: 600 | Y113: 600 | Z113: 600 | AA113: 600 | AB113: 600 | AC113: 600 | AD113: 600 | AE113: 600 | AF113: 600 | AG113: 600 | AH113: 600 | AI113: 600 | AJ113: 600 | AK113: 600 | AL113: 600 | AM113: 600 | AN113: 600 | AO113: 600 | AP113: 600 | AQ113: 600 | AR113: 600 | AS113: 600 | AT113: 600 | AU113: 600 | AV113: 600 | AW113: 600 | AX113: 600 | AY113: 600 | AZ113: 600 | BA113: 600 | BB113: 600 | BC113: 600 | BD113: 600 | BE113: 600 | BF113: 600 | BG113: 600 | BH113: 600 | BI113: 600 | BJ113: 600 | BK113: 600 | BL113: 600 | BM113: 600 | BN113: 600 | BO113: 600 | BP113: 600 | BQ113: 600
B114: Total | J114: =SUM(J110:J113) -> 1235 | K114: =SUM(K110:K113) -> 1235 | L114: =SUM(L110:L113) -> 1235 | M114: =SUM(M110:M113) -> 1235 | N114: =SUM(N110:N113) -> 1235 | O114: =SUM(O110:O113) -> 1235 | P114: =SUM(P110:P113) -> 1235 | Q114: =SUM(Q110:Q113) -> 1235 | ... BQ114: =SUM(BQ110:BQ113) -> 1235
B116: Screen replacement/reapirs | J116: 0.01 | K116: 0.01 | L116: 0.01 | M116: 0.01 | N116: 0.01 | O116: 0.01 | P116: 0.01 | Q116: 0.01 | R116: 0.01 | S116: 0.01 | T116: 0.01 | U116: 0.01 | V116: 0.01 | W116: 0.01 | X116: 0.01 | Y116: 0.01 | Z116: 0.01 | AA116: 0.01 | AB116: 0.01 | AC116: 0.01 | AD116: 0.01 | AE116: 0.01 | AF116: 0.01 | AG116: 0.01 | AH116: 0.01 | AI116: 0.01 | AJ116: 0.01 | AK116: 0.01 | AL116: 0.01 | AM116: 0.01 | AN116: 0.01 | AO116: 0.01 | AP116: 0.01 | AQ116: 0.01 | AR116: 0.01 | AS116: 0.01 | AT116: 0.01 | AU116: 0.01 | AV116: 0.01 | AW116: 0.01 | AX116: 0.01 | AY116: 0.01 | AZ116: 0.01 | BA116: 0.01 | BB116: 0.01 | BC116: 0.01 | BD116: 0.01 | BE116: 0.01 | BF116: 0.01 | BG116: 0.01 | BH116: 0.01 | BI116: 0.01 | BJ116: 0.01 | BK116: 0.01 | BL116: 0.01 | BM116: 0.01 | BN116: 0.01 | BO116: 0.01 | BP116: 0.01 | BQ116: 0.01

Sheet Revenue
A1: Business 1
A2: Revenue | J2: =Timing!J2 -> 44986 | K2: =Timing!K2 -> 45017 | L2: =Timing!L2 -> 45047 | M2: =Timing!M2 -> 45078 | N2: =Timing!N2 -> 45108 | O2: =Timing!O2 -> 45139 | P2: =Timing!P2 -> 45170 | Q2: =Timing!Q2 -> 45200 | ... BQ2: =Timing!BQ2 -> 46784
J3: =Timing!J3 -> 45016 | K3: =Timing!K3 -> 45046 | L3: =Timing!L3 -> 45077 | M3: =Timing!M3 -> 45107 | N3: =Timing!N3 -> 45138 | O3: =Timing!O3 -> 45169 | P3: =Timing!P3 -> 45199 | Q3: =Timing!Q3 -> 45230 | ... BQ3: =Timing!BQ3 -> 46812
B4: Revenue Summary
B6: One Off Revenue
B7: =B36 -> Revenue - new screens | J7: =J38 -> 30000 | K7: =K38 -> 30000 | L7: =L38 -> 0 | M7: =M38 -> 30000 | N7: =N38 -> 30000 | O7: =O38 -> 30000 | P7: =P38 -> 60000 | Q7: =Q38 -> 0 | ... BQ7: =BQ38 -> 62920
B8: =B40 -> Revenue - set up and installation/Survey/wall mount | J8: =J42 -> 2250 | K8: =K42 -> 10050 | L8: =L42 -> 5620 | M8: =M42 -> 19673 | N8: =N42 -> 14774 | O8: =O42 -> 110844 | P8: =P42 -> 31714 | Q8: =Q42 -> 16000 | ... BQ8: =BQ42 -> 67639
B9: =B44 -> Revenue - software set-up | J9: =J46 -> 4550 | K9: =K46 -> 1500 | L9: =L46 -> 0 | M9: =M46 -> 0 | N9: =N46 -> 1500 | O9: =O46 -> 1500 | P9: =P46 -> 3000 | Q9: =Q46 -> 0 | ... BQ9: =BQ46 -> 3146
B10: =B48 -> Revenue - other | J10: =J50 -> 0 | K10: =K50 -> 0 | L10: =L50 -> 0 | M10: =M50 -> 0 | N10: =N50 -> 0 | O10: =O50 -> 1890 | P10: =P50 -> 12743 | Q10: =Q50 -> 1450 | ... BQ10: =BQ50 -> 0
B11: =B52 -> Revenue - SCCI initial set up | J11: =J54 -> 0 | K11: =K54 -> 0 | L11: =L54 -> 0 | M11: =M54 -> 0 | N11: =N54 -> 0 | O11: =O54 -> 0 | P11: =P54 -> 0 | Q11: =Q54 -> 0 | ... BQ11: =BQ54 -> 5808
B12: =B56 -> Revenue - ISP £0 Capex initial set up | J12: =J58 -> 0 | K12: =K58 -> 0 | L12: =L58 -> 0 | M12: =M58 -> 0 | N12: =N58 -> 0 | O12: =O58 -> 0 | P12: =P58 -> 0 | Q12: =Q58 -> 0 | ... BQ12: =BQ58 -> 11616
B15: Total One Off Revenue | J15: =SUM(J7:J14) -> 36800 | K15: =SUM(K7:K14) -> 41550 | L15: =SUM(L7:L14) -> 5620 | M15: =SUM(M7:M14) -> 49673 | N15: =SUM(N7:N14) -> 46274 | O15: =SUM(O7:O14) -> 144234 | P15: =SUM(P7:P14) -> 107457 | Q15: =SUM(Q7:Q14) -> 17450 | ... BQ15: =SUM(BQ7:BQ14) -> 151129
B18: Recurring Revenue
B19: =B64 -> Revenue - Software | J19: =J66 -> 0 | K19: =K66 -> 6750 | L19: =L66 -> 9000 | M19: =M66 -> 12750 | N19: =N66 -> 13500 | O19: =O66 -> 13500 | P19: =P66 -> 16275 | Q19: =Q66 -> 17175 | ... BQ19: =BQ66 -> 195112.5
B20: =B68 -> Revenue - Per month rental | J20: =J72 -> 0 | K20: =K72 -> 0 | L20: =L72 -> 0 | M20: =M72 -> 0 | N20: =N72 -> 0 | O20: =O72 -> 0 | P20: =P72 -> 0 | Q20: =Q72 -> 0 | ... BQ20: =BQ72 -> 84548.75
B21: =B74 -> Revenue - Media and Advertising | J21: =J76 -> 0 | K21: =K76 -> 0 | L21: =L76 -> 0 | M21: =M76 -> 0 | N21: =N76 -> 0 | O21: =O76 -> 0 | P21: =P76 -> 0 | Q21: =Q76 -> 0 | ... BQ21: =BQ76 -> 195112.5
B22: =B98 -> Revenue - Managing Agent | J22: =J100 -> 0 | K22: =K100 -> 0 | L22: =L100 -> 0 | M22: =M100 -> 0 | N22: =N100 -> 0 | O22: =O100 -> 0 | P22: =P100 -> 0 | Q22: =Q100 -> 0 | ... BQ22: =BQ100 -> 228690
B23: =B78 -> Revenue - SCCI Software rental | J23: =J80 -> 0 | K23: =K80 -> 0 | L23: =L80 -> 0 | M23: =M80 -> 0 | N23: =N80 -> 0 | O23: =O80 -> 0 | P23: =P80 -> 0 | Q23: =Q80 -> 0 | ... BQ23: =BQ80 -> 155848
B24: =B82 -> Revenue - SCCI Media and Advertising | J24: =J84 -> 0 | K24: =K84 -> 0 | L24: =L84 -> 0 | M24: =M84 -> 0 | N24: =N84 -> 0 | O24: =O84 -> 0 | P24: =P84 -> 0 | Q24: =Q84 -> 0 | ... BQ24: =BQ84 -> 75988
B25: =B86 -> Revenue - ISP £0 Capex Software rental | J25: =J88 -> 0 | K25: =K88 -> 0 | L25: =L88 -> 0 | M25: =M88 -> 0 | N25: =N88 -> 0 | O25: =O88 -> 0 | P25: =P88 -> 0 | Q25: =Q88 -> 0 | ... BQ25: =BQ88 -> 190575
B26: =B90 -> Revenue - ISP £0 Capex Media and Advertising | J26: =J92 -> 0 | K26: =K92 -> 0 | L26: =L92 -> 0 | M26: =M92 -> 0 | N26: =N92 -> 0 | O26: =O92 -> 0 | P26: =P92 -> 0 | Q26: =Q92 -> 0 | ... BQ26: =BQ92 -> 111441
B27: =B94 -> Revenue - Other Media and Advertising | J27: =J96 -> 0 | K27: =K96 -> 0 | L27: =L96 -> 0 | M27: =M96 -> 0 | N27: =N96 -> 0 | O27: =O96 -> 0 | P27: =P96 -> 0 | Q27: =Q96 -> 0 | ... BQ27: =BQ96 -> 0
B28: =B102 -> Revenue - ISP £0 Capex Managing Agent | J28: =J104 -> 0 | K28: =K104 -> 0 | L28: =L104 -> 0 | M28: =M104 -> 0 | N28: =N104 -> 0 | O28: =O104 -> 0 | P28: =P104 -> 0 | Q28: =Q104 -> 0 | ... BQ28: =BQ104 -> 129228
B31: Total Recurring Revenue | J31: =SUM(J19:J30) -> 0 | K31: =SUM(K19:K30) -> 6750 | L31: =SUM(L19:L30) -> 9000 | M31: =SUM(M19:M30) -> 12750 | N31: =SUM(N19:N30) -> 13500 | O31: =SUM(O19:O30) -> 13500 | P31: =SUM(P19:P30) -> 16275 | Q31: =SUM(Q19:Q30) -> 17175 | ... BQ31: =SUM(BQ19:BQ30) -> 1366543.8
A33: Total
B35: One Off Revenue
B36: Revenue - new screens | J36: 30000 | K36: 30000 | L36: 0 | M36: 30000 | N36: 30000 | O36: 30000 | P36: 60000 | Q36: 0 | R36: =Inputs!R32*Inputs!R51 -> 0 | S36: =Inputs!S32*Inputs!S51 -> 0 | T36: =Inputs!T32*Inputs!T51 -> 0 | U36: =Inputs!U32*Inputs!U51 -> 0 | V36: =Inputs!V32*Inputs!V51 -> 0 | W36: =Inputs!W32*Inputs!W51 -> 30000 | X36: =Inputs!X32*Inputs!X51 -> 30000 | Y36: =Inputs!Y32*Inputs!Y51 -> 30000 | ... BQ36: =Inputs!BQ32*Inputs!BQ51 -> 62920
B38: Total | J38: =SUM(J36:J37) -> 30000 | K38: =SUM(K36:K37) -> 30000 | L38: =SUM(L36:L37) -> 0 | M38: =SUM(M36:M37) -> 30000 | N38: =SUM(N36:N37) -> 30000 | O38: =SUM(O36:O37) -> 30000 | P38: =SUM(P36:P37) -> 60000 | Q38: =SUM(Q36:Q37) -> 0 | ... BQ38: =SUM(BQ36:BQ37) -> 62920
B40: Revenue - set up and installation/Survey/wall mount | J40: 2250 | K40: =2250+7800 -> 10050 | L40: 5620 | M40: =2250+17423 -> 19673 | N40: =2250+12524 -> 14774 | O40: =2250+78094+30500 -> 110844 | P40: 31714 | Q40: 16000 | R40: 15750 | S40: =Inputs!S32*(Inputs!S52+Inputs!S53+Inputs!S54) -> 0 | T40: =Inputs!T32*(Inputs!T52+Inputs!T53+Inputs!T54) -> 0 | U40: =Inputs!U32*(Inputs!U52+Inputs!U53+Inputs!U54) -> 0 | V40: =Inputs!V32*(Inputs!V52+Inputs!V53+Inputs!V54) -> 0 | W40: =Inputs!W32*(Inputs!W52+Inputs!W53+Inputs!W54) -> 32250 | X40: =Inputs!X32*(Inputs!X52+Inputs!X53+Inputs!X54) -> 32250 | Y40: =Inputs!Y32*(Inputs!Y52+Inputs!Y53+Inputs!Y54) -> 32250 | Z40: =Inputs!Z32*(Inputs!Z52+Inputs!Z53+Inputs!Z54) -> 32250 | ... BQ40: =Inputs!BQ32*(Inputs!BQ52+Inputs!BQ53+Inputs!BQ54) -> 67639
B42: Total | J42: =SUM(J40:J41) -> 2250 | K42: =SUM(K40:K41) -> 10050 | L42: =SUM(L40:L41) -> 5620 | M42: =SUM(M40:M41) -> 19673 | N42: =SUM(N40:N41) -> 14774 | O42: =SUM(O40:O41) -> 110844 | P42: =SUM(P40:P41) -> 31714 | Q42: =SUM(Q40:Q41) -> 16000 | ... BQ42: =SUM(BQ40:BQ41) -> 67639
B44: Revenue - software set-up | J44: 4550 | K44: 1500 | L44: 0 | M44: 0 | N44: 1500 | O44: 1500 | P44: =Inputs!P32*Inputs!P55 -> 3000 | Q44: 0 | R44: =Inputs!R32*Inputs!R55 -> 0 | S44: =Inputs!S32*Inputs!S55 -> 0 | T44: =Inputs!T32*Inputs!T55 -> 0 | U44: =Inputs!U32*Inputs!U55 -> 0 | V44: =Inputs!V32*Inputs!V55 -> 0 | W44: =Inputs!W32*Inputs!W55 -> 1500 | X44: =Inputs!X32*Inputs!X55 -> 1500 | Y44: =Inputs!Y32*Inputs!Y55 -> 1500 | ... BQ44: =Inputs!BQ32*Inputs!BQ55 -> 3146
B46: Total | J46: =SUM(J44:J45) -> 4550 | K46: =SUM(K44:K45) -> 1500 | L46: =SUM(L44:L45) -> 0 | M46: =SUM(M44:M45) -> 0 | N46: =SUM(N44:N45) -> 1500 | O46: =SUM(O44:O45) -> 1500 | P46: =SUM(P44:P45) -> 3000 | Q46: =SUM(Q44:Q45) -> 0 | ... BQ46: =SUM(BQ44:BQ45) -> 3146
B48: Revenue - other | J48: =Inputs!J56 -> 0 | K48: =Inputs!K56 -> 0 | L48: =Inputs!L56 -> 0 | M48: =Inputs!M56 -> 0 | N48: =Inputs!N56 -> 0 | O48: 1890 | P48: 12743 | Q48: 1450 | R48: =Inputs!R56 -> 0 | S48: =Inputs!S56 -> 0 | T48: =Inputs!T56 -> 0 | U48: =Inputs!U56 -> 0 | V48: =Inputs!V56 -> 0 | W48: =Inputs!W56 -> 0 | X48: =Inputs!X56 -> 0 | Y48: =Inputs!Y56 -> 0 | ... BQ48: =Inputs!BQ56 -> 0
B50: Total | J50: =SUM(J48:J49) -> 0 | K50: =SUM(K48:K49) -> 0 | L50: =SUM(L48:L49) -> 0 | M50: =SUM(M48:M49) -> 0 | N50: =SUM(N48:N49) -> 0 | O50: =SUM(O48:O49) -> 1890 | P50: =SUM(P48:P49) -> 12743 | Q50: =SUM(Q48:Q49) -> 1450 | ... BQ50: =SUM(BQ48:BQ49) -> 0
B52: Revenue - SCCI initial set up | J52: =Inputs!J36*Inputs!J68 -> 0 | K52: =Inputs!K36*Inputs!K68 -> 0 | L52: =Inputs!L36*Inputs!L68 -> 0 | M52: =Inputs!M36*Inputs!M68 -> 0 | N52: =Inputs!N36*Inputs!N68 -> 0 | O52: =Inputs!O36*Inputs!O68 -> 0 | P52: =Inputs!P36*Inputs!P68 -> 0 | Q52: =Inputs!Q36*Inputs!Q68 -> 0 | ... BQ52: =Inputs!BQ36*Inputs!BQ68 -> 5808
B54: Total | J54: =SUM(J52:J53) -> 0 | K54: =SUM(K52:K53) -> 0 | L54: =SUM(L52:L53) -> 0 | M54: =SUM(M52:M53) -> 0 | N54: =SUM(N52:N53) -> 0 | O54: =SUM(O52:O53) -> 0 | P54: =SUM(P52:P53) -> 0 | Q54: =SUM(Q52:Q53) -> 0 | ... BQ54: =SUM(BQ52:BQ53) -> 5808
B56: Revenue - ISP £0 Capex initial set up | J56: =Inputs!J40*Inputs!J75 -> 0 | K56: =Inputs!K40*Inputs!K75 -> 0 | L56: =Inputs!L40*Inputs!L75 -> 0 | M56: =Inputs!M40*Inputs!M75 -> 0 | N56: =Inputs!N40*Inputs!N75 -> 0 | O56: =Inputs!O40*Inputs!O75 -> 0 | P56: =Inputs!P40*Inputs!P75 -> 0 | Q56: =Inputs!Q40*Inputs!Q75 -> 0 | ... BQ56: =Inputs!BQ40*Inputs!BQ75 -> 11616
B58: Total | J58: =SUM(J56:J57) -> 0 | K58: =SUM(K56:K57) -> 0 | L58: =SUM(L56:L57) -> 0 | M58: =SUM(M56:M57) -> 0 | N58: =SUM(N56:N57) -> 0 | O58: =SUM(O56:O57) -> 0 | P58: =SUM(P56:P57) -> 0 | Q58: =SUM(Q56:Q57) -> 0 | ... BQ58: =SUM(BQ56:BQ57) -> 11616
B63: Recurring Revenue
B64: Revenue - Software | J64: 0 | K64: 6750 | L64: 9000 | M64: 12750 | N64: 13500 | O64: 13500 | P64: 16275 | Q64: 17175 | R64: =Inputs!Q33*Inputs!R59 -> 22500 | S64: =Inputs!R33*Inputs!S59 -> 22500 | T64: =Inputs!S33*Inputs!T59 -> 22500 | U64: =Inputs!T33*Inputs!U59 -> 22500 | V64: =Inputs!U33*Inputs!V59 -> 22500 | W64: =Inputs!V33*Inputs!W59 -> 22500 | X64: =Inputs!W33*Inputs!X59 -> 24750 | Y64: =Inputs!X33*Inputs!Y59 -> 27000 | ... BQ64: =Inputs!BP33*Inputs!BQ59 -> 195112.5
B66: Total | J66: =SUM(J64:J65) -> 0 | K66: =SUM(K64:K65) -> 6750 | L66: =SUM(L64:L65) -> 9000 | M66: =SUM(M64:M65) -> 12750 | N66: =SUM(N64:N65) -> 13500 | O66: =SUM(O64:O65) -> 13500 | P66: =SUM(P64:P65) -> 16275 | Q66: =SUM(Q64:Q65) -> 17175 | ... BQ66: =SUM(BQ64:BQ65) -> 195112.5
B68: Revenue - Per month rental
B69: Per Month Rental 50 or below | J69: 0 | K69: 0 | L69: 0 | M69: 0 | N69: 0 | O69: 0 | P69: =(Inputs!O33*Inputs!P62)*Inputs!P60 -> 0 | Q69: =(Inputs!P33*Inputs!Q62)*Inputs!Q60 -> 0 | R69: =(Inputs!Q33*Inputs!R62)*Inputs!R60 -> 0 | S69: =(Inputs!R33*Inputs!S62)*Inputs!S60 -> 0 | T69: =(Inputs!S33*Inputs!T62)*Inputs!T60 -> 5250 | U69: =(Inputs!T33*Inputs!U62)*Inputs!U60 -> 5250 | V69: =(Inputs!U33*Inputs!V62)*Inputs!V60 -> 5250 | W69: =(Inputs!V33*Inputs!W62)*Inputs!W60 -> 5250 | ... BQ69: =(Inputs!BP33*Inputs!BQ62)*Inputs!BQ60 -> 45526.25
B70: Per Month Rental 50 or above | J70: 0 | K70: 0 | L70: 0 | M70: 0 | N70: 0 | O70: 0 | P70: =(Inputs!O33*Inputs!P63)*Inputs!P61 -> 0 | Q70: =(Inputs!P33*Inputs!Q63)*Inputs!Q61 -> 0 | R70: =(Inputs!Q33*Inputs!R63)*Inputs!R61 -> 0 | S70: =(Inputs!R33*Inputs!S63)*Inputs!S61 -> 0 | T70: =(Inputs!S33*Inputs!T63)*Inputs!T61 -> 4500 | U70: =(Inputs!T33*Inputs!U63)*Inputs!U61 -> 4500 | V70: =(Inputs!U33*Inputs!V63)*Inputs!V61 -> 4500 | W70: =(Inputs!V33*Inputs!W63)*Inputs!W61 -> 4500 | ... BQ70: =(Inputs!BP33*Inputs!BQ63)*Inputs!BQ61 -> 39022.5
B72: Total | J72: =SUM(J68:J71) -> 0 | K72: =SUM(K68:K71) -> 0 | L72: =SUM(L68:L71) -> 0 | M72: =SUM(M68:M71) -> 0 | N72: =SUM(N68:N71) -> 0 | O72: =SUM(O68:O71) -> 0 | P72: =SUM(P68:P71) -> 0 | Q72: =SUM(Q68:Q71) -> 0 | ... BQ72: =SUM(BQ68:BQ71) -> 84548.75
B74: Revenue - Media and Advertising | J74: 0 | K74: 0 | L74: 0 | M74: 0 | N74: 0 | O74: 0 | P74: =Inputs!O33*Inputs!P64 -> 0 | Q74: =Inputs!P33*Inputs!Q64 -> 0 | R74: =Inputs!Q33*Inputs!R64 -> 0 | S74: =Inputs!R33*Inputs!S64 -> 0 | T74: =Inputs!S33*Inputs!T64 -> 0 | U74: =Inputs!T33*Inputs!U64 -> 15000 | V74: =Inputs!U33*Inputs!V64 -> 15000 | W74: =Inputs!V33*Inputs!W64 -> 15000 | ... BQ74: =Inputs!BP33*Inputs!BQ64 -> 195112.5
B76: Total | J76: =SUM(J74:J75) -> 0 | K76: =SUM(K74:K75) -> 0 | L76: =SUM(L74:L75) -> 0 | M76: =SUM(M74:M75) -> 0 | N76: =SUM(N74:N75) -> 0 | O76: =SUM(O74:O75) -> 0 | P76: =SUM(P74:P75) -> 0 | Q76: =SUM(Q74:Q75) -> 0 | ... BQ76: =SUM(BQ74:BQ75) -> 195112.5
B78: Revenue - SCCI Software rental | J78: =Inputs!J37*Inputs!J71 -> 0 | K78: =Inputs!K37*Inputs!K71 -> 0 | L78: =Inputs!L37*Inputs!L71 -> 0 | M78: =Inputs!M37*Inputs!M71 -> 0 | N78: =Inputs!N37*Inputs!N71 -> 0 | O78: =Inputs!O37*Inputs!O71 -> 0 | P78: =Inputs!P37*Inputs!P71 -> 0 | Q78: =Inputs!Q37*Inputs!Q71 -> 0 | ... BQ78: =Inputs!BQ37*Inputs!BQ71 -> 155848
B80: Total | J80: =SUM(J78:J79) -> 0 | K80: =SUM(K78:K79) -> 0 | L80: =SUM(L78:L79) -> 0 | M80: =SUM(M78:M79) -> 0 | N80: =SUM(N78:N79) -> 0 | O80: =SUM(O78:O79) -> 0 | P80: =SUM(P78:P79) -> 0 | Q80: =SUM(Q78:Q79) -> 0 | ... BQ80: =SUM(BQ78:BQ79) -> 155848
B82: Revenue - SCCI Media and Advertising | J82: =Inputs!I37*Inputs!J72 -> 0 | K82: =Inputs!J37*Inputs!K72 -> 0 | L82: =Inputs!K37*Inputs!L72 -> 0 | M82: =Inputs!L37*Inputs!M72 -> 0 | N82: =Inputs!M37*Inputs!N72 -> 0 | O82: =Inputs!N37*Inputs!O72 -> 0 | P82: =Inputs!O37*Inputs!P72 -> 0 | Q82: =Inputs!P37*Inputs!Q72 -> 0 | ... BQ82: =Inputs!BP37*Inputs!BQ72 -> 75988
B84: Total | J84: =SUM(J82:J83) -> 0 | K84: =SUM(K82:K83) -> 0 | L84: =SUM(L82:L83) -> 0 | M84: =SUM(M82:M83) -> 0 | N84: =SUM(N82:N83) -> 0 | O84: =SUM(O82:O83) -> 0 | P84: =SUM(P82:P83) -> 0 | Q84: =SUM(Q82:Q83) -> 0 | ... BQ84: =SUM(BQ82:BQ83) -> 75988
B86: Revenue - ISP £0 Capex Software rental | J86: =Inputs!J41*Inputs!J78 -> 0 | K86: =Inputs!K41*Inputs!K78 -> 0 | L86: =Inputs!L41*Inputs!L78 -> 0 | M86: =Inputs!M41*Inputs!M78 -> 0 | N86: =Inputs!N41*Inputs!N78 -> 0 | O86: =Inputs!O41*Inputs!O78 -> 0 | P86: =Inputs!P41*Inputs!P78 -> 0 | Q86: =Inputs!Q41*Inputs!Q78 -> 0 | ... BQ86: =Inputs!BQ41*Inputs!BQ78 -> 190575
B88: Total | J88: =SUM(J86:J87) -> 0 | K88: =SUM(K86:K87) -> 0 | L88: =SUM(L86:L87) -> 0 | M88: =SUM(M86:M87) -> 0 | N88: =SUM(N86:N87) -> 0 | O88: =SUM(O86:O87) -> 0 | P88: =SUM(P86:P87) -> 0 | Q88: =SUM(Q86:Q87) -> 0 | ... BQ88: =SUM(BQ86:BQ87) -> 190575
B90: Revenue - ISP £0 Capex Media and Advertising | J90: =Inputs!I41*Inputs!J79 -> 0 | K90: =Inputs!J41*Inputs!K79 -> 0 | L90: =Inputs!K41*Inputs!L79 -> 0 | M90: =Inputs!L41*Inputs!M79 -> 0 | N90: =Inputs!M41*Inputs!N79 -> 0 | O90: =Inputs!N41*Inputs!O79 -> 0 | P90: =Inputs!O41*Inputs!P79 -> 0 | Q90: =Inputs!P41*Inputs!Q79 -> 0 | ... BQ90: =Inputs!BP41*Inputs!BQ79 -> 111441
B92: Total | J92: =SUM(J90:J91) -> 0 | K92: =SUM(K90:K91) -> 0 | L92: =SUM(L90:L91) -> 0 | M92: =SUM(M90:M91) -> 0 | N92: =SUM(N90:N91) -> 0 | O92: =SUM(O90:O91) -> 0 | P92: =SUM(P90:P91) -> 0 | Q92: =SUM(Q90:Q91) -> 0 | ... BQ92: =SUM(BQ90:BQ91) -> 111441
B94: Revenue - Other Media and Advertising | J94: =Inputs!I45*Inputs!J83 -> 0 | K94: =Inputs!J45*Inputs!K83 -> 0 | L94: =Inputs!K45*Inputs!L83 -> 0 | M94: =Inputs!L45*Inputs!M83 -> 0 | N94: =Inputs!M45*Inputs!N83 -> 0 | O94: =Inputs!N45*Inputs!O83 -> 0 | P94: =Inputs!O45*Inputs!P83 -> 0 | Q94: =Inputs!P45*Inputs!Q83 -> 0 | ... BQ94: =Inputs!BP45*Inputs!BQ83 -> 0
B96: Total | J96: =SUM(J94:J95) -> 0 | K96: =SUM(K94:K95) -> 0 | L96: =SUM(L94:L95) -> 0 | M96: =SUM(M94:M95) -> 0 | N96: =SUM(N94:N95) -> 0 | O96: =SUM(O94:O95) -> 0 | P96: =SUM(P94:P95) -> 0 | Q96: =SUM(Q94:Q95) -> 0 | ... BQ96: =SUM(BQ94:BQ95) -> 0
B98: Revenue - Managing Agent | Y98: =Inputs!Y65*Inputs!S33 -> 30000 | Z98: =Inputs!Z65*Inputs!T33 -> 30000 | AA98: =Inputs!AA65*Inputs!U33 -> 30000 | AB98: =Inputs!AB65*Inputs!V33 -> 30000 | AC98: =Inputs!AC65*Inputs!W33 -> 33000 | AD98: =Inputs!AD65*Inputs!X33 -> 36000 | AE98: =Inputs!AE65*Inputs!Y33 -> 39000 | AF98: =Inputs!AF65*Inputs!Z33 -> 42000 | ... BQ98: =Inputs!BQ65*Inputs!BK33 -> 228690
B100: Total | J100: =SUM(J98:J99) -> 0 | K100: =SUM(K98:K99) -> 0 | L100: =SUM(L98:L99) -> 0 | M100: =SUM(M98:M99) -> 0 | N100: =SUM(N98:N99) -> 0 | O100: =SUM(O98:O99) -> 0 | P100: =SUM(P98:P99) -> 0 | Q100: =SUM(Q98:Q99) -> 0 | ... BQ100: =SUM(BQ98:BQ99) -> 228690
B102: Revenue - ISP £0 Capex Managing Agent | Y102: =Inputs!Y80*Inputs!S41 -> 200 | Z102: =Inputs!Z80*Inputs!T41 -> 1200 | AA102: =Inputs!AA80*Inputs!U41 -> 2200 | AB102: =Inputs!AB80*Inputs!V41 -> 3200 | AC102: =Inputs!AC80*Inputs!W41 -> 5200 | AD102: =Inputs!AD80*Inputs!X41 -> 7200 | AE102: =Inputs!AE80*Inputs!Y41 -> 9200 | AF102: =Inputs!AF80*Inputs!Z41 -> 11200 | ... BQ102: =Inputs!BQ80*Inputs!BK41 -> 129228
B104: Total | J104: =SUM(J102:J103) -> 0 | K104: =SUM(K102:K103) -> 0 | L104: =SUM(L102:L103) -> 0 | M104: =SUM(M102:M103) -> 0 | N104: =SUM(N102:N103) -> 0 | O104: =SUM(O102:O103) -> 0 | P104: =SUM(P102:P103) -> 0 | Q104: =SUM(Q102:Q103) -> 0 | ... BQ104: =SUM(BQ102:BQ103) -> 129228

Sheet COS and Overheads
A1: Business 1
A2: Cost of Sales and Overheads | J2: =Timing!J2 -> 44986 | K2: =Timing!K2 -> 45017 | L2: =Timing!L2 -> 45047 | M2: =Timing!M2 -> 45078 | N2: =Timing!N2 -> 45108 | O2: =Timing!O2 -> 45139 | P2: =Timing!P2 -> 45170 | Q2: =Timing!Q2 -> 45200 | ... BQ2: =Timing!BQ2 -> 46784
J3: =Timing!J3 -> 45016 | K3: =Timing!K3 -> 45046 | L3: =Timing!L3 -> 45077 | M3: =Timing!M3 -> 45107 | N3: =Timing!N3 -> 45138 | O3: =Timing!O3 -> 45169 | P3: =Timing!P3 -> 45199 | Q3: =Timing!Q3 -> 45230 | ... BQ3: =Timing!BQ3 -> 46812
B5: COS Summary
B6: =B52 -> ISP capex - Cost of screens | J6: =J54 -> 18000 | K6: =K54 -> 0 | L6: =L54 -> 18000 | M6: =M54 -> 18000 | N6: =N54 -> 18000 | O6: =O54 -> 18000 | P6: =P54 -> 40692 | Q6: =Q54 -> 0 | ... BQ6: =BQ54 -> 32396
B7: =B57 -> ISP capex - Screen Set up and Installation | J7: =J59 -> 0 | K7: =K59 -> 7364 | L7: =L59 -> 8896 | M7: =M59 -> 5055 | N7: =N59 -> 10047 | O7: =O59 -> 60033 | P7: =P59 -> 17604 | Q7: =Q59 -> 3285 | ... BQ7: =BQ59 -> 31200
B8: =B62 -> ISP capex - Screen Wall mount | J8: =J64 -> 1425 | K8: =K64 -> 0 | L8: =L64 -> 1425 | M8: =M64 -> 1500 | N8: =N64 -> 1500 | O8: =O64 -> 1425 | P8: =P64 -> 3207 | Q8: =Q64 -> 0 | ... BQ8: =BQ64 -> 2496
B9: =B67 -> ISP capex - Screen Survey cost | J9: =J69 -> 0 | K9: =K69 -> 0 | L9: =L69 -> 0 | M9: =M69 -> 0 | N9: =N69 -> 0 | O9: =O69 -> 21800 | P9: =P69 -> 476 | Q9: =Q69 -> 4000 | ... BQ9: =BQ69 -> 10400
B10: =B72 -> ISP capex - Software charge | J10: =J74 -> 0 | K10: =K74 -> 0 | L10: =L74 -> 484 | M10: =M74 -> 484 | N10: =N74 -> 1760 | O10: =O74 -> 1804 | P10: =P74 -> 2266 | Q10: =Q74 -> 3344 | ... BQ10: =BQ74 -> 49545
B11: =B77 -> ISP capex - Other costs | J11: =J79 -> 0 | K11: =K79 -> 0 | L11: =L79 -> 0 | M11: =M79 -> 0 | N11: =N79 -> 0 | O11: =O79 -> 345 | P11: =P79 -> 45 | Q11: =Q79 -> 0 | ... BQ11: =BQ79 -> 0
B12: =B82 -> ISP capex - Media and Advertising | J12: =J84 -> 0 | K12: =K84 -> 0 | L12: =L84 -> 0 | M12: =M84 -> 0 | N12: =N84 -> 0 | O12: =O84 -> 0 | P12: =P84 -> 0 | Q12: =Q84 -> 0 | ... BQ12: =BQ84 -> 129000
B13: =B87 -> SCCI - Software charge | J13: =J89 -> 0 | K13: =K89 -> 0 | L13: =L89 -> 0 | M13: =M89 -> 0 | N13: =N89 -> 0 | O13: =O89 -> 0 | P13: =P89 -> 0 | Q13: =Q89 -> 0 | ... BQ13: =BQ89 -> 28980
B14: =B92 -> SCCI - 5g ongoing cost | J14: =J94 -> 0 | K14: =K94 -> 0 | L14: =L94 -> 0 | M14: =M94 -> 0 | N14: =N94 -> 0 | O14: =O94 -> 0 | P14: =P94 -> 0 | Q14: =Q94 -> 0 | ... BQ14: =BQ94 -> 3864
B15: =B97 -> ISP Funds £0 Capex - Software charge | J15: =J99 -> 0 | K15: =K99 -> 0 | L15: =L99 -> 0 | M15: =M99 -> 0 | N15: =N99 -> 0 | O15: =O99 -> 0 | P15: =P99 -> 0 | Q15: =Q99 -> 0 | ... BQ15: =BQ99 -> 28350
B16: =B102 -> ISP Funds £0 Capex - 5g ongoing cost | J16: =J104 -> 0 | K16: =K104 -> 0 | L16: =L104 -> 0 | M16: =M104 -> 0 | N16: =N104 -> 0 | O16: =O104 -> 0 | P16: =P104 -> 0 | Q16: =Q104 -> 0 | ... BQ16: =BQ104 -> 3780
B17: =B107 -> Other - Software charge | J17: =J109 -> 0 | K17: =K109 -> 0 | L17: =L109 -> 0 | M17: =M109 -> 0 | N17: =N109 -> 0 | O17: =O109 -> 0 | P17: =P109 -> 0 | Q17: =Q109 -> 0 | ... BQ17: =BQ109 -> 0
B18: =B112 -> Other - 5g ongoing cost | J18: =J114 -> 0 | K18: =K114 -> 0 | L18: =L114 -> 0 | M18: =M114 -> 0 | N18: =N114 -> 0 | O18: =O114 -> 0 | P18: =P114 -> 0 | Q18: =Q114 -> 0 | ... BQ18: =BQ114 -> 0
B19: =B117 -> Other - Freeholder cost | J19: =J119 -> 0 | K19: =K119 -> 0 | L19: =L119 -> 0 | M19: =M119 -> 0 | N19: =N119 -> 0 | O19: =O119 -> 0 | P19: =P119 -> 0 | Q19: =Q119 -> 0 | ... BQ19: =BQ119 -> 173100
B25: Total COS | J25: =SUM(J6:J24) -> 19425 | K25: =SUM(K6:K24) -> 7364 | L25: =SUM(L6:L24) -> 28805 | M25: =SUM(M6:M24) -> 25039 | N25: =SUM(N6:N24) -> 31307 | O25: =SUM(O6:O24) -> 103407 | P25: =SUM(P6:P24) -> 64290 | Q25: =SUM(Q6:Q24) -> 10629 | ... BQ25: =SUM(BQ6:BQ24) -> 493111
B28: Overhead Summary
B29: Rent | J29: =J137 -> 0 | K29: =K137 -> 0 | L29: =L137 -> 0 | M29: =M137 -> 0 | N29: =N137 -> 0 | O29: =O137 -> 0 | P29: =P137 -> 0 | Q29: =Q137 -> 0 | ... BQ29: =BQ137 -> 2500
B30: Rates | J30: =J143 -> 0 | K30: =K143 -> 0 | L30: =L143 -> 0 | M30: =M143 -> 0 | N30: =N143 -> 0 | O30: =O143 -> 0 | P30: =P143 -> 0 | Q30: =Q143 -> 0 | ... BQ30: =BQ143 -> 0
B31: Recruitment Costs | J31: =J149 -> 0 | K31: =K149 -> 0 | L31: =L149 -> 0 | M31: =M149 -> 0 | N31: =N149 -> 0 | O31: =O149 -> 0 | P31: =P149 -> 0 | Q31: =Q149 -> 0 | ... BQ31: =BQ149 -> 0
B32: Repairs and maintenance | J32: =J155 -> 0 | K32: =K155 -> 0 | L32: =L155 -> 0 | M32: =M155 -> 0 | N32: =N155 -> 0 | O32: =O155 -> 0 | P32: =P155 -> 0 | Q32: =Q155 -> 0 | ... BQ32: =BQ155 -> 2156.25
B33: Insurance | J33: =J164 -> 0 | K33: =K164 -> 0 | L33: =L164 -> 0 | M33: =M164 -> 0 | N33: =N164 -> 0 | O33: =O164 -> 0 | P33: =P164 -> 0 | Q33: =Q164 -> 0 | ... BQ33: =BQ164 -> 3050
B34: Computer running costs | J34: =J172 -> 2575 | K34: =K172 -> 1500 | L34: =L172 -> 170 | M34: =M172 -> 2079 | N34: =N172 -> 0 | O34: =O172 -> 170 | P34: =P172 -> 0 | Q34: =Q172 -> 18850 | ... BQ34: =BQ172 -> 1270
B35: Travelling expenses | J35: =J178 -> 0 | K35: =K178 -> 399 | L35: =L178 -> 230 | M35: =M178 -> 156 | N35: =N178 -> 2199 | O35: =O178 -> 0 | P35: =P178 -> 0 | Q35: =Q178 -> 0 | ... BQ35: =BQ178 -> 7000
B36: Legal and professional fees | J36: =J184 -> 0 | K36: =K184 -> 0 | L36: =L184 -> 0 | M36: =M184 -> 0 | N36: =N184 -> 0 | O36: =O184 -> 0 | P36: =P184 -> 0 | Q36: =Q184 -> 0 | ... BQ36: =BQ184 -> 2000
B37: Consultancy | J37: =J190 -> 0 | K37: =K190 -> 0 | L37: =L190 -> 15000 | M37: =M190 -> 32550 | N37: =N190 -> 30000 | O37: =O190 -> 30000 | P37: =P190 -> 30000 | Q37: =Q190 -> 40368 | ... BQ37: =BQ190 -> 0
B38: Audit and accountancy fees | J38: =J196 -> 600 | K38: =K196 -> 0 | L38: =L196 -> 600 | M38: =M196 -> 600 | N38: =N196 -> 1000 | O38: =O196 -> 1000 | P38: =P196 -> 1000 | Q38: =Q196 -> 1000 | ... BQ38: =BQ196 -> 1800
B39: Office costs | J39: =J202 -> 72 | K39: =K202 -> 0 | L39: =L202 -> 0 | M39: =M202 -> 0 | N39: =N202 -> 195 | O39: =O202 -> 195 | P39: =P202 -> 0 | Q39: =Q202 -> 0 | ... BQ39: =BQ202 -> 2000
B40: Bank charges | J40: =J208 -> 0 | K40: =K208 -> 0 | L40: =L208 -> 0 | M40: =M208 -> 0 | N40: =N208 -> 0 | O40: =O208 -> 0 | P40: =P208 -> 0 | Q40: =Q208 -> 0 | ... BQ40: =BQ208 -> 0
B41: Printing, postage and stationery | J41: =J214 -> 0 | K41: =K214 -> 305 | L41: =L214 -> 0 | M41: =M214 -> 0 | N41: =N214 -> 0 | O41: =O214 -> 0 | P41: =P214 -> 0 | Q41: =Q214 -> 0 | ... BQ41: =BQ214 -> 1000
B42: Marketing and PR | J42: =J220 -> 0 | K42: =K220 -> 0 | L42: =L220 -> 0 | M42: =M220 -> 0 | N42: =N220 -> 0 | O42: =O220 -> 0 | P42: =P220 -> 0 | Q42: =Q220 -> 0 | ... BQ42: =BQ220 -> 7000
B43: Telephone | J43: =J226 -> 0 | K43: =K226 -> 0 | L43: =L226 -> 0 | M43: =M226 -> 0 | N43: =N226 -> 0 | O43: =O226 -> 0 | P43: =P226 -> 0 | Q43: =Q226 -> 0 | ... BQ43: =BQ226 -> 1500
B44: Entertaining | J44: =J232 -> 0 | K44: =K232 -> 0 | L44: =L232 -> 0 | M44: =M232 -> 0 | N44: =N232 -> 0 | O44: =O232 -> 0 | P44: =P232 -> 0 | Q44: =Q232 -> 6171 | ... BQ44: =BQ232 -> 6000
B45: Sundry expenses | J45: =J238 -> 5 | K45: =K238 -> 194 | L45: =L238 -> 19 | M45: =M238 -> 19 | N45: =N238 -> 33 | O45: =O238 -> 33 | P45: =P238 -> 33 | Q45: =Q238 -> 35 | ... BQ45: =BQ238 -> 1033
B46: Total Overheads | J46: =SUM(J29:J45) -> 3252 | K46: =SUM(K29:K45) -> 2398 | L46: =SUM(L29:L45) -> 16019 | M46: =SUM(M29:M45) -> 35404 | N46: =SUM(N29:N45) -> 33427 | O46: =SUM(O29:O45) -> 31398 | P46: =SUM(P29:P45) -> 31033 | Q46: =SUM(Q29:Q45) -> 66424 | ... BQ46: =SUM(BQ29:BQ45) -> 38309.25
B50: COS
B52: ISP capex - Cost of screens | J52: 18000 | K52: 0 | L52: 18000 | M52: 18000 | N52: 18000 | O52: 18000 | P52: =36000+ 4692 -> 40692 | Q52: 0 | R52: =Inputs!R32*Inputs!R89 -> 0 | S52: =Inputs!S32*Inputs!S89 -> 0 | T52: =Inputs!T32*Inputs!T89 -> 0 | U52: =Inputs!U32*Inputs!U89 -> 0 | V52: =Inputs!V32*Inputs!V89 -> 0 | W52: =Inputs!W32*Inputs!W89 -> 18690 | X52: =Inputs!X32*Inputs!X89 -> 18690 | Y52: =Inputs!Y32*Inputs!Y89 -> 18690 | ... BQ52: =Inputs!BQ32*Inputs!BQ89 -> 32396
B54: Total | J54: =SUM(J52:J53) -> 18000 | K54: =SUM(K52:K53) -> 0 | L54: =SUM(L52:L53) -> 18000 | M54: =SUM(M52:M53) -> 18000 | N54: =SUM(N52:N53) -> 18000 | O54: =SUM(O52:O53) -> 18000 | P54: =SUM(P52:P53) -> 40692 | Q54: =SUM(Q52:Q53) -> 0 | ... BQ54: =SUM(BQ52:BQ53) -> 32396
B57: ISP capex - Screen Set up and Installation | J57: 0 | K57: 7364 | L57: 8896 | M57: 5055 | N57: 10047 | O57: 60033 | P57: =16454+1150 -> 17604 | Q57: 3285 | R57: =Inputs!R32*Inputs!R90 -> 0 | S57: =Inputs!S32*Inputs!S90 -> 0 | T57: =Inputs!T32*Inputs!T90 -> 0 | U57: =Inputs!U32*Inputs!U90 -> 0 | V57: =Inputs!V32*Inputs!V90 -> 0 | W57: =Inputs!W32*Inputs!W90 -> 18000 | X57: =Inputs!X32*Inputs!X90 -> 18000 | Y57: =Inputs!Y32*Inputs!Y90 -> 18000 | ... BQ57: =Inputs!BQ32*Inputs!BQ90 -> 31200
B59: Total | J59: =SUM(J57:J58) -> 0 | K59: =SUM(K57:K58) -> 7364 | L59: =SUM(L57:L58) -> 8896 | M59: =SUM(M57:M58) -> 5055 | N59: =SUM(N57:N58) -> 10047 | O59: =SUM(O57:O58) -> 60033 | P59: =SUM(P57:P58) -> 17604 | Q59: =SUM(Q57:Q58) -> 3285 | ... BQ59: =SUM(BQ57:BQ58) -> 31200
B62: ISP capex - Screen Wall mount | J62: 1425 | K62: 0 | L62: 1425 | M62: 1500 | N62: 1500 | O62: 1425 | P62: =2850+357 -> 3207 | Q62: =Inputs!Q32*Inputs!Q91 -> 0 | R62: =Inputs!R32*Inputs!R91 -> 0 | S62: =Inputs!S32*Inputs!S91 -> 0 | T62: =Inputs!T32*Inputs!T91 -> 0 | U62: =Inputs!U32*Inputs!U91 -> 0 | V62: =Inputs!V32*Inputs!V91 -> 0 | W62: =Inputs!W32*Inputs!W91 -> 1440 | X62: =Inputs!X32*Inputs!X91 -> 1440 | ... BQ62: =Inputs!BQ32*Inputs!BQ91 -> 2496
B64: Total | J64: =SUM(J62:J63) -> 1425 | K64: =SUM(K62:K63) -> 0 | L64: =SUM(L62:L63) -> 1425 | M64: =SUM(M62:M63) -> 1500 | N64: =SUM(N62:N63) -> 1500 | O64: =SUM(O62:O63) -> 1425 | P64: =SUM(P62:P63) -> 3207 | Q64: =SUM(Q62:Q63) -> 0 | ... BQ64: =SUM(BQ62:BQ63) -> 2496
B67: ISP capex - Screen Survey cost | J67: 0 | K67: 0 | L67: 0 | M67: 0 | N67: 0 | O67: 21800 | P67: 476 | Q67: 4000 | R67: =Inputs!R32*Inputs!R92 -> 0 | S67: =Inputs!S32*Inputs!S92 -> 0 | T67: =Inputs!T32*Inputs!T92 -> 0 | U67: =Inputs!U32*Inputs!U92 -> 0 | V67: =Inputs!V32*Inputs!V92 -> 0 | W67: =Inputs!W32*Inputs!W92 -> 6000 | X67: =Inputs!X32*Inputs!X92 -> 6000 | Y67: =Inputs!Y32*Inputs!Y92 -> 6000 | ... BQ67: =Inputs!BQ32*Inputs!BQ92 -> 10400
B69: Total | J69: =SUM(J67:J68) -> 0 | K69: =SUM(K67:K68) -> 0 | L69: =SUM(L67:L68) -> 0 | M69: =SUM(M67:M68) -> 0 | N69: =SUM(N67:N68) -> 0 | O69: =SUM(O67:O68) -> 21800 | P69: =SUM(P67:P68) -> 476 | Q69: =SUM(Q67:Q68) -> 4000 | ... BQ69: =SUM(BQ67:BQ68) -> 10400
B72: ISP capex - Software charge | J72: 0 | K72: 0 | L72: 484 | M72: 484 | N72: 1760 | O72: 1804 | P72: 2266 | Q72: 3344 | R72: =Inputs!R33*Inputs!R93 -> 6750 | S72: =Inputs!S33*Inputs!S93 -> 6750 | T72: =Inputs!T33*Inputs!T93 -> 6750 | U72: =Inputs!U33*Inputs!U93 -> 6750 | V72: =Inputs!V33*Inputs!V93 -> 6750 | W72: =Inputs!W33*Inputs!W93 -> 7425 | X72: =Inputs!X33*Inputs!X93 -> 8100 | Y72: =Inputs!Y33*Inputs!Y93 -> 8775 | ... BQ72: =Inputs!BQ33*Inputs!BQ93 -> 49545
B74: Total | J74: =SUM(J72:J73) -> 0 | K74: =SUM(K72:K73) -> 0 | L74: =SUM(L72:L73) -> 484 | M74: =SUM(M72:M73) -> 484 | N74: =SUM(N72:N73) -> 1760 | O74: =SUM(O72:O73) -> 1804 | P74: =SUM(P72:P73) -> 2266 | Q74: =SUM(Q72:Q73) -> 3344 | ... BQ74: =SUM(BQ72:BQ73) -> 49545
B77: ISP capex - Other costs | J77: 0 | K77: 0 | L77: 0 | M77: 0 | N77: 0 | O77: =345 -> 345 | P77: 45 | Q77: =Inputs!Q94 -> 0 | R77: =Inputs!R94 -> 0 | S77: =Inputs!S94 -> 0 | T77: =Inputs!T94 -> 0 | U77: =Inputs!U94 -> 0 | V77: =Inputs!V94 -> 0 | W77: =Inputs!W94 -> 0 | X77: =Inputs!X94 -> 0 | ... BQ77: =Inputs!BQ94 -> 0
B79: Total | J79: =SUM(J77:J78) -> 0 | K79: =SUM(K77:K78) -> 0 | L79: =SUM(L77:L78) -> 0 | M79: =SUM(M77:M78) -> 0 | N79: =SUM(N77:N78) -> 0 | O79: =SUM(O77:O78) -> 345 | P79: =SUM(P77:P78) -> 45 | Q79: =SUM(Q77:Q78) -> 0 | ... BQ79: =SUM(BQ77:BQ78) -> 0
B82: ISP capex - Media and Advertising | J82: 0 | K82: 0 | L82: 0 | M82: 0 | N82: 0 | O82: 0 | P82: =Inputs!O33*Inputs!P95 -> 0 | Q82: =Inputs!P33*Inputs!Q95 -> 0 | R82: =Inputs!Q33*Inputs!R95 -> 0 | S82: 10000 | T82: 10000 | U82: 10000 | V82: =Inputs!U33*Inputs!V95 -> 18000 | W82: =Inputs!V33*Inputs!W95 -> 18000 | X82: =Inputs!W33*Inputs!X95 -> 19800 | Y82: =Inputs!X33*Inputs!Y95 -> 21600 | Z82: =Inputs!Y33*Inputs!Z95 -> 23400 | AA82: =Inputs!Z33*Inputs!AA95 -> 25200 | AB82: =Inputs!AA33*Inputs!AB95 -> 27000 | AC82: =Inputs!AB33*Inputs!AC95 -> 28800 | ... BQ82: =Inputs!BP33*Inputs!BQ95 -> 129000
B84: Total | J84: =SUM(J82:J83) -> 0 | K84: =SUM(K82:K83) -> 0 | L84: =SUM(L82:L83) -> 0 | M84: =SUM(M82:M83) -> 0 | N84: =SUM(N82:N83) -> 0 | O84: =SUM(O82:O83) -> 0 | P84: =SUM(P82:P83) -> 0 | Q84: =SUM(Q82:Q83) -> 0 | ... BQ84: =SUM(BQ82:BQ83) -> 129000
B87: SCCI - Software charge | J87: =Inputs!J37*Inputs!J97 -> 0 | K87: =Inputs!K37*Inputs!K97 -> 0 | L87: =Inputs!L37*Inputs!L97 -> 0 | M87: =Inputs!M37*Inputs!M97 -> 0 | N87: =Inputs!N37*Inputs!N97 -> 0 | O87: =Inputs!O37*Inputs!O97 -> 0 | P87: =Inputs!P37*Inputs!P97 -> 0 | Q87: =Inputs!Q37*Inputs!Q97 -> 0 | ... BQ87: =Inputs!BQ37*Inputs!BQ97 -> 28980
B89: Total | J89: =SUM(J87:J88) -> 0 | K89: =SUM(K87:K88) -> 0 | L89: =SUM(L87:L88) -> 0 | M89: =SUM(M87:M88) -> 0 | N89: =SUM(N87:N88) -> 0 | O89: =SUM(O87:O88) -> 0 | P89: =SUM(P87:P88) -> 0 | Q89: =SUM(Q87:Q88) -> 0 | ... BQ89: =SUM(BQ87:BQ88) -> 28980
B92: SCCI - 5g ongoing cost | J92: =Inputs!J37*Inputs!J98 -> 0 | K92: =Inputs!K37*Inputs!K98 -> 0 | L92: =Inputs!L37*Inputs!L98 -> 0 | M92: =Inputs!M37*Inputs!M98 -> 0 | N92: =Inputs!N37*Inputs!N98 -> 0 | O92: =Inputs!O37*Inputs!O98 -> 0 | P92: =Inputs!P37*Inputs!P98 -> 0 | Q92: =Inputs!Q37*Inputs!Q98 -> 0 | ... BQ92: =Inputs!BQ37*Inputs!BQ98 -> 3864
B94: Total | J94: =SUM(J92:J93) -> 0 | K94: =SUM(K92:K93) -> 0 | L94: =SUM(L92:L93) -> 0 | M94: =SUM(M92:M93) -> 0 | N94: =SUM(N92:N93) -> 0 | O94: =SUM(O92:O93) -> 0 | P94: =SUM(P92:P93) -> 0 | Q94: =SUM(Q92:Q93) -> 0 | ... BQ94: =SUM(BQ92:BQ93) -> 3864
B97: ISP Funds £0 Capex - Software charge | J97: =Inputs!J41*Inputs!J100 -> 0 | K97: =Inputs!K41*Inputs!K100 -> 0 | L97: =Inputs!L41*Inputs!L100 -> 0 | M97: =Inputs!M41*Inputs!M100 -> 0 | N97: =Inputs!N41*Inputs!N100 -> 0 | O97: =Inputs!O41*Inputs!O100 -> 0 | P97: =Inputs!P41*Inputs!P100 -> 0 | Q97: =Inputs!Q41*Inputs!Q100 -> 0 | ... BQ97: =Inputs!BQ41*Inputs!BQ100 -> 28350
B99: Total | J99: =SUM(J97:J98) -> 0 | K99: =SUM(K97:K98) -> 0 | L99: =SUM(L97:L98) -> 0 | M99: =SUM(M97:M98) -> 0 | N99: =SUM(N97:N98) -> 0 | O99: =SUM(O97:O98) -> 0 | P99: =SUM(P97:P98) -> 0 | Q99: =SUM(Q97:Q98) -> 0 | ... BQ99: =SUM(BQ97:BQ98) -> 28350
B102: ISP Funds £0 Capex - 5g ongoing cost | J102: =Inputs!J41*Inputs!J101 -> 0 | K102: =Inputs!K41*Inputs!K101 -> 0 | L102: =Inputs!L41*Inputs!L101 -> 0 | M102: =Inputs!M41*Inputs!M101 -> 0 | N102: =Inputs!N41*Inputs!N101 -> 0 | O102: =Inputs!O41*Inputs!O101 -> 0 | P102: =Inputs!P41*Inputs!P101 -> 0 | Q102: =Inputs!Q41*Inputs!Q101 -> 0 | ... BQ102: =Inputs!BQ41*Inputs!BQ101 -> 3780
B104: Total | J104: =SUM(J102:J103) -> 0 | K104: =SUM(K102:K103) -> 0 | L104: =SUM(L102:L103) -> 0 | M104: =SUM(M102:M103) -> 0 | N104: =SUM(N102:N103) -> 0 | O104: =SUM(O102:O103) -> 0 | P104: =SUM(P102:P103) -> 0 | Q104: =SUM(Q102:Q103) -> 0 | ... BQ104: =SUM(BQ102:BQ103) -> 3780
B107: Other - Software charge | J107: =Inputs!J45*Inputs!J103 -> 0 | K107: =Inputs!K45*Inputs!K103 -> 0 | L107: =Inputs!L45*Inputs!L103 -> 0 | M107: =Inputs!M45*Inputs!M103 -> 0 | N107: =Inputs!N45*Inputs!N103 -> 0 | O107: =Inputs!O45*Inputs!O103 -> 0 | P107: =Inputs!P45*Inputs!P103 -> 0 | Q107: =Inputs!Q45*Inputs!Q103 -> 0 | ... BQ107: =Inputs!BQ45*Inputs!BQ103 -> 0
B109: Total | J109: =SUM(J107:J108) -> 0 | K109: =SUM(K107:K108) -> 0 | L109: =SUM(L107:L108) -> 0 | M109: =SUM(M107:M108) -> 0 | N109: =SUM(N107:N108) -> 0 | O109: =SUM(O107:O108) -> 0 | P109: =SUM(P107:P108) -> 0 | Q109: =SUM(Q107:Q108) -> 0 | ... BQ109: =SUM(BQ107:BQ108) -> 0
B112: Other - 5g ongoing cost | J112: =Inputs!J45*Inputs!J104 -> 0 | K112: =Inputs!K45*Inputs!K104 -> 0 | L112: =Inputs!L45*Inputs!L104 -> 0 | M112: =Inputs!M45*Inputs!M104 -> 0 | N112: =Inputs!N45*Inputs!N104 -> 0 | O112: =Inputs!O45*Inputs!O104 -> 0 | P112: =Inputs!P45*Inputs!P104 -> 0 | Q112: =Inputs!Q45*Inputs!Q104 -> 0 | ... BQ112: =Inputs!BQ45*Inputs!BQ104 -> 0
B114: Total | J114: =SUM(J112:J113) -> 0 | K114: =SUM(K112:K113) -> 0 | L114: =SUM(L112:L113) -> 0 | M114: =SUM(M112:M113) -> 0 | N114: =SUM(N112:N113) -> 0 | O114: =SUM(O112:O113) -> 0 | P114: =SUM(P112:P113) -> 0 | Q114: =SUM(Q112:Q113) -> 0 | ... BQ114: =SUM(BQ112:BQ113) -> 0
B117: Other - Freeholder cost | J117: =(Inputs!J33+Inputs!J41+Inputs!J45)*Inputs!J105 -> 0 | K117: =(Inputs!K33+Inputs!K41+Inputs!K45)*Inputs!K105 -> 0 | L117: =(Inputs!L33+Inputs!L41+Inputs!L45)*Inputs!L105 -> 0 | M117: =(Inputs!M33+Inputs!M41+Inputs!M45)*Inputs!M105 -> 0 | N117: =(Inputs!N33+Inputs!N41+Inputs!N45)*Inputs!N105 -> 0 | O117: =(Inputs!O33+Inputs!O41+Inputs!O45)*Inputs!O105 -> 0 | P117: =(Inputs!P33+Inputs!P41+Inputs!P45)*Inputs!P105 -> 0 | Q117: =(Inputs!Q33+Inputs!Q41+Inputs!Q45)*Inputs!Q105 -> 0 | ... BQ117: =(Inputs!BQ33+Inputs!BQ41+Inputs!BQ45)*Inputs!BQ105 -> 173100
B119: Total | J119: =SUM(J117:J118) -> 0 | K119: =SUM(K117:K118) -> 0 | L119: =SUM(L117:L118) -> 0 | M119: =SUM(M117:M118) -> 0 | N119: =SUM(N117:N118) -> 0 | O119: =SUM(O117:O118) -> 0 | P119: =SUM(P117:P118) -> 0 | Q119: =SUM(Q117:Q118) -> 0 | ... BQ119: =SUM(BQ117:BQ118) -> 173100
B132: Overheads
B134: Rent
B135: Premises 1 | T135: 1750 | U135: 1750 | V135: 1750 | W135: 1750 | X135: 1750 | Y135: 1750 | Z135: 1750 | AA135: 1750 | AB135: 1750 | AC135: 1750 | AD135: 1750 | AE135: 1750 | AF135: 1750 | AG135: 1750 | AH135: 1750 | AI135: 1750 | AJ135: 1750 | AK135: 1750 | AL135: 1750 | AM135: 1750 | AN135: 1750 | AO135: 1750 | AP135: 1750 | AQ135: 1750 | AR135: 1750 | AS135: 1750 | AT135: 1750 | AU135: 1750 | AV135: 1750 | AW135: 1750 | AX135: 1750 | AY135: 1750 | AZ135: 1750 | BA135: 1750 | BB135: 1750 | BC135: 1750 | BD135: 1750 | BE135: 1750 | BF135: 2500 | BG135: 2500 | BH135: 2500 | BI135: 2500 | BJ135: 2500 | BK135: 2500 | BL135: 2500 | BM135: 2500 | BN135: 2500 | BO135: 2500 | BP135: 2500 | BQ135: 2500
B136: Premises 2
B137: Total Rent | J137: =SUM(J135:J136) -> 0 | K137: =SUM(K135:K136) -> 0 | L137: =SUM(L135:L136) -> 0 | M137: =SUM(M135:M136) -> 0 | N137: =SUM(N135:N136) -> 0 | O137: =SUM(O135:O136) -> 0 | P137: =SUM(P135:P136) -> 0 | Q137: =SUM(Q135:Q136) -> 0 | ... BQ137: =SUM(BQ135:BQ136) -> 2500
B140: Rates
B141: Premises 1 | C141: (incl in rent) | T141: 0 | U141: 0 | V141: 0 | W141: 0 | X141: 0 | Y141: 0 | Z141: 0 | AA141: 0 | AB141: 0 | AC141: 0 | AD141: 0 | AE141: 0 | AF141: 0 | AG141: 0 | AH141: 0 | AI141: 0 | AJ141: 0 | AK141: 0 | AL141: 0 | AM141: 0 | AN141: 0 | AO141: 0 | AP141: 0 | AQ141: 0 | AR141: 0 | AS141: 0 | AT141: 0 | AU141: 0 | AV141: 0 | AW141: 0 | AX141: 0 | AY141: 0 | AZ141: 0 | BA141: 0 | BB141: 0 | BC141: 0 | BD141: 0 | BE141: 0 | BF141: 0 | BG141: 0 | BH141: 0 | BI141: 0 | BJ141: 0 | BK141: 0 | BL141: 0 | BM141: 0 | BN141: 0 | BO141: 0 | BP141: 0 | BQ141: 0
B142: Premises 2
B143: Total Rates | J143: =SUM(J141:J142) -> 0 | K143: =SUM(K141:K142) -> 0 | L143: =SUM(L141:L142) -> 0 | M143: =SUM(M141:M142) -> 0 | N143: =SUM(N141:N142) -> 0 | O143: =SUM(O141:O142) -> 0 | P143: =SUM(P141:P142) -> 0 | Q143: =SUM(Q141:Q142) -> 0 | ... BQ143: =SUM(BQ141:BQ142) -> 0
B146: Recruitment Costs
B147: General | W147: 6000
B149: Total Recruitment costs | J149: =SUM(J147:J148) -> 0 | K149: =SUM(K147:K148) -> 0 | L149: =SUM(L147:L148) -> 0 | M149: =SUM(M147:M148) -> 0 | N149: =SUM(N147:N148) -> 0 | O149: =SUM(O147:O148) -> 0 | P149: =SUM(P147:P148) -> 0 | Q149: =SUM(Q147:Q148) -> 0 | ... BQ149: =SUM(BQ147:BQ148) -> 0
B152: Repairs and Maintenance Costs
B153: Replacement/damaged screens | J153: =(ROUND('KPI''s'!J8*Inputs!J116,0))*(Inputs!J111+Inputs!J112+Inputs!J113)/12 -> 0 | K153: =(ROUND('KPI''s'!K8*Inputs!K116,0))*(Inputs!K111+Inputs!K112+Inputs!K113)/12 -> 0 | L153: =(ROUND('KPI''s'!L8*Inputs!L116,0))*(Inputs!L111+Inputs!L112+Inputs!L113)/12 -> 0 | M153: =(ROUND('KPI''s'!M8*Inputs!M116,0))*(Inputs!M111+Inputs!M112+Inputs!M113)/12 -> 0 | N153: =(ROUND('KPI''s'!N8*Inputs!N116,0))*(Inputs!N111+Inputs!N112+Inputs!N113)/12 -> 0 | O153: =(ROUND('KPI''s'!O8*Inputs!O116,0))*(Inputs!O111+Inputs!O112+Inputs!O113)/12 -> 0 | P153: =(ROUND('KPI''s'!P8*Inputs!P116,0))*(Inputs!P111+Inputs!P112+Inputs!P113)/12 -> 0 | Q153: =(ROUND('KPI''s'!Q8*Inputs!Q116,0))*(Inputs!Q111+Inputs!Q112+Inputs!Q113)/12 -> 0 | ... BQ153: =(ROUND('KPI''s'!BQ8*Inputs!BQ116,0))*(Inputs!BQ111+Inputs!BQ112+Inputs!BQ113)/12 -> 2156.25
B155: Total Repairs and Maintenance costs | J155: =SUM(J153:J154) -> 0 | K155: =SUM(K153:K154) -> 0 | L155: =SUM(L153:L154) -> 0 | M155: =SUM(M153:M154) -> 0 | N155: =SUM(N153:N154) -> 0 | O155: =SUM(O153:O154) -> 0 | P155: =SUM(P153:P154) -> 0 | Q155: =SUM(Q153:Q154) -> 0 | ... BQ155: =SUM(BQ153:BQ154) -> 2156.25
B158: Insurance Costs
B159: Commercial Combined | T159: 100 | U159: 100 | V159: 100 | W159: 100 | X159: 100 | Y159: 100 | Z159: 100 | AA159: 100 | AB159: 100 | AC159: 100 | AD159: 100 | AE159: 300 | AF159: 300 | AG159: 300 | AH159: 300 | AI159: 300 | AJ159: 300 | AK159: 300 | AL159: 300 | AM159: 300 | AN159: 300 | AO159: 300 | AP159: 300 | AQ159: 300 | AR159: 300 | AS159: 300 | AT159: 300 | AU159: 300 | AV159: 300 | AW159: 1800 | AX159: 1800 | AY159: 1800 | AZ159: 1800 | BA159: 1800 | BB159: 1800 | BC159: 1800 | BD159: 1800 | BE159: 1800 | BF159: 1800 | BG159: 1800 | BH159: 1800 | BI159: 1800 | BJ159: 1800 | BK159: 1800 | BL159: 1800 | BM159: 1800 | BN159: 1800 | BO159: 1800 | BP159: 1800 | BQ159: 1800
B160: Professional Indemnity | T160: 175 | U160: 175 | V160: 175 | W160: 175 | X160: 175 | Y160: 175 | Z160: 175 | AA160: 175 | AB160: 175 | AC160: 175 | AD160: 175 | AE160: 475 | AF160: 475 | AG160: 475 | AH160: 475 | AI160: 475 | AJ160: 475 | AK160: 475 | AL160: 475 | AM160: 475 | AN160: 475 | AO160: 475 | AP160: 475 | AQ160: 475 | AR160: 475 | AS160: 475 | AT160: 475 | AU160: 475 | AV160: 475 | AW160: 1000 | AX160: 1000 | AY160: 1000 | AZ160: 1000 | BA160: 1000 | BB160: 1000 | BC160: 1000 | BD160: 1000 | BE160: 1000 | BF160: 1000 | BG160: 1000 | BH160: 1000 | BI160: 1000 | BJ160: 1000 | BK160: 1000 | BL160: 1000 | BM160: 1000 | BN160: 1000 | BO160: 1000 | BP160: 1000 | BQ160: 1000
B161: Motor | T161: 0 | U161: 0 | V161: 0 | W161: 0 | X161: 0 | Y161: 0 | Z161: 0 | AA161: 0 | AB161: 0 | AC161: 0 | AD161: 0 | AE161: 0 | AF161: 0 | AG161: 0 | AH161: 0 | AI161: 0 | AJ161: 0 | AK161: 0 | AL161: 0 | AM161: 0 | AN161: 0 | AO161: 0 | AP161: 0 | AQ161: 0 | AR161: 0 | AS161: 0 | AT161: 0 | AU161: 0 | AV161: 0 | AW161: 0 | AX161: 0 | AY161: 0 | AZ161: 0 | BA161: 0 | BB161: 0 | BC161: 0 | BD161: 0 | BE161: 0 | BF161: 0 | BG161: 0 | BH161: 0 | BI161: 0 | BJ161: 0 | BK161: 0 | BL161: 0 | BM161: 0 | BN161: 0 | BO161: 0 | BP161: 0 | BQ161: 0
B162: Healthcare | T162: 250 | U162: 250 | V162: 250 | W162: 250 | X162: 250 | Y162: 250 | Z162: 250 | AA162: 250 | AB162: 250 | AC162: 250 | AD162: 250 | AE162: 250 | AF162: 250 | AG162: 250 | AH162: 250 | AI162: 250 | AJ162: 250 | AK162: 250 | AL162: 250 | AM162: 250 | AN162: 250 | AO162: 250 | AP162: 250 | AQ162: 250 | AR162: 250 | AS162: 250 | AT162: 250 | AU162: 250 | AV162: 250 | AW162: 250 | AX162: 250 | AY162: 250 | AZ162: 250 | BA162: 250 | BB162: 250 | BC162: 250 | BD162: 250 | BE162: 250 | BF162: 250 | BG162: 250 | BH162: 250 | BI162: 250 | BJ162: 250 | BK162: 250 | BL162: 250 | BM162: 250 | BN162: 250 | BO162: 250 | BP162: 250 | BQ162: 250
B164: Total Insurance costs | J164: =SUM(J159:J163) -> 0 | K164: =SUM(K159:K163) -> 0 | L164: =SUM(L159:L163) -> 0 | M164: =SUM(M159:M163) -> 0 | N164: =SUM(N159:N163) -> 0 | O164: =SUM(O159:O163) -> 0 | P164: =SUM(P159:P163) -> 0 | Q164: =SUM(Q159:Q163) -> 0 | ... BQ164: =SUM(BQ159:BQ163) -> 3050
B167: Computer Running Costs
B168: Website | J168: 2500 | K168: 1500 | L168: 0 | M168: 1909 | Q168: 18850
B169: Accounting software | T169: 100 | U169: 100 | V169: 100 | W169: 100 | X169: 100 | Y169: 100 | Z169: 100 | AA169: 100 | AB169: 100 | AC169: 100 | AD169: 100 | AE169: 100 | AF169: 100 | AG169: 100 | AH169: 100 | AI169: 100 | AJ169: 100 | AK169: 100 | AL169: 100 | AM169: 100 | AN169: 100 | AO169: 100 | AP169: 100 | AQ169: 100 | AR169: 100 | AS169: 100 | AT169: 100 | AU169: 100 | AV169: 100 | AW169: 100 | AX169: 100 | AY169: 100 | AZ169: 100 | BA169: 100 | BB169: 100 | BC169: 100 | BD169: 100 | BE169: 100 | BF169: 100 | BG169: 100 | BH169: 100 | BI169: 100 | BJ169: 100 | BK169: 100 | BL169: 100 | BM169: 100 | BN169: 100 | BO169: 100 | BP169: 100 | BQ169: 100
B170: Office 365 | T170: 600 | U170: 600 | V170: 600 | W170: 600 | X170: 600 | Y170: 600 | Z170: 600 | AA170: 600 | AB170: 600 | AC170: 1000 | AD170: 1000 | AE170: 1000 | AF170: 1000 | AG170: 1000 | AH170: 1000 | AI170: 1000 | AJ170: 1000 | AK170: 1000 | AL170: 1000 | AM170: 1000 | AN170: 1000 | AO170: 1000 | AP170: 1000 | AQ170: 1000 | AR170: 1000 | AS170: 1000 | AT170: 1000 | AU170: 1000 | AV170: 1000 | AW170: 1000 | AX170: 1000 | AY170: 1000 | AZ170: 1000 | BA170: 1000 | BB170: 1000 | BC170: 1000 | BD170: 1000 | BE170: 1000 | BF170: 1000 | BG170: 1000 | BH170: 1000 | BI170: 1000 | BJ170: 1000 | BK170: 1000 | BL170: 1000 | BM170: 1000 | BN170: 1000 | BO170: 1000 | BP170: 1000 | BQ170: 1000
B171: Domain hosting & other expenses | J171: 75 | L171: 170 | M171: 170 | O171: 170 | Q171: 0 | R171: 170 | S171: 170 | T171: 170 | U171: 170 | V171: 170 | W171: 170 | X171: 170 | Y171: 170 | Z171: 170 | AA171: 170 | AB171: 170 | AC171: 170 | AD171: 170 | AE171: 170 | AF171: 170 | AG171: 170 | AH171: 170 | AI171: 170 | AJ171: 170 | AK171: 170 | AL171: 170 | AM171: 170 | AN171: 170 | AO171: 170 | AP171: 170 | AQ171: 170 | AR171: 170 | AS171: 170 | AT171: 170 | AU171: 170 | AV171: 170 | AW171: 170 | AX171: 170 | AY171: 170 | AZ171: 170 | BA171: 170 | BB171: 170 | BC171: 170 | BD171: 170 | BE171: 170 | BF171: 170 | BG171: 170 | BH171: 170 | BI171: 170 | BJ171: 170 | BK171: 170 | BL171: 170 | BM171: 170 | BN171: 170 | BO171: 170 | BP171: 170 | BQ171: 170
B172: Total Computer costs | J172: =SUM(J168:J171) -> 2575 | K172: =SUM(K168:K171) -> 1500 | L172: =SUM(L168:L171) -> 170 | M172: =SUM(M168:M171) -> 2079 | N172: =SUM(N168:N171) -> 0 | O172: =SUM(O168:O171) -> 170 | P172: =SUM(P168:P171) -> 0 | Q172: =SUM(Q168:Q171) -> 18850 | ... BQ172: =SUM(BQ168:BQ171) -> 1270
B175: Travelling expenses
B176: General travel | J176: 0 | K176: 399 | L176: 230 | M176: 156 | N176: 2199 | Q176: 0 | R176: 2000 | S176: 2000 | T176: 2000 | U176: 2000 | V176: 2000 | W176: 2000 | X176: 2000 | Y176: 2000 | Z176: 2000 | AA176: 2000 | AB176: 2000 | AC176: 2000 | AD176: 2000 | AE176: 2000 | AF176: 4000 | AG176: 4000 | AH176: 4000 | AI176: 4000 | AJ176: 4000 | AK176: 4000 | AL176: 4000 | AM176: 4000 | AN176: 4000 | AO176: 4000 | AP176: 4000 | AQ176: 4000 | AR176: 4000 | AS176: 4000 | AT176: 5000 | AU176: 5000 | AV176: 5000 | AW176: 5000 | AX176: 5000 | AY176: 5000 | AZ176: 5000 | BA176: 5000 | BB176: 5000 | BC176: 5000 | BD176: 5000 | BE176: 5000 | BF176: 7000 | BG176: 7000 | BH176: 7000 | BI176: 7000 | BJ176: 7000 | BK176: 7000 | BL176: 7000 | BM176: 7000 | BN176: 7000 | BO176: 7000 | BP176: 7000 | BQ176: 7000
B178: Total travelling expenses | J178: =SUM(J176:J177) -> 0 | K178: =SUM(K176:K177) -> 399 | L178: =SUM(L176:L177) -> 230 | M178: =SUM(M176:M177) -> 156 | N178: =SUM(N176:N177) -> 2199 | O178: =SUM(O176:O177) -> 0 | P178: =SUM(P176:P177) -> 0 | Q178: =SUM(Q176:Q177) -> 0 | ... BQ178: =SUM(BQ176:BQ177) -> 7000
B181: Legal fees
B182: Legal costs | S182: 500 | T182: 500 | U182: 500 | V182: 500 | W182: 500 | X182: 500 | Y182: 500 | Z182: 500 | AA182: 500 | AB182: 500 | AC182: 1000 | AD182: 1000 | AE182: 1000 | AF182: 1000 | AG182: 1000 | AH182: 1000 | AI182: 1000 | AJ182: 1000 | AK182: 1000 | AL182: 1000 | AM182: 1000 | AN182: 1000 | AO182: 1000 | AP182: 1000 | AQ182: 1000 | AR182: 1000 | AS182: 1000 | AT182: 1500 | AU182: 1500 | AV182: 1500 | AW182: 1500 | AX182: 1500 | AY182: 1500 | AZ182: 1500 | BA182: 1500 | BB182: 1500 | BC182: 1500 | BD182: 1500 | BE182: 1500 | BF182: 2000 | BG182: 2000 | BH182: 2000 | BI182: 2000 | BJ182: 2000 | BK182: 2000 | BL182: 2000 | BM182: 2000 | BN182: 2000 | BO182: 2000 | BP182: 2000 | BQ182: 2000
B184: Total legal | J184: =SUM(J182:J183) -> 0 | K184: =SUM(K182:K183) -> 0 | L184: =SUM(L182:L183) -> 0 | M184: =SUM(M182:M183) -> 0 | N184: =SUM(N182:N183) -> 0 | O184: =SUM(O182:O183) -> 0 | P184: =SUM(P182:P183) -> 0 | Q184: =SUM(Q182:Q183) -> 0 | ... BQ184: =SUM(BQ182:BQ183) -> 2000
...

Sheet Wages and Salaries
A1: Business 1
A2: Wages and Salaries | J2: =Timing!J2 -> 44986 | K2: =Timing!K2 -> 45017 | L2: =Timing!L2 -> 45047 | M2: =Timing!M2 -> 45078 | N2: =Timing!N2 -> 45108 | O2: =Timing!O2 -> 45139 | P2: =Timing!P2 -> 45170 | Q2: =Timing!Q2 -> 45200 | ... BQ2: =Timing!BQ2 -> 46784
J3: =Timing!J3 -> 45016 | K3: =Timing!K3 -> 45046 | L3: =Timing!L3 -> 45077 | M3: =Timing!M3 -> 45107 | N3: =Timing!N3 -> 45138 | O3: =Timing!O3 -> 45169 | P3: =Timing!P3 -> 45199 | Q3: =Timing!Q3 -> 45230 | ... BQ3: =Timing!BQ3 -> 46812
B5: COS
B6: Media Manager | J6: 0 | K6: 0 | L6: 0 | M6: 0 | N6: 0 | O6: 0 | P6: 0 | Q6: 0 | R6: 0 | S6: 0 | T6: 1 | U6: 1 | V6: 1 | W6: 1 | X6: 1 | Y6: 1 | Z6: 1 | AA6: 1 | AB6: 1 | AC6: 1 | AD6: 1 | AE6: 1 | AF6: 1 | AG6: 1 | AH6: 1 | AI6: 1 | AJ6: 1 | AK6: 1 | AL6: 1 | AM6: 1 | AN6: 1 | AO6: 1 | AP6: 1 | AQ6: 1 | AR6: 1 | AS6: 1 | AT6: 1 | AU6: 1 | AV6: 1 | AW6: 1 | AX6: 1 | AY6: 1 | AZ6: 1 | BA6: 1 | BB6: 1 | BC6: 1 | BD6: 1 | BE6: 1 | BF6: 1 | BG6: 1 | BH6: 1 | BI6: 1 | BJ6: 1 | BK6: 1 | BL6: 1 | BM6: 1 | BN6: 1 | BO6: 1 | BP6: 1 | BQ6: 1
B7: Media Sales | J7: 0 | K7: 0 | L7: 0 | M7: 0 | N7: 0 | O7: 0 | P7: 0 | Q7: 0 | R7: 0 | S7: 0 | T7: 0 | U7: 0 | V7: 0 | W7: 3 | X7: 3 | Y7: 3 | Z7: 3 | AA7: 3 | AB7: 3 | AC7: 3 | AD7: 3 | AE7: 3 | AF7: 3 | AG7: 3 | AH7: 3 | AI7: 3 | AJ7: 3 | AK7: 3 | AL7: 3 | AM7: 3 | AN7: 3 | AO7: 3 | AP7: 3 | AQ7: 3 | AR7: 3 | AS7: 3 | AT7: 3 | AU7: 3 | AV7: 3 | AW7: 3 | AX7: 3 | AY7: 3 | AZ7: 3 | BA7: 3 | BB7: 3 | BC7: 3 | BD7: 3 | BE7: 3 | BF7: 3 | BG7: 3 | BH7: 3 | BI7: 3 | BJ7: 3 | BK7: 3 | BL7: 3 | BM7: 3 | BN7: 3 | BO7: 3 | BP7: 3 | BQ7: 3
B8: Operations manager | J8: 0 | K8: 0 | L8: 0 | M8: 0 | N8: 0 | O8: 0 | P8: 0 | Q8: 0 | R8: 0 | S8: 1 | T8: 1 | U8: 1 | V8: 1 | W8: 1 | X8: 1 | Y8: 1 | Z8: 1 | AA8: 1 | AB8: 1 | AC8: 1 | AD8: 1 | AE8: 1 | AF8: 1 | AG8: 1 | AH8: 1 | AI8: 1 | AJ8: 1 | AK8: 1 | AL8: 1 | AM8: 1 | AN8: 1 | AO8: 1 | AP8: 1 | AQ8: 1 | AR8: 1 | AS8: 1 | AT8: 1 | AU8: 1 | AV8: 1 | AW8: 1 | AX8: 1 | AY8: 1 | AZ8: 1 | BA8: 1 | BB8: 1 | BC8: 1 | BD8: 1 | BE8: 1 | BF8: 1 | BG8: 1 | BH8: 1 | BI8: 1 | BJ8: 1 | BK8: 1 | BL8: 1 | BM8: 1 | BN8: 1 | BO8: 1 | BP8: 1 | BQ8: 1
B9: Role 4 | J9: 0 | K9: 0 | L9: 0 | M9: 0 | N9: 0 | O9: 0 | P9: 0 | Q9: 0 | R9: 0 | S9: 0 | T9: 0 | U9: 0 | V9: 0 | W9: 0 | X9: 0 | Y9: 0 | Z9: 0 | AA9: 0 | AB9: 0 | AC9: 0 | AD9: 0 | AE9: 0 | AF9: 0 | AG9: 0 | AH9: 1 | AI9: 1 | AJ9: 1 | AK9: 1 | AL9: 1 | AM9: 1 | AN9: 1 | AO9: 1 | AP9: 1 | AQ9: 1 | AR9: 1 | AS9: 2 | AT9: 2 | AU9: 2 | AV9: 2 | AW9: 2 | AX9: 2 | AY9: 2 | AZ9: 2 | BA9: 2 | BB9: 2 | BC9: 2 | BD9: 2 | BE9: 2 | BF9: 2 | BG9: 2 | BH9: 2 | BI9: 2 | BJ9: 2 | BK9: 2 | BL9: 2 | BM9: 2 | BN9: 2 | BO9: 2 | BP9: 2 | BQ9: 2
B10: Role 5 | J10: 0 | K10: 0 | L10: 0 | M10: 0 | N10: 0 | O10: 0 | P10: 0 | Q10: 0 | R10: 0 | S10: 0 | T10: 0 | U10: 0 | V10: 0 | W10: 0 | X10: 0 | Y10: 0 | Z10: 0 | AA10: 0 | AB10: 0 | AC10: 0 | AD10: 0 | AE10: 0 | AF10: 0 | AG10: 0 | AH10: 0 | AI10: 0 | AJ10: 0 | AK10: 0 | AL10: 0 | AM10: 0 | AN10: 0 | AO10: 0 | AP10: 0 | AQ10: 0 | AR10: 0 | AS10: 0 | AT10: 1 | AU10: 1 | AV10: 1 | AW10: 1 | AX10: 1 | AY10: 1 | AZ10: 1 | BA10: 1 | BB10: 1 | BC10: 1 | BD10: 1 | BE10: 1 | BF10: 2 | BG10: 2 | BH10: 2 | BI10: 2 | BJ10: 2 | BK10: 2 | BL10: 2 | BM10: 2 | BN10: 2 | BO10: 2 | BP10: 2 | BQ10: 2
B11: Role 6 | J11: 0 | K11: 0 | L11: 0 | M11: 0 | N11: 0 | O11: 0 | P11: 0 | Q11: 0 | R11: 0 | S11: 0 | T11: 0 | U11: 0 | V11: 0 | W11: 0 | X11: 0 | Y11: 0 | Z11: 0 | AA11: 0 | AB11: 0 | AC11: 0 | AD11: 0 | AE11: 0 | AF11: 0 | AG11: 0 | AH11: 0 | AI11: 0 | AJ11: 0 | AK11: 0 | AL11: 0 | AM11: 0 | AN11: 0 | AO11: 0 | AP11: 0 | AQ11: 0 | AR11: 0 | AS11: 0 | AT11: 0 | AU11: 0 | AV11: 0 | AW11: 0 | AX11: 0 | AY11: 0 | AZ11: 0 | BA11: 0 | BB11: 0 | BC11: 0 | BD11: 0 | BE11: 0 | BF11: 1 | BG11: 1 | BH11: 1 | BI11: 1 | BJ11: 1 | BK11: 1 | BL11: 1 | BM11: 1 | BN11: 1 | BO11: 1 | BP11: 1 | BQ11: 1
B12: Total Headcount | J12: =SUM(J6:J11) -> 0 | K12: =SUM(K6:K11) -> 0 | L12: =SUM(L6:L11) -> 0 | M12: =SUM(M6:M11) -> 0 | N12: =SUM(N6:N11) -> 0 | O12: =SUM(O6:O11) -> 0 | P12: =SUM(P6:P11) -> 0 | Q12: =SUM(Q6:Q11) -> 0 | ... BQ12: =SUM(BQ6:BQ11) -> 10
B14: COS | C14: Salary
B15: =B6 -> Media Manager | C15: 75000 | J15: =($C15/12)*J6 -> 0 | K15: =($C15/12)*K6 -> 0 | L15: =($C15/12)*L6 -> 0 | M15: =($C15/12)*M6 -> 0 | N15: =($C15/12)*N6 -> 0 | O15: =($C15/12)*O6 -> 0 | P15: =($C15/12)*P6 -> 0 | Q15: =($C15/12)*Q6 -> 0 | ... BQ15: =($C15/12)*BQ6 -> 6250
B16: =B7 -> Media Sales | C16: 50000 | J16: =($C16/12)*J7 -> 0 | K16: =($C16/12)*K7 -> 0 | L16: =($C16/12)*L7 -> 0 | M16: =($C16/12)*M7 -> 0 | N16: =($C16/12)*N7 -> 0 | O16: =($C16/12)*O7 -> 0 | P16: =($C16/12)*P7 -> 0 | Q16: =($C16/12)*Q7 -> 0 | ... BQ16: =($C16/12)*BQ7 -> 12500
B17: =B8 -> Operations manager | C17: 35000 | J17: =($C17/12)*J8 -> 0 | K17: =($C17/12)*K8 -> 0 | L17: =($C17/12)*L8 -> 0 | M17: =($C17/12)*M8 -> 0 | N17: =($C17/12)*N8 -> 0 | O17: =($C17/12)*O8 -> 0 | P17: =($C17/12)*P8 -> 0 | Q17: =($C17/12)*Q8 -> 0 | ... BQ17: =($C17/12)*BQ8 -> 2916.6667
B18: =B9 -> Role 4 | C18: 40000 | J18: =($C18/12)*J9 -> 0 | K18: =($C18/12)*K9 -> 0 | L18: =($C18/12)*L9 -> 0 | M18: =($C18/12)*M9 -> 0 | N18: =($C18/12)*N9 -> 0 | O18: =($C18/12)*O9 -> 0 | P18: =($C18/12)*P9 -> 0 | Q18: =($C18/12)*Q9 -> 0 | ... BQ18: =($C18/12)*BQ9 -> 6666.6667
B19: =B10 -> Role 5 | C19: 45000 | J19: =($C19/12)*J10 -> 0 | K19: =($C19/12)*K10 -> 0 | L19: =($C19/12)*L10 -> 0 | M19: =($C19/12)*M10 -> 0 | N19: =($C19/12)*N10 -> 0 | O19: =($C19/12)*O10 -> 0 | P19: =($C19/12)*P10 -> 0 | Q19: =($C19/12)*Q10 -> 0 | ... BQ19: =($C19/12)*BQ10 -> 7500
B20: =B11 -> Role 6 | J20: =($C20/12)*J11 -> 0 | K20: =($C20/12)*K11 -> 0 | L20: =($C20/12)*L11 -> 0 | M20: =($C20/12)*M11 -> 0 | N20: =($C20/12)*N11 -> 0 | O20: =($C20/12)*O11 -> 0 | P20: =($C20/12)*P11 -> 0 | Q20: =($C20/12)*Q11 -> 0 | ... BQ20: =($C20/12)*BQ11 -> 0
B21: Total COS Gross Salary | J21: =SUM(J15:J20) -> 0 | K21: =SUM(K15:K20) -> 0 | L21: =SUM(L15:L20) -> 0 | M21: =SUM(M15:M20) -> 0 | N21: =SUM(N15:N20) -> 0 | O21: =SUM(O15:O20) -> 0 | P21: =SUM(P15:P20) -> 0 | Q21: =SUM(Q15:Q20) -> 0 | ... BQ21: =SUM(BQ15:BQ20) -> 35833.333
B24: Ers NI | J24: =J21*Inputs!J14 -> 0 | K24: =K21*Inputs!K14 -> 0 | L24: =L21*Inputs!L14 -> 0 | M24: =M21*Inputs!M14 -> 0 | N24: =N21*Inputs!N14 -> 0 | O24: =O21*Inputs!O14 -> 0 | P24: =P21*Inputs!P14 -> 0 | Q24: =Q21*Inputs!Q14 -> 0 | ... BQ24: =BQ21*Inputs!BQ14 -> 5375
B25: Pension | J25: =J21*Inputs!J15 -> 0 | K25: =K21*Inputs!K15 -> 0 | L25: =L21*Inputs!L15 -> 0 | M25: =M21*Inputs!M15 -> 0 | N25: =N21*Inputs!N15 -> 0 | O25: =O21*Inputs!O15 -> 0 | P25: =P21*Inputs!P15 -> 0 | Q25: =Q21*Inputs!Q15 -> 0 | ... BQ25: =BQ21*Inputs!BQ15 -> 1075
B26: PAYE | J26: =J21*Inputs!J12 -> 0 | K26: =K21*Inputs!K12 -> 0 | L26: =L21*Inputs!L12 -> 0 | M26: =M21*Inputs!M12 -> 0 | N26: =N21*Inputs!N12 -> 0 | O26: =O21*Inputs!O12 -> 0 | P26: =P21*Inputs!P12 -> 0 | Q26: =Q21*Inputs!Q12 -> 0 | ... BQ26: =BQ21*Inputs!BQ12 -> 8958.3333
B27: Ees NI | J27: =J21*Inputs!J13 -> 0 | K27: =K21*Inputs!K13 -> 0 | L27: =L21*Inputs!L13 -> 0 | M27: =M21*Inputs!M13 -> 0 | N27: =N21*Inputs!N13 -> 0 | O27: =O21*Inputs!O13 -> 0 | P27: =P21*Inputs!P13 -> 0 | Q27: =Q21*Inputs!Q13 -> 0 | ... BQ27: =BQ21*Inputs!BQ13 -> 3941.6667
B28: Total | J28: =SUM(J24:J27) -> 0 | K28: =SUM(K24:K27) -> 0 | L28: =SUM(L24:L27) -> 0 | M28: =SUM(M24:M27) -> 0 | N28: =SUM(N24:N27) -> 0 | O28: =SUM(O24:O27) -> 0 | P28: =SUM(P24:P27) -> 0 | Q28: =SUM(Q24:Q27) -> 0 | ... BQ28: =SUM(BQ24:BQ27) -> 19350
B31: Wages and Salaries
B32: Administrator | J32: 0 | K32: 0 | L32: 0 | M32: 0 | N32: 0 | O32: 0 | P32: 0 | Q32: 0 | R32: 0 | S32: 1 | T32: 1 | U32: 1 | V32: 1 | W32: 1 | X32: 1 | Y32: 1 | Z32: 1 | AA32: 1 | AB32: 1 | AC32: 1 | AD32: 1 | AE32: 1 | AF32: 1 | AG32: 1 | AH32: 1 | AI32: 1 | AJ32: 1 | AK32: 1 | AL32: 1 | AM32: 1 | AN32: 1 | AO32: 1 | AP32: 1 | AQ32: 1 | AR32: 1 | AS32: 1 | AT32: 1 | AU32: 1 | AV32: 1 | AW32: 1 | AX32: 1 | AY32: 1 | AZ32: 1 | BA32: 1 | BB32: 1 | BC32: 1 | BD32: 1 | BE32: 1 | BF32: 1 | BG32: 1 | BH32: 1 | BI32: 1 | BJ32: 1 | BK32: 1 | BL32: 1 | BM32: 1 | BN32: 1 | BO32: 1 | BP32: 1 | BQ32: 1
B33: Software Admin | J33: 0 | K33: 0 | L33: 0 | M33: 0 | N33: 0 | O33: 0 | P33: 0 | Q33: 0 | R33: 0 | S33: 1 | T33: 1 | U33: 1 | V33: 1 | W33: 1 | X33: 1 | Y33: 1 | Z33: 1 | AA33: 1 | AB33: 1 | AC33: 1 | AD33: 1 | AE33: 1 | AF33: 1 | AG33: 1 | AH33: 1 | AI33: 1 | AJ33: 1 | AK33: 1 | AL33: 1 | AM33: 1 | AN33: 1 | AO33: 1 | AP33: 1 | AQ33: 1 | AR33: 1 | AS33: 1 | AT33: 1 | AU33: 1 | AV33: 1 | AW33: 1 | AX33: 1 | AY33: 1 | AZ33: 1 | BA33: 1 | BB33: 1 | BC33: 1 | BD33: 1 | BE33: 1 | BF33: 1 | BG33: 1 | BH33: 1 | BI33: 1 | BJ33: 1 | BK33: 1 | BL33: 1 | BM33: 1 | BN33: 1 | BO33: 1 | BP33: 1 | BQ33: 1
B34: Accountant | J34: 0 | K34: 0 | L34: 0 | M34: 0 | N34: 0 | O34: 0 | P34: 0 | Q34: 0 | R34: 0 | S34: 0 | T34: 0 | U34: 0 | V34: 0 | W34: 1 | X34: 1 | Y34: 1 | Z34: 1 | AA34: 1 | AB34: 1 | AC34: 1 | AD34: 1 | AE34: 1 | AF34: 1 | AG34: 1 | AH34: 1 | AI34: 1 | AJ34: 1 | AK34: 1 | AL34: 1 | AM34: 1 | AN34: 1 | AO34: 1 | AP34: 1 | AQ34: 1 | AR34: 1 | AS34: 1 | AT34: 1 | AU34: 1 | AV34: 1 | AW34: 1 | AX34: 1 | AY34: 1 | AZ34: 1 | BA34: 1 | BB34: 1 | BC34: 1 | BD34: 1 | BE34: 1 | BF34: 1 | BG34: 1 | BH34: 1 | BI34: 1 | BJ34: 1 | BK34: 1 | BL34: 1 | BM34: 1 | BN34: 1 | BO34: 1 | BP34: 1 | BQ34: 1
B35: Role 4 | J35: 0 | K35: 0 | L35: 0 | M35: 0 | N35: 0 | O35: 0 | P35: 0 | Q35: 0 | R35: 0 | S35: 0 | T35: 0 | U35: 0 | V35: 0 | W35: 0 | X35: 0 | Y35: 0 | Z35: 0 | AA35: 0 | AB35: 0 | AC35: 0 | AD35: 0 | AE35: 0 | AF35: 0 | AG35: 0 | AH35: 1 | AI35: 1 | AJ35: 1 | AK35: 1 | AL35: 1 | AM35: 1 | AN35: 1 | AO35: 1 | AP35: 1 | AQ35: 1 | AR35: 1 | AS35: 1 | AT35: 1 | AU35: 1 | AV35: 1 | AW35: 1 | AX35: 1 | AY35: 1 | AZ35: 1 | BA35: 1 | BB35: 1 | BC35: 1 | BD35: 1 | BE35: 1 | BF35: 1 | BG35: 1 | BH35: 1 | BI35: 1 | BJ35: 1 | BK35: 1 | BL35: 1 | BM35: 1 | BN35: 1 | BO35: 1 | BP35: 1 | BQ35: 1
B36: Role 5 | J36: 0 | K36: 0 | L36: 0 | M36: 0 | N36: 0 | O36: 0 | P36: 0 | Q36: 0 | R36: 0 | S36: 0 | T36: 0 | U36: 0 | V36: 0 | W36: 0 | X36: 0 | Y36: 0 | Z36: 0 | AA36: 0 | AB36: 0 | AC36: 0 | AD36: 0 | AE36: 0 | AF36: 0 | AG36: 0 | AH36: 0 | AI36: 0 | AJ36: 0 | AK36: 0 | AL36: 0 | AM36: 0 | AN36: 0 | AO36: 0 | AP36: 0 | AQ36: 0 | AR36: 0 | AS36: 0 | AT36: 1 | AU36: 1 | AV36: 1 | AW36: 1 | AX36: 1 | AY36: 1 | AZ36: 1 | BA36: 1 | BB36: 1 | BC36: 1 | BD36: 1 | BE36: 1 | BF36: 1 | BG36: 1 | BH36: 1 | BI36: 1 | BJ36: 1 | BK36: 1 | BL36: 1 | BM36: 1 | BN36: 1 | BO36: 1 | BP36: 1 | BQ36: 1
B37: Role 6 | J37: 0 | K37: 0 | L37: 0 | M37: 0 | N37: 0 | O37: 0 | P37: 0 | Q37: 0 | R37: 0 | S37: 0 | T37: 0 | U37: 0 | V37: 0 | W37: 0 | X37: 0 | Y37: 0 | Z37: 0 | AA37: 0 | AB37: 0 | AC37: 0 | AD37: 0 | AE37: 0 | AF37: 0 | AG37: 0 | AH37: 0 | AI37: 0 | AJ37: 0 | AK37: 0 | AL37: 0 | AM37: 0 | AN37: 0 | AO37: 0 | AP37: 0 | AQ37: 0 | AR37: 0 | AS37: 0 | AT37: 0 | AU37: 0 | AV37: 0 | AW37: 0 | AX37: 0 | AY37: 0 | AZ37: 0 | BA37: 0 | BB37: 0 | BC37: 0 | BD37: 0 | BE37: 0 | BF37: 1 | BG37: 1 | BH37: 1 | BI37: 1 | BJ37: 1 | BK37: 1 | BL37: 1 | BM37: 1 | BN37: 1 | BO37: 1 | BP37: 1 | BQ37: 1
B38: Total Headcount | J38: =SUM(J32:J37) -> 0 | K38: =SUM(K32:K37) -> 0 | L38: =SUM(L32:L37) -> 0 | M38: =SUM(M32:M37) -> 0 | N38: =SUM(N32:N37) -> 0 | O38: =SUM(O32:O37) -> 0 | P38: =SUM(P32:P37) -> 0 | Q38: =SUM(Q32:Q37) -> 0 | ... BQ38: =SUM(BQ32:BQ37) -> 6
B40: Wages and Salaries | C40: Salary
B41: =B32 -> Administrator | C41: 25000 | J41: 5000 | K41: 0 | L41: 5000 | M41: 5000 | N41: 5000 | O41: 5000 | P41: =($C41/12)*P32 -> 0 | Q41: =($C41/12)*Q32 -> 0 | R41: =($C41/12)*R32 -> 0 | S41: =($C41/12)*S32 -> 2083.3333 | T41: =($C41/12)*T32 -> 2083.3333 | U41: =($C41/12)*U32 -> 2083.3333 | V41: =($C41/12)*V32 -> 2083.3333 | W41: =($C41/12)*W32 -> 2083.3333 | ... BQ41: =($C41/12)*BQ32 -> 2083.3333
B42: =B33 -> Software Admin | C42: 25000 | J42: =($C42/12)*J33 -> 0 | K42: =($C42/12)*K33 -> 0 | L42: =($C42/12)*L33 -> 0 | M42: =($C42/12)*M33 -> 0 | N42: =($C42/12)*N33 -> 0 | O42: =($C42/12)*O33 -> 0 | P42: =($C42/12)*P33 -> 0 | Q42: =($C42/12)*Q33 -> 0 | ... BQ42: =($C42/12)*BQ33 -> 2083.3333
B43: =B34 -> Accountant | C43: 45000 | J43: =($C43/12)*J34 -> 0 | K43: =($C43/12)*K34 -> 0 | L43: =($C43/12)*L34 -> 0 | M43: =($C43/12)*M34 -> 0 | N43: =($C43/12)*N34 -> 0 | O43: =($C43/12)*O34 -> 0 | P43: =($C43/12)*P34 -> 0 | Q43: =($C43/12)*Q34 -> 0 | ... BQ43: =($C43/12)*BQ34 -> 3750
B44: =B35 -> Role 4 | C44: 30000 | J44: =($C44/12)*J35 -> 0 | K44: =($C44/12)*K35 -> 0 | L44: =($C44/12)*L35 -> 0 | M44: =($C44/12)*M35 -> 0 | N44: =($C44/12)*N35 -> 0 | O44: =($C44/12)*O35 -> 0 | P44: =($C44/12)*P35 -> 0 | Q44: =($C44/12)*Q35 -> 0 | ... BQ44: =($C44/12)*BQ35 -> 2500
B45: =B36 -> Role 5 | C45: 35000 | J45: =($C45/12)*J36 -> 0 | K45: =($C45/12)*K36 -> 0 | L45: =($C45/12)*L36 -> 0 | M45: =($C45/12)*M36 -> 0 | N45: =($C45/12)*N36 -> 0 | O45: =($C45/12)*O36 -> 0 | P45: =($C45/12)*P36 -> 0 | Q45: =($C45/12)*Q36 -> 0 | ... BQ45: =($C45/12)*BQ36 -> 2916.6667
B46: =B37 -> Role 6 | C46: 35000 | J46: =($C46/12)*J37 -> 0 | K46: =($C46/12)*K37 -> 0 | L46: =($C46/12)*L37 -> 0 | M46: =($C46/12)*M37 -> 0 | N46: =($C46/12)*N37 -> 0 | O46: =($C46/12)*O37 -> 0 | P46: =($C46/12)*P37 -> 0 | Q46: =($C46/12)*Q37 -> 0 | ... BQ46: =($C46/12)*BQ37 -> 2916.6667
B47: Total Wages and Salaries Gross Salary | J47: =SUM(J41:J46) -> 5000 | K47: =SUM(K41:K46) -> 0 | L47: =SUM(L41:L46) -> 5000 | M47: =SUM(M41:M46) -> 5000 | N47: =SUM(N41:N46) -> 5000 | O47: =SUM(O41:O46) -> 5000 | P47: =SUM(P41:P46) -> 0 | Q47: =SUM(Q41:Q46) -> 0 | ... BQ47: =SUM(BQ41:BQ46) -> 16250
B50: Ers NI | J50: 0 | K50: 0 | L50: 0 | M50: 0 | N50: 0 | O50: 0 | P50: =P47*Inputs!P14 -> 0 | Q50: =Q47*Inputs!Q14 -> 0 | R50: =R47*Inputs!R14 -> 0 | S50: =S47*Inputs!S14 -> 625 | T50: =T47*Inputs!T14 -> 625 | U50: =U47*Inputs!U14 -> 625 | V50: =V47*Inputs!V14 -> 625 | W50: =W47*Inputs!W14 -> 1187.5 | ... BQ50: =BQ47*Inputs!BQ14 -> 2437.5
B51: Pension | J51: 0 | K51: 0 | L51: 0 | M51: 0 | N51: 0 | O51: 0 | P51: =P47*Inputs!P15 -> 0 | Q51: =Q47*Inputs!Q15 -> 0 | R51: =R47*Inputs!R15 -> 0 | S51: =S47*Inputs!S15 -> 125 | T51: =T47*Inputs!T15 -> 125 | U51: =U47*Inputs!U15 -> 125 | V51: =V47*Inputs!V15 -> 125 | W51: =W47*Inputs!W15 -> 237.5 | ... BQ51: =BQ47*Inputs!BQ15 -> 487.5
B52: PAYE | J52: 0 | K52: 0 | L52: 0 | M52: 0 | N52: 0 | O52: 0 | P52: =P47*Inputs!P12 -> 0 | Q52: =Q47*Inputs!Q12 -> 0 | R52: =R47*Inputs!R12 -> 0 | S52: =S47*Inputs!S12 -> 1041.6667 | T52: =T47*Inputs!T12 -> 1041.6667 | U52: =U47*Inputs!U12 -> 1041.6667 | V52: =V47*Inputs!V12 -> 1041.6667 | W52: =W47*Inputs!W12 -> 1979.1667 | ... BQ52: =BQ47*Inputs!BQ12 -> 4062.5
B53: Ees NI | J53: 0 | K53: 0 | L53: 0 | M53: 0 | N53: 0 | O53: 0 | P53: =P47*Inputs!P13 -> 0 | Q53: =Q47*Inputs!Q13 -> 0 | R53: =R47*Inputs!R13 -> 0 | S53: =S47*Inputs!S13 -> 458.33333 | T53: =T47*Inputs!T13 -> 458.33333 | U53: =U47*Inputs!U13 -> 458.33333 | V53: =V47*Inputs!V13 -> 458.33333 | W53: =W47*Inputs!W13 -> 870.83333 | ... BQ53: =BQ47*Inputs!BQ13 -> 1787.5
B54: Total | J54: =SUM(J50:J53) -> 0 | K54: =SUM(K50:K53) -> 0 | L54: =SUM(L50:L53) -> 0 | M54: =SUM(M50:M53) -> 0 | N54: =SUM(N50:N53) -> 0 | O54: =SUM(O50:O53) -> 0 | P54: =SUM(P50:P53) -> 0 | Q54: =SUM(Q50:Q53) -> 0 | ... BQ54: =SUM(BQ50:BQ53) -> 8775
B57: Directors
B58: CEO - TH | J58: 0 | K58: 0 | L58: 0 | M58: 0 | N58: 0 | O58: 0 | P58: 0 | Q58: 0 | R58: 0 | S58: 0 | T58: 0 | U58: 0 | V58: 0 | W58: 0 | X58: 1 | Y58: 1 | Z58: 1 | AA58: 1 | AB58: 1 | AC58: 1 | AD58: 1 | AE58: 1 | AF58: 1 | AG58: 1 | AH58: 1 | AI58: 1 | AJ58: 1 | AK58: 1 | AL58: 1 | AM58: 1 | AN58: 1 | AO58: 1 | AP58: 1 | AQ58: 1 | AR58: 1 | AS58: 1 | AT58: 1 | AU58: 1 | AV58: 1 | AW58: 1 | AX58: 1 | AY58: 1 | AZ58: 1 | BA58: 1 | BB58: 1 | BC58: 1 | BD58: 1 | BE58: 1 | BF58: 1 | BG58: 1 | BH58: 1 | BI58: 1 | BJ58: 1 | BK58: 1 | BL58: 1 | BM58: 1 | BN58: 1 | BO58: 1 | BP58: 1 | BQ58: 1
B59: Owen | J59: 0 | K59: 0 | L59: 0 | M59: 0 | N59: 0 | O59: 0 | P59: 0 | Q59: 0 | R59: 0 | S59: 0 | T59: 0 | U59: 0 | V59: 0 | W59: 0 | X59: 1 | Y59: 1 | Z59: 1 | AA59: 1 | AB59: 1 | AC59: 1 | AD59: 1 | AE59: 1 | AF59: 1 | AG59: 1 | AH59: 1 | AI59: 1 | AJ59: 1 | AK59: 1 | AL59: 1 | AM59: 1 | AN59: 1 | AO59: 1 | AP59: 1 | AQ59: 1 | AR59: 1 | AS59: 1 | AT59: 1 | AU59: 1 | AV59: 1 | AW59: 1 | AX59: 1 | AY59: 1 | AZ59: 1 | BA59: 1 | BB59: 1 | BC59: 1 | BD59: 1 | BE59: 1 | BF59: 1 | BG59: 1 | BH59: 1 | BI59: 1 | BJ59: 1 | BK59: 1 | BL59: 1 | BM59: 1 | BN59: 1 | BO59: 1 | BP59: 1 | BQ59: 1
B60: FD | J60: 0 | K60: 0 | L60: 0 | M60: 0 | N60: 0 | O60: 0 | P60: 0 | Q60: 0 | R60: 0 | S60: 0 | T60: 0 | U60: 0 | V60: 0 | W60: 1 | X60: 1 | Y60: 1 | Z60: 1 | AA60: 1 | AB60: 1 | AC60: 1 | AD60: 1 | AE60: 1 | AF60: 1 | AG60: 1 | AH60: 1 | AI60: 1 | AJ60: 1 | AK60: 1 | AL60: 1 | AM60: 1 | AN60: 1 | AO60: 1 | AP60: 1 | AQ60: 1 | AR60: 1 | AS60: 1 | AT60: 1 | AU60: 1 | AV60: 1 | AW60: 1 | AX60: 1 | AY60: 1 | AZ60: 1 | BA60: 1 | BB60: 1 | BC60: 1 | BD60: 1 | BE60: 1 | BF60: 1 | BG60: 1 | BH60: 1 | BI60: 1 | BJ60: 1 | BK60: 1 | BL60: 1 | BM60: 1 | BN60: 1 | BO60: 1 | BP60: 1 | BQ60: 1
B61: Role 4 | J61: 0 | K61: 0 | L61: 0 | M61: 0 | N61: 0 | O61: 0 | P61: 0 | Q61: 0 | R61: 0 | S61: 0 | T61: 0 | U61: 0 | V61: 0 | W61: 0 | X61: 0 | Y61: 0 | Z61: 0 | AA61: 0 | AB61: 0 | AC61: 0 | AD61: 0 | AE61: 0 | AF61: 0 | AG61: 0 | AH61: 0 | AI61: 0 | AJ61: 0 | AK61: 0 | AL61: 0 | AM61: 0 | AN61: 0 | AO61: 0 | AP61: 0 | AQ61: 0 | AR61: 0 | AS61: 0 | AT61: 0 | AU61: 0 | AV61: 0 | AW61: 0 | AX61: 0 | AY61: 0 | AZ61: 0 | BA61: 0 | BB61: 0 | BC61: 0 | BD61: 0 | BE61: 0 | BF61: 0 | BG61: 0 | BH61: 0 | BI61: 0 | BJ61: 0 | BK61: 0 | BL61: 0 | BM61: 0 | BN61: 0 | BO61: 0 | BP61: 0 | BQ61: 0
B62: Role 5 | J62: 0 | K62: 0 | L62: 0 | M62: 0 | N62: 0 | O62: 0 | P62: 0 | Q62: 0 | R62: 0 | S62: 0 | T62: 0 | U62: 0 | V62: 0 | W62: 0 | X62: 0 | Y62: 0 | Z62: 0 | AA62: 0 | AB62: 0 | AC62: 0 | AD62: 0 | AE62: 0 | AF62: 0 | AG62: 0 | AH62: 0 | AI62: 0 | AJ62: 0 | AK62: 0 | AL62: 0 | AM62: 0 | AN62: 0 | AO62: 0 | AP62: 0 | AQ62: 0 | AR62: 0 | AS62: 0 | AT62: 0 | AU62: 0 | AV62: 0 | AW62: 0 | AX62: 0 | AY62: 0 | AZ62: 0 | BA62: 0 | BB62: 0 | BC62: 0 | BD62: 0 | BE62: 0 | BF62: 0 | BG62: 0 | BH62: 0 | BI62: 0 | BJ62: 0 | BK62: 0 | BL62: 0 | BM62: 0 | BN62: 0 | BO62: 0 | BP62: 0 | BQ62: 0
B63: Role 6 | J63: 0 | K63: 0 | L63: 0 | M63: 0 | N63: 0 | O63: 0 | P63: 0 | Q63: 0 | R63: 0 | S63: 0 | T63: 0 | U63: 0 | V63: 0 | W63: 0 | X63: 0 | Y63: 0 | Z63: 0 | AA63: 0 | AB63: 0 | AC63: 0 | AD63: 0 | AE63: 0 | AF63: 0 | AG63: 0 | AH63: 0 | AI63: 0 | AJ63: 0 | AK63: 0 | AL63: 0 | AM63: 0 | AN63: 0 | AO63: 0 | AP63: 0 | AQ63: 0 | AR63: 0 | AS63: 0 | AT63: 0 | AU63: 0 | AV63: 0 | AW63: 0 | AX63: 0 | AY63: 0 | AZ63: 0 | BA63: 0 | BB63: 0 | BC63: 0 | BD63: 0 | BE63: 0 | BF63: 0 | BG63: 0 | BH63: 0 | BI63: 0 | BJ63: 0 | BK63: 0 | BL63: 0 | BM63: 0 | BN63: 0 | BO63: 0 | BP63: 0 | BQ63: 0
B64: Total Headcount | J64: =SUM(J58:J63) -> 0 | K64: =SUM(K58:K63) -> 0 | L64: =SUM(L58:L63) -> 0 | M64: =SUM(M58:M63) -> 0 | N64: =SUM(N58:N63) -> 0 | O64: =SUM(O58:O63) -> 0 | P64: =SUM(P58:P63) -> 0 | Q64: =SUM(Q58:Q63) -> 0 | ... BQ64: =SUM(BQ58:BQ63) -> 3
B66: Directors | C66: Salary
B67: =B58 -> CEO - TH | C67: 180000 | J67: 0 | K67: 0 | L67: 0 | M67: 0 | N67: 0 | O67: 0 | P67: =($C67/12)*P58 -> 0 | Q67: =($C67/12)*Q58 -> 0 | R67: =($C67/12)*R58 -> 0 | S67: =($C67/12)*S58 -> 0 | T67: =($C67/12)*T58 -> 0 | U67: =($C67/12)*U58 -> 0 | V67: =($C67/12)*V58 -> 0 | W67: =($C67/12)*W58 -> 0 | ... BQ67: =($C67/12)*BQ58 -> 15000
B68: =B59 -> Owen | C68: 120000 | J68: =($C68/12)*J59 -> 0 | K68: =($C68/12)*K59 -> 0 | L68: =($C68/12)*L59 -> 0 | M68: =($C68/12)*M59 -> 0 | N68: =($C68/12)*N59 -> 0 | O68: =($C68/12)*O59 -> 0 | P68: =($C68/12)*P59 -> 0 | Q68: =($C68/12)*Q59 -> 0 | ... BQ68: =($C68/12)*BQ59 -> 10000
B69: =B60 -> FD | C69: 150000 | J69: =($C69/12)*J60 -> 0 | K69: =($C69/12)*K60 -> 0 | L69: =($C69/12)*L60 -> 0 | M69: =($C69/12)*M60 -> 0 | N69: =($C69/12)*N60 -> 0 | O69: =($C69/12)*O60 -> 0 | P69: =($C69/12)*P60 -> 0 | Q69: =($C69/12)*Q60 -> 0 | ... BQ69: =($C69/12)*BQ60 -> 12500
B70: =B61 -> Role 4 | J70: =($C70/12)*J61 -> 0 | K70: =($C70/12)*K61 -> 0 | L70: =($C70/12)*L61 -> 0 | M70: =($C70/12)*M61 -> 0 | N70: =($C70/12)*N61 -> 0 | O70: =($C70/12)*O61 -> 0 | P70: =($C70/12)*P61 -> 0 | Q70: =($C70/12)*Q61 -> 0 | ... BQ70: =($C70/12)*BQ61 -> 0
B71: =B62 -> Role 5 | J71: =($C71/12)*J62 -> 0 | K71: =($C71/12)*K62 -> 0 | L71: =($C71/12)*L62 -> 0 | M71: =($C71/12)*M62 -> 0 | N71: =($C71/12)*N62 -> 0 | O71: =($C71/12)*O62 -> 0 | P71: =($C71/12)*P62 -> 0 | Q71: =($C71/12)*Q62 -> 0 | ... BQ71: =($C71/12)*BQ62 -> 0
B72: =B63 -> Role 6 | J72: =($C72/12)*J63 -> 0 | K72: =($C72/12)*K63 -> 0 | L72: =($C72/12)*L63 -> 0 | M72: =($C72/12)*M63 -> 0 | N72: =($C72/12)*N63 -> 0 | O72: =($C72/12)*O63 -> 0 | P72: =($C72/12)*P63 -> 0 | Q72: =($C72/12)*Q63 -> 0 | ... BQ72: =($C72/12)*BQ63 -> 0
B73: Total Directors Gross Salary | J73: =SUM(J67:J72) -> 0 | K73: =SUM(K67:K72) -> 0 | L73: =SUM(L67:L72) -> 0 | M73: =SUM(M67:M72) -> 0 | N73: =SUM(N67:N72) -> 0 | O73: =SUM(O67:O72) -> 0 | P73: =SUM(P67:P72) -> 0 | Q73: =SUM(Q67:Q72) -> 0 | ... BQ73: =SUM(BQ67:BQ72) -> 37500
B76: Ers NI | J76: 0 | K76: 0 | L76: 0 | M76: 0 | N76: 0 | O76: 0 | P76: =P73*Inputs!P19 -> 0 | Q76: =Q73*Inputs!Q19 -> 0 | R76: =R73*Inputs!R19 -> 0 | S76: =S73*Inputs!S19 -> 0 | T76: =T73*Inputs!T19 -> 0 | U76: =U73*Inputs!U19 -> 0 | V76: =V73*Inputs!V19 -> 0 | W76: =W73*Inputs!W19 -> 1750 | ... BQ76: =BQ73*Inputs!BQ19 -> 5250
B77: Pension | J77: 0 | K77: 0 | L77: 0 | M77: 0 | N77: 0 | O77: 0 | P77: =P73*Inputs!P20 -> 0 | Q77: =Q73*Inputs!Q20 -> 0 | R77: =R73*Inputs!R20 -> 0 | S77: =S73*Inputs!S20 -> 0 | T77: =T73*Inputs!T20 -> 0 | U77: =U73*Inputs!U20 -> 0 | V77: =V73*Inputs!V20 -> 0 | W77: =W73*Inputs!W20 -> 375 | ... BQ77: =BQ73*Inputs!BQ20 -> 1125
B78: PAYE | J78: 0 | K78: 0 | L78: 0 | M78: 0 | N78: 0 | O78: 0 | P78: =P73*Inputs!P17 -> 0 | Q78: =Q73*Inputs!Q17 -> 0 | R78: =R73*Inputs!R17 -> 0 | S78: =S73*Inputs!S17 -> 0 | T78: =T73*Inputs!T17 -> 0 | U78: =U73*Inputs!U17 -> 0 | V78: =V73*Inputs!V17 -> 0 | W78: =W73*Inputs!W17 -> 4375 | ... BQ78: =BQ73*Inputs!BQ17 -> 13125
B79: Ees NI | J79: 0 | K79: 0 | L79: 0 | M79: 0 | N79: 0 | O79: 0 | P79: =P73*Inputs!P18 -> 0 | Q79: =Q73*Inputs!Q18 -> 0 | R79: =R73*Inputs!R18 -> 0 | S79: =S73*Inputs!S18 -> 0 | T79: =T73*Inputs!T18 -> 0 | U79: =U73*Inputs!U18 -> 0 | V79: =V73*Inputs!V18 -> 0 | W79: =W73*Inputs!W18 -> 625 | ... BQ79: =BQ73*Inputs!BQ18 -> 1875
B80: Total | J80: =SUM(J76:J79) -> 0 | K80: =SUM(K76:K79) -> 0 | L80: =SUM(L76:L79) -> 0 | M80: =SUM(M76:M79) -> 0 | N80: =SUM(N76:N79) -> 0 | O80: =SUM(O76:O79) -> 0 | P80: =SUM(P76:P79) -> 0 | Q80: =SUM(Q76:Q79) -> 0 | ... BQ80: =SUM(BQ76:BQ79) -> 21375
B84: Total Monthly Payroll Related Costs
B85: COS | J85: =J28 -> 0 | K85: =K28 -> 0 | L85: =L28 -> 0 | M85: =M28 -> 0 | N85: =N28 -> 0 | O85: =O28 -> 0 | P85: =P28 -> 0 | Q85: =Q28 -> 0 | ... BQ85: =BQ28 -> 19350
B86: Wages and Salaries | J86: =J54 -> 0 | K86: =K54 -> 0 | L86: =L54 -> 0 | M86: =M54 -> 0 | N86: =N54 -> 0 | O86: =O54 -> 0 | P86: =P54 -> 0 | Q86: =Q54 -> 0 | ... BQ86: =BQ54 -> 8775
B87: Directors | J87: =J80 -> 0 | K87: =K80 -> 0 | L87: =L80 -> 0 | M87: =M80 -> 0 | N87: =N80 -> 0 | O87: =O80 -> 0 | P87: =P80 -> 0 | Q87: =Q80 -> 0 | ... BQ87: =BQ80 -> 21375
B88: Total | J88: =SUM(J85:J87) -> 0 | K88: =SUM(K85:K87) -> 0 | L88: =SUM(L85:L87) -> 0 | M88: =SUM(M85:M87) -> 0 | N88: =SUM(N85:N87) -> 0 | O88: =SUM(O85:O87) -> 0 | P88: =SUM(P85:P87) -> 0 | Q88: =SUM(Q85:Q87) -> 0 | ... BQ88: =SUM(BQ85:BQ87) -> 49500

Sheet Fixed Assets
A1: Business 1
A2: Fixed Assets | J2: =Timing!J2 -> 44986 | K2: =Timing!K2 -> 45017 | L2: =Timing!L2 -> 45047 | M2: =Timing!M2 -> 45078 | N2: =Timing!N2 -> 45108 | O2: =Timing!O2 -> 45139 | P2: =Timing!P2 -> 45170 | Q2: =Timing!Q2 -> 45200 | ... BQ2: =Timing!BQ2 -> 46784
J3: =Timing!J3 -> 45016 | K3: =Timing!K3 -> 45046 | L3: =Timing!L3 -> 45077 | M3: =Timing!M3 -> 45107 | N3: =Timing!N3 -> 45138 | O3: =Timing!O3 -> 45169 | P3: =Timing!P3 -> 45199 | Q3: =Timing!Q3 -> 45230 | ... BQ3: =Timing!BQ3 -> 46812
B6: Intangible Fixed Assets
B8: Intangible fixed assets
B9: Cost brought forward | J9: 0 | K9: =J12 -> 0 | L9: =K12 -> 0 | M9: =L12 -> 0 | N9: =M12 -> 0 | O9: =N12 -> 0 | P9: =O12 -> 0 | Q9: =P12 -> 0 | R9: =Q12 -> 0 | ... BQ9: =BP12 -> 140000
B10: Additions | J10: 0 | K10: 0 | L10: 0 | M10: 0 | N10: 0 | O10: 0 | P10: 0 | Q10: 0 | R10: 0 | S10: 0 | T10: 35000 | U10: 35000 | V10: 35000 | W10: 35000 | X10: 0 | Y10: 0 | Z10: 0 | AA10: 0 | AB10: 0 | AC10: 0 | AD10: 0 | AE10: 0 | AF10: 0 | AG10: 0 | AH10: 0 | AI10: 0 | AJ10: 0 | AK10: 0 | AL10: 0 | AM10: 0 | AN10: 0 | AO10: 0 | AP10: 0 | AQ10: 0 | AR10: 0 | AS10: 0 | AT10: 0 | AU10: 0 | AV10: 0 | AW10: 0 | AX10: 0 | AY10: 0 | AZ10: 0 | BA10: 0 | BB10: 0 | BC10: 0 | BD10: 0 | BE10: 0 | BF10: 0 | BG10: 0 | BH10: 0 | BI10: 0 | BJ10: 0 | BK10: 0 | BL10: 0 | BM10: 0 | BN10: 0 | BO10: 0 | BP10: 0 | BQ10: 0
B11: Disposals | J11: 0 | K11: 0 | L11: 0 | M11: 0 | N11: 0 | O11: 0 | P11: 0 | Q11: 0 | R11: 0 | S11: 0 | T11: 0 | U11: 0 | V11: 0 | W11: 0 | X11: 0 | Y11: 0 | Z11: 0 | AA11: 0 | AB11: 0 | AC11: 0 | AD11: 0 | AE11: 0 | AF11: 0 | AG11: 0 | AH11: 0 | AI11: 0 | AJ11: 0 | AK11: 0 | AL11: 0 | AM11: 0 | AN11: 0 | AO11: 0 | AP11: 0 | AQ11: 0 | AR11: 0 | AS11: 0 | AT11: 0 | AU11: 0 | AV11: 0 | AW11: 0 | AX11: 0 | AY11: 0 | AZ11: 0 | BA11: 0 | BB11: 0 | BC11: 0 | BD11: 0 | BE11: 0 | BF11: 0 | BG11: 0 | BH11: 0 | BI11: 0 | BJ11: 0 | BK11: 0 | BL11: 0 | BM11: 0 | BN11: 0 | BO11: 0 | BP11: 0 | BQ11: 0
B12: Cost carried forward | J12: =SUM(J9:J11) -> 0 | K12: =SUM(K9:K11) -> 0 | L12: =SUM(L9:L11) -> 0 | M12: =SUM(M9:M11) -> 0 | N12: =SUM(N9:N11) -> 0 | O12: =SUM(O9:O11) -> 0 | P12: =SUM(P9:P11) -> 0 | Q12: =SUM(Q9:Q11) -> 0 | ... BQ12: =SUM(BQ9:BQ11) -> 140000
B14: Amortisation brought forward | J14: 0 | K14: =J17 -> 0 | L14: =K17 -> 0 | M14: =L17 -> 0 | N14: =M17 -> 0 | O14: =N17 -> 0 | P14: =O17 -> 0 | Q14: =P17 -> 0 | R14: =Q17 -> 0 | ... BQ14: =BP17 -> 69270.833
B15: Amortisation charge | J15: =(J12*Inputs!J23)/12 -> 0 | K15: =(K12*Inputs!K23)/12 -> 0 | L15: =(L12*Inputs!L23)/12 -> 0 | M15: =(M12*Inputs!M23)/12 -> 0 | N15: =(N12*Inputs!N23)/12 -> 0 | O15: =(O12*Inputs!O23)/12 -> 0 | P15: =(P12*Inputs!P23)/12 -> 0 | Q15: =(Q12*Inputs!Q23)/12 -> 0 | ... BQ15: =(BQ12*Inputs!BQ23)/12 -> 1458.3333
B16: Amortisation on disposals | J16: 0 | K16: 0 | L16: 0 | M16: 0 | N16: 0 | O16: 0 | P16: 0 | Q16: 0 | R16: 0 | S16: 0 | T16: 0 | U16: 0 | V16: 0 | W16: 0 | X16: 0 | Y16: 0 | Z16: 0 | AA16: 0 | AB16: 0 | AC16: 0 | AD16: 0 | AE16: 0 | AF16: 0 | AG16: 0 | AH16: 0 | AI16: 0 | AJ16: 0 | AK16: 0 | AL16: 0 | AM16: 0 | AN16: 0 | AO16: 0 | AP16: 0 | AQ16: 0 | AR16: 0 | AS16: 0 | AT16: 0 | AU16: 0 | AV16: 0 | AW16: 0 | AX16: 0 | AY16: 0 | AZ16: 0 | BA16: 0 | BB16: 0 | BC16: 0 | BD16: 0 | BE16: 0 | BF16: 0 | BG16: 0 | BH16: 0 | BI16: 0 | BJ16: 0 | BK16: 0 | BL16: 0 | BM16: 0 | BN16: 0 | BO16: 0 | BP16: 0 | BQ16: 0
B17: Amortisation carried forward | J17: =SUM(J14:J16) -> 0 | K17: =SUM(K14:K16) -> 0 | L17: =SUM(L14:L16) -> 0 | M17: =SUM(M14:M16) -> 0 | N17: =SUM(N14:N16) -> 0 | O17: =SUM(O14:O16) -> 0 | P17: =SUM(P14:P16) -> 0 | Q17: =SUM(Q14:Q16) -> 0 | ... BQ17: =SUM(BQ14:BQ16) -> 70729.167
B19: Net book value | J19: =J12-J17 -> 0 | K19: =K12-K17 -> 0 | L19: =L12-L17 -> 0 | M19: =M12-M17 -> 0 | N19: =N12-N17 -> 0 | O19: =O12-O17 -> 0 | P19: =P12-P17 -> 0 | Q19: =Q12-Q17 -> 0 | ... BQ19: =BQ12-BQ17 -> 69270.833
B22: TANGIBLE FIXED ASSETS
B24: Tangible fixed assets - Screens
B25: Cost brought forward | J25: 0 | K25: =J28 -> 0 | L25: =K28 -> 0 | M25: =L28 -> 0 | N25: =M28 -> 0 | O25: =N28 -> 0 | P25: =O28 -> 0 | Q25: =P28 -> 0 | R25: =Q28 -> 0 | ... BQ25: =BP28 -> 1516580
B26: Additions | J26: =J88 -> 0 | K26: =K88 -> 0 | L26: =L88 -> 0 | M26: =M88 -> 0 | N26: =N88 -> 0 | O26: =O88 -> 0 | P26: =P88 -> 0 | Q26: =Q88 -> 0 | ... BQ26: =BQ88 -> 39520
B27: Disposals
B28: Cost carried forward | J28: =SUM(J25:J27) -> 0 | K28: =SUM(K25:K27) -> 0 | L28: =SUM(L25:L27) -> 0 | M28: =SUM(M25:M27) -> 0 | N28: =SUM(N25:N27) -> 0 | O28: =SUM(O25:O27) -> 0 | P28: =SUM(P25:P27) -> 0 | Q28: =SUM(Q25:Q27) -> 0 | ... BQ28: =SUM(BQ25:BQ27) -> 1556100
B30: Depreciation brought forward | J30: 0 | K30: =J33 -> 0 | L30: =K33 -> 0 | M30: =L33 -> 0 | N30: =M33 -> 0 | O30: =N33 -> 0 | P30: =O33 -> 0 | Q30: =P33 -> 0 | R30: =Q33 -> 0 | ... BQ30: =BP33 -> 695922.5
B31: Depreciation charge | J31: =(J28*Inputs!J24)/12 -> 0 | K31: =(K28*Inputs!K24)/12 -> 0 | L31: =(L28*Inputs!L24)/12 -> 0 | M31: =(M28*Inputs!M24)/12 -> 0 | N31: =(N28*Inputs!N24)/12 -> 0 | O31: =(O28*Inputs!O24)/12 -> 0 | P31: =(P28*Inputs!P24)/12 -> 0 | Q31: =(Q28*Inputs!Q24)/12 -> 0 | ... BQ31: =(BQ28*Inputs!BQ24)/12 -> 32418.75
B32: Depreciation on disposals
B33: Depreciation carried forward | J33: =SUM(J30:J32) -> 0 | K33: =SUM(K30:K32) -> 0 | L33: =SUM(L30:L32) -> 0 | M33: =SUM(M30:M32) -> 0 | N33: =SUM(N30:N32) -> 0 | O33: =SUM(O30:O32) -> 0 | P33: =SUM(P30:P32) -> 0 | Q33: =SUM(Q30:Q32) -> 0 | ... BQ33: =SUM(BQ30:BQ32) -> 728341.25
B35: Net book value | J35: =J28-J33 -> 0 | K35: =K28-K33 -> 0 | L35: =L28-L33 -> 0 | M35: =M28-M33 -> 0 | N35: =N28-N33 -> 0 | O35: =O28-O33 -> 0 | P35: =P28-P33 -> 0 | Q35: =Q28-Q33 -> 0 | ... BQ35: =BQ28-BQ33 -> 827758.75
B38: Tangible fixed assets - Office Equipment
B39: Cost brought forward | J39: 0 | K39: =J42 -> 0 | L39: =K42 -> 0 | M39: =L42 -> 0 | N39: =M42 -> 0 | O39: =N42 -> 0 | P39: =O42 -> 0 | Q39: =P42 -> 0 | R39: =Q42 -> 0 | ... BQ39: =BP42 -> 7000
B40: Additions | J40: 0 | T40: 1000 | X40: 1000 | AB40: 1000 | AF40: 1000 | AJ40: 1000 | AN40: 1000 | AR40: 1000
B41: Disposals
B42: Cost carried forward | J42: =SUM(J39:J41) -> 0 | K42: =SUM(K39:K41) -> 0 | L42: =SUM(L39:L41) -> 0 | M42: =SUM(M39:M41) -> 0 | N42: =SUM(N39:N41) -> 0 | O42: =SUM(O39:O41) -> 0 | P42: =SUM(P39:P41) -> 0 | Q42: =SUM(Q39:Q41) -> 0 | ... BQ42: =SUM(BQ39:BQ41) -> 7000
B44: Depreciation brought forward | J44: 0 | K44: =J47 -> 0 | L44: =K47 -> 0 | M44: =L47 -> 0 | N44: =M47 -> 0 | O44: =N47 -> 0 | P44: =O47 -> 0 | Q44: =P47 -> 0 | R44: =Q47 -> 0 | ... BQ44: =BP47 -> 5395.8333
B45: Depreciation charge | J45: =(J42*Inputs!J25)/12 -> 0 | K45: =(K42*Inputs!K25)/12 -> 0 | L45: =(L42*Inputs!L25)/12 -> 0 | M45: =(M42*Inputs!M25)/12 -> 0 | N45: =(N42*Inputs!N25)/12 -> 0 | O45: =(O42*Inputs!O25)/12 -> 0 | P45: =(P42*Inputs!P25)/12 -> 0 | Q45: =(Q42*Inputs!Q25)/12 -> 0 | ... BQ45: =(BQ42*Inputs!BQ25)/12 -> 145.83333
B46: Depreciation on disposals
B47: Depreciation carried forward | J47: =SUM(J44:J46) -> 0 | K47: =SUM(K44:K46) -> 0 | L47: =SUM(L44:L46) -> 0 | M47: =SUM(M44:M46) -> 0 | N47: =SUM(N44:N46) -> 0 | O47: =SUM(O44:O46) -> 0 | P47: =SUM(P44:P46) -> 0 | Q47: =SUM(Q44:Q46) -> 0 | ... BQ47: =SUM(BQ44:BQ46) -> 5541.6667
B49: Net book value | J49: =J42-J47 -> 0 | K49: =K42-K47 -> 0 | L49: =L42-L47 -> 0 | M49: =M42-M47 -> 0 | N49: =N42-N47 -> 0 | O49: =O42-O47 -> 0 | P49: =P42-P47 -> 0 | Q49: =Q42-Q47 -> 0 | ... BQ49: =BQ42-BQ47 -> 1458.3333
B52: Tangible fixed assets - Computer Equipment
B53: Cost brought forward | J53: 0 | K53: =J56 -> 0 | L53: =K56 -> 0 | M53: =L56 -> 0 | N53: =M56 -> 0 | O53: =N56 -> 0 | P53: =O56 -> 0 | Q53: =P56 -> 0 | R53: =Q56 -> 0 | ... BQ53: =BP56 -> 14000
B54: Additions | J54: 0 | T54: 2000 | X54: 2000 | AB54: 2000 | AF54: 2000 | AJ54: 2000 | AN54: 2000 | AR54: 2000
B55: Disposals
B56: Cost carried forward | J56: =SUM(J53:J55) -> 0 | K56: =SUM(K53:K55) -> 0 | L56: =SUM(L53:L55) -> 0 | M56: =SUM(M53:M55) -> 0 | N56: =SUM(N53:N55) -> 0 | O56: =SUM(O53:O55) -> 0 | P56: =SUM(P53:P55) -> 0 | Q56: =SUM(Q53:Q55) -> 0 | ... BQ56: =SUM(BQ53:BQ55) -> 14000
B58: Depreciation brought forward | J58: 0 | K58: =J61 -> 0 | L58: =K61 -> 0 | M58: =L61 -> 0 | N58: =M61 -> 0 | O58: =N61 -> 0 | P58: =O61 -> 0 | Q58: =P61 -> 0 | R58: =Q61 -> 0 | ... BQ58: =BP61 -> 14245
B59: Depreciation charge | J59: =(J56*Inputs!J26)/12 -> 0 | K59: =(K56*Inputs!K26)/12 -> 0 | L59: =(L56*Inputs!L26)/12 -> 0 | M59: =(M56*Inputs!M26)/12 -> 0 | N59: =(N56*Inputs!N26)/12 -> 0 | O59: =(O56*Inputs!O26)/12 -> 0 | P59: =(P56*Inputs!P26)/12 -> 0 | Q59: =(Q56*Inputs!Q26)/12 -> 0 | ... BQ59: =(BQ56*Inputs!BQ26)/12 -> 385
B60: Depreciation on disposals
B61: Depreciation carried forward | J61: =SUM(J58:J60) -> 0 | K61: =SUM(K58:K60) -> 0 | L61: =SUM(L58:L60) -> 0 | M61: =SUM(M58:M60) -> 0 | N61: =SUM(N58:N60) -> 0 | O61: =SUM(O58:O60) -> 0 | P61: =SUM(P58:P60) -> 0 | Q61: =SUM(Q58:Q60) -> 0 | ... BQ61: =SUM(BQ58:BQ60) -> 14630
B63: Net book value | J63: =J56-J61 -> 0 | K63: =K56-K61 -> 0 | L63: =L56-L61 -> 0 | M63: =M56-M61 -> 0 | N63: =N56-N61 -> 0 | O63: =O56-O61 -> 0 | P63: =P56-P61 -> 0 | Q63: =Q56-Q61 -> 0 | ... BQ63: =BQ56-BQ61 -> -630
B66: Tangible fixed assets - Total
B67: Cost brought forward | J67: =J25+J39+J53 -> 0 | K67: =K25+K39+K53 -> 0 | L67: =L25+L39+L53 -> 0 | M67: =M25+M39+M53 -> 0 | N67: =N25+N39+N53 -> 0 | O67: =O25+O39+O53 -> 0 | P67: =P25+P39+P53 -> 0 | Q67: =Q25+Q39+Q53 -> 0 | ... BQ67: =BQ25+BQ39+BQ53 -> 1537580
B68: Additions | J68: =J26+J40+J54 -> 0 | K68: =K26+K40+K54 -> 0 | L68: =L26+L40+L54 -> 0 | M68: =M26+M40+M54 -> 0 | N68: =N26+N40+N54 -> 0 | O68: =O26+O40+O54 -> 0 | P68: =P26+P40+P54 -> 0 | Q68: =Q26+Q40+Q54 -> 0 | ... BQ68: =BQ26+BQ40+BQ54 -> 39520
B69: Disposals | J69: =J27+J41+J55 -> 0 | K69: =K27+K41+K55 -> 0 | L69: =L27+L41+L55 -> 0 | M69: =M27+M41+M55 -> 0 | N69: =N27+N41+N55 -> 0 | O69: =O27+O41+O55 -> 0 | P69: =P27+P41+P55 -> 0 | Q69: =Q27+Q41+Q55 -> 0 | ... BQ69: =BQ27+BQ41+BQ55 -> 0
B70: Cost carried forward | J70: =SUM(J67:J69) -> 0 | K70: =SUM(K67:K69) -> 0 | L70: =SUM(L67:L69) -> 0 | M70: =SUM(M67:M69) -> 0 | N70: =SUM(N67:N69) -> 0 | O70: =SUM(O67:O69) -> 0 | P70: =SUM(P67:P69) -> 0 | Q70: =SUM(Q67:Q69) -> 0 | ... BQ70: =SUM(BQ67:BQ69) -> 1577100
B72: Depreciation brought forward | J72: =J30+J44+J58 -> 0 | K72: =K30+K44+K58 -> 0 | L72: =L30+L44+L58 -> 0 | M72: =M30+M44+M58 -> 0 | N72: =N30+N44+N58 -> 0 | O72: =O30+O44+O58 -> 0 | P72: =P30+P44+P58 -> 0 | Q72: =Q30+Q44+Q58 -> 0 | ... BQ72: =BQ30+BQ44+BQ58 -> 715563.33
B73: Depreciation charge | J73: =J31+J45+J59 -> 0 | K73: =K31+K45+K59 -> 0 | L73: =L31+L45+L59 -> 0 | M73: =M31+M45+M59 -> 0 | N73: =N31+N45+N59 -> 0 | O73: =O31+O45+O59 -> 0 | P73: =P31+P45+P59 -> 0 | Q73: =Q31+Q45+Q59 -> 0 | ... BQ73: =BQ31+BQ45+BQ59 -> 32949.583
B74: Depreciation on disposals | J74: =J32+J46+J60 -> 0 | K74: =K32+K46+K60 -> 0 | L74: =L32+L46+L60 -> 0 | M74: =M32+M46+M60 -> 0 | N74: =N32+N46+N60 -> 0 | O74: =O32+O46+O60 -> 0 | P74: =P32+P46+P60 -> 0 | Q74: =Q32+Q46+Q60 -> 0 | ... BQ74: =BQ32+BQ46+BQ60 -> 0
B75: Depreciation carried forward | J75: =SUM(J72:J74) -> 0 | K75: =SUM(K72:K74) -> 0 | L75: =SUM(L72:L74) -> 0 | M75: =SUM(M72:M74) -> 0 | N75: =SUM(N72:N74) -> 0 | O75: =SUM(O72:O74) -> 0 | P75: =SUM(P72:P74) -> 0 | Q75: =SUM(Q72:Q74) -> 0 | ... BQ75: =SUM(BQ72:BQ74) -> 748512.92
B77: Net book value | J77: =J70-J75 -> 0 | K77: =K70-K75 -> 0 | L77: =L70-L75 -> 0 | M77: =M70-M75 -> 0 | N77: =N70-N75 -> 0 | O77: =O70-O75 -> 0 | P77: =P70-P75 -> 0 | Q77: =Q70-Q75 -> 0 | ... BQ77: =BQ70-BQ75 -> 828587.08
B78: check | J78: =(J35+J49+J63)-J77 -> 0 | K78: =(K35+K49+K63)-K77 -> 0 | L78: =(L35+L49+L63)-L77 -> 0 | M78: =(M35+M49+M63)-M77 -> 0 | N78: =(N35+N49+N63)-N77 -> 0 | O78: =(O35+O49+O63)-O77 -> 0 | P78: =(P35+P49+P63)-P77 -> 0 | Q78: =(Q35+Q49+Q63)-Q77 -> 0 | ... BQ78: =(BQ35+BQ49+BQ63)-BQ77 -> 0
B83: New Screens
B84: =Inputs!B39 -> ISP Funds £0 Capex | J84: =Inputs!J40 -> 0 | K84: =Inputs!K40 -> 0 | L84: =Inputs!L40 -> 0 | M84: =Inputs!M40 -> 0 | N84: =Inputs!N40 -> 0 | O84: =Inputs!O40 -> 0 | P84: =Inputs!P40 -> 0 | Q84: =Inputs!Q40 -> 0 | ... BQ84: =Inputs!BQ40 -> 32
B85: =Inputs!B43 -> Other | J85: =Inputs!J44 -> 0 | K85: =Inputs!K44 -> 0 | L85: =Inputs!L44 -> 0 | M85: =Inputs!M44 -> 0 | N85: =Inputs!N44 -> 0 | O85: =Inputs!O44 -> 0 | P85: =Inputs!P44 -> 0 | Q85: =Inputs!Q44 -> 0 | ... BQ85: =Inputs!BQ44 -> 0
B86: Total | J86: =SUM(J84:J85) -> 0 | K86: =SUM(K84:K85) -> 0 | L86: =SUM(L84:L85) -> 0 | M86: =SUM(M84:M85) -> 0 | N86: =SUM(N84:N85) -> 0 | O86: =SUM(O84:O85) -> 0 | P86: =SUM(P84:P85) -> 0 | Q86: =SUM(Q84:Q85) -> 0 | ... BQ86: =SUM(BQ84:BQ85) -> 32
B88: Cost of capex | J88: =J86*Inputs!J114 -> 0 | K88: =K86*Inputs!K114 -> 0 | L88: =L86*Inputs!L114 -> 0 | M88: =M86*Inputs!M114 -> 0 | N88: =N86*Inputs!N114 -> 0 | O88: =O86*Inputs!O114 -> 0 | P88: =P86*Inputs!P114 -> 0 | Q88: =Q86*Inputs!Q114 -> 0 | ... BQ88: =BQ86*Inputs!BQ114 -> 39520

Sheet Working Capital
A1: Business 1
A2: Working Capital | J2: =Timing!J2 -> 44986 | K2: =Timing!K2 -> 45017 | L2: =Timing!L2 -> 45047 | M2: =Timing!M2 -> 45078 | N2: =Timing!N2 -> 45108 | O2: =Timing!O2 -> 45139 | P2: =Timing!P2 -> 45170 | Q2: =Timing!Q2 -> 45200 | ... BQ2: =Timing!BQ2 -> 46784
J3: =Timing!J3 -> 45016 | K3: =Timing!K3 -> 45046 | L3: =Timing!L3 -> 45077 | M3: =Timing!M3 -> 45107 | N3: =Timing!N3 -> 45138 | O3: =Timing!O3 -> 45169 | P3: =Timing!P3 -> 45199 | Q3: =Timing!Q3 -> 45230 | ... BQ3: =Timing!BQ3 -> 46812
B6: Trade Debtors
B7: Net sales invoices | J7: 0 | K7: 33750 | L7: =Revenue!L15+Revenue!L31 -> 14620 | M7: =Revenue!M15+Revenue!M31 -> 62423 | N7: =Revenue!N15+Revenue!N31 -> 59774 | O7: =Revenue!O15+Revenue!O31 -> 157734 | P7: =Revenue!P15+Revenue!P31 -> 123732 | Q7: =Revenue!Q15+Revenue!Q31 -> 34625 | R7: =Revenue!R15+Revenue!R31 -> 38250 | S7: =Revenue!S15+Revenue!S31 -> 23350 | ... BQ7: =Revenue!BQ15+Revenue!BQ31 -> 1517672.8
B8: Output VAT | J8: 0 | K8: =K7*Inputs!K7 -> 6750 | L8: =L7*Inputs!L7 -> 2924 | M8: =M7*Inputs!M7 -> 12484.6 | N8: =N7*Inputs!N7 -> 11954.8 | O8: =O7*Inputs!O7 -> 31546.8 | P8: =P7*Inputs!P7 -> 24746.4 | Q8: =Q7*Inputs!Q7 -> 6925 | R8: =R7*Inputs!R7 -> 7650 | ... BQ8: =BQ7*Inputs!BQ7 -> 303534.55
B9: Gross sales invoices | J9: =SUM(J7:J8) -> 0 | K9: =SUM(K7:K8) -> 40500 | L9: =SUM(L7:L8) -> 17544 | M9: =SUM(M7:M8) -> 74907.6 | N9: =SUM(N7:N8) -> 71728.8 | O9: =SUM(O7:O8) -> 189280.8 | P9: =SUM(P7:P8) -> 148478.4 | Q9: =SUM(Q7:Q8) -> 41550 | ... BQ9: =SUM(BQ7:BQ8) -> 1821207.3
B10: Trade debtors brought forward | J10: 0 | K10: =J12 -> 0 | L10: =K12 -> 40500 | M10: =L12 -> 17545 | N10: =M12 -> 92453 | O10: =N12 -> 93407 | P10: =O12 -> 220509 | Q10: =P12 -> 297259.6 | R10: =Q12 -> 76688.8 | ... BQ10: =BP12 -> 2601942.4
B11: Trade debtor remittances | K11: =-K10/(Inputs!K9*(12/365)) -> 0 | L11: =-L10/(Inputs!L9*(12/365)) -> -27375 | M11: =-M10/(Inputs!M9*(12/365)) -> -11859.12 | N11: =-N10/(Inputs!N9*(12/365)) -> -62491.38 | O11: =-O10/(Inputs!O9*(12/365)) -> -63136.213 | P11: =-P10/(Inputs!P9*(12/365)) -> -149047.75 | Q11: =-Q10/(Inputs!Q9*(12/365)) -> -200925.47 | R11: =-R10/(Inputs!R9*(12/365)) -> -51835.948 | ... BQ11: =-BQ10/(Inputs!BQ9*(12/365)) -> -1758720.3
B12: Trade debtors carried forward | J12: =J9+J10+J11 -> 0 | K12: =K9+K10+K11 -> 40500 | L12: 17545 | M12: 92453 | N12: 93407 | O12: 220509 | P12: 297259.6 | Q12: 76688.8 | R12: =R9+R10+R11 -> 70752.852 | S12: =S9+S10+S11 -> 50949.165 | T12: =T9+T10+T11 -> 66731.303 | U12: =U9+U10+U11 -> 95545.885 | V12: =V9+V10+V11 -> 110583.94 | W12: =W9+W10+W11 -> 202757.39 | X12: =X9+X10+X11 -> 257558.41 | Y12: =Y9+Y10+Y11 -> 326528 | ... BQ12: =BQ9+BQ10+BQ11 -> 2664429.4
B15: Other Debtors
B16: Other debtors brought forward | J16: 0 | K16: =J18 -> 0 | L16: =K18 -> 0 | M16: =L18 -> 0 | N16: =M18 -> 0 | O16: =N18 -> 0 | P16: =O18 -> 0 | Q16: =P18 -> 0 | R16: =Q18 -> 0 | ... BQ16: =BP18 -> 0
B17: Movement on other debtors | J17: 0
B18: Other debtors carried forward | J18: =SUM(J16:J17) -> 0 | K18: =SUM(K16:K17) -> 0 | L18: =SUM(L16:L17) -> 0 | M18: =SUM(M16:M17) -> 0 | N18: =SUM(N16:N17) -> 0 | O18: =SUM(O16:O17) -> 0 | P18: =SUM(P16:P17) -> 0 | Q18: =SUM(Q16:Q17) -> 0 | ... BQ18: =SUM(BQ16:BQ17) -> 0
B20: Prepayments
B21: Prepayments brought forward | J21: 0 | K21: =J23 -> 0 | L21: =K23 -> 0 | M21: =L23 -> 0 | N21: =M23 -> 0 | O21: =N23 -> 0 | P21: =O23 -> 0 | Q21: =P23 -> 0 | R21: =Q23 -> 0 | ... BQ21: =BP23 -> 0
B22: Movement on prepayments | J22: 0 | K22: 0 | L22: 0 | M22: 0
B23: Prepayments carried forward | J23: =SUM(J21:J22) -> 0 | K23: =SUM(K21:K22) -> 0 | L23: =SUM(L21:L22) -> 0 | M23: =SUM(M21:M22) -> 0 | N23: =SUM(N21:N22) -> 0 | O23: =SUM(O21:O22) -> 0 | P23: =SUM(P21:P22) -> 0 | Q23: =SUM(Q21:Q22) -> 0 | ... BQ23: =SUM(BQ21:BQ22) -> 0
B25: Total Other Debtors and Prepayments | J25: =J18+J23 -> 0 | K25: =K18+K23 -> 0 | L25: =L18+L23 -> 0 | M25: =M18+M23 -> 0 | N25: =N18+N23 -> 0 | O25: =O18+O23 -> 0 | P25: =P18+P23 -> 0 | Q25: =Q18+Q23 -> 0 | ... BQ25: =BQ18+BQ23 -> 0
B28: Trade Creditors
B29: Total COS | J29: 0 | K29: =3125+238 -> 3363 | L29: ='COS and Overheads'!L25 -> 28805 | M29: ='COS and Overheads'!M25 -> 25039 | N29: ='COS and Overheads'!N25 -> 31307 | O29: ='COS and Overheads'!O25 -> 103407 | P29: ='COS and Overheads'!P25 -> 64290 | Q29: ='COS and Overheads'!Q25 -> 10629 | R29: ='COS and Overheads'!R25 -> 6750 | S29: ='COS and Overheads'!S25 -> 16801 | ... BQ29: ='COS and Overheads'!BQ25 -> 493111
B30: Total Admin Expenses | J30: 2643 | K30: ='COS and Overheads'!K46 -> 2398 | L30: ='COS and Overheads'!L46 -> 16019 | M30: ='COS and Overheads'!M46 -> 35404 | N30: ='COS and Overheads'!N46 -> 33427 | O30: ='COS and Overheads'!O46 -> 31398 | P30: ='COS and Overheads'!P46 -> 31033 | Q30: ='COS and Overheads'!Q46 -> 66424 | R30: ='COS and Overheads'!R46 -> 39148 | ... BQ30: ='COS and Overheads'!BQ46 -> 38309.25
B31: Capex | J31: ='Fixed Assets'!J68 -> 0 | K31: ='Fixed Assets'!K68 -> 0 | L31: ='Fixed Assets'!L68 -> 0 | M31: ='Fixed Assets'!M68 -> 0 | N31: ='Fixed Assets'!N68 -> 0 | O31: ='Fixed Assets'!O68 -> 0 | P31: ='Fixed Assets'!P68 -> 0 | Q31: ='Fixed Assets'!Q68 -> 0 | ... BQ31: ='Fixed Assets'!BQ68 -> 39520
B32: Total Invoices | J32: =SUM(J29:J31) -> 2643 | K32: =SUM(K29:K31) -> 5761 | L32: =SUM(L29:L31) -> 44824 | M32: =SUM(M29:M31) -> 60443 | N32: =SUM(N29:N31) -> 64734 | O32: =SUM(O29:O31) -> 134805 | P32: =SUM(P29:P31) -> 95323 | Q32: =SUM(Q29:Q31) -> 77053 | ... BQ32: =SUM(BQ29:BQ31) -> 570940.25
B33: Input VAT | J33: =J32*Inputs!J8 -> 528.6 | K33: =K32*Inputs!K8 -> 1152.2 | L33: =L32*Inputs!L8 -> 8964.8 | M33: =M32*Inputs!M8 -> 12088.6 | N33: =N32*Inputs!N8 -> 12946.8 | O33: =O32*Inputs!O8 -> 26961 | P33: =P32*Inputs!P8 -> 19064.6 | Q33: =Q32*Inputs!Q8 -> 15410.6 | ... BQ33: =BQ32*Inputs!BQ8 -> 114188.05
B34: Gross purchase invoices | J34: =SUM(J32:J33) -> 3171.6 | K34: =SUM(K32:K33) -> 6913.2 | L34: =SUM(L32:L33) -> 53788.8 | M34: =SUM(M32:M33) -> 72531.6 | N34: =SUM(N32:N33) -> 77680.8 | O34: =SUM(O32:O33) -> 161766 | P34: =SUM(P32:P33) -> 114387.6 | Q34: =SUM(Q32:Q33) -> 92463.6 | ... BQ34: =SUM(BQ32:BQ33) -> 685128.3
B35: Trade creditors brought forward | J35: 0 | K35: =J37 -> 3171.6 | L35: =K37 -> 6628.8 | M35: =L37 -> 11647 | N35: =M37 -> 79497 | O35: =N37 -> 55824.5 | P35: =O37 -> 21864.6 | Q35: =P37 -> 42040.64 | R35: =Q37 -> 65244.18 | ... BQ35: =BP37 -> 663928.5
B36: Trade creditor payments | K36: -3456 | L36: =-L35/(Inputs!L10*(12/365)) -> -6720.8667 | M36: =-M35/(Inputs!M10*(12/365)) -> -11808.764 | N36: =-N35/(Inputs!N10*(12/365)) -> -80601.125 | O36: =-O35/(Inputs!O10*(12/365)) -> -56599.84 | P36: =-P35/(Inputs!P10*(12/365)) -> -22168.275 | Q36: =-Q35/(Inputs!Q10*(12/365)) -> -42624.538 | R36: =-R35/(Inputs!R10*(12/365)) -> -66150.349 | S36: =-S35/(Inputs!S10*(12/365)) -> -54923.812 | ... BQ36: =-BQ35/(Inputs!BQ10*(12/365)) -> -673149.73
B37: Trade creditors carried forward | J37: =SUM(J34:J36) -> 3171.6 | K37: =SUM(K34:K36) -> 6628.8 | L37: 11647 | M37: 79497 | N37: 55824.5 | O37: 21864.6 | P37: 42040.64 | Q37: 65244.18 | R37: =SUM(R34:R36) -> 54171.431 | S37: =SUM(S34:S36) -> 95150.419 | T37: =SUM(T34:T36) -> 113850.87 | U37: =SUM(U34:U36) -> 111612.64 | V37: =SUM(V34:V36) -> 123121.72 | W37: =SUM(W34:W36) -> 202971.88 | X37: =SUM(X34:X36) -> 169560.35 | Y37: =SUM(Y34:Y36) -> 173978.4 | ... BQ37: =SUM(BQ34:BQ36) -> 675907.07
B40: Other Creditors
B41: Other creditors brought forward | J41: 0 | K41: =J43 -> 0 | L41: =K43 -> 0 | M41: =L43 -> 0 | N41: =M43 -> 0 | O41: =N43 -> 0 | P41: =O43 -> 0 | Q41: =P43 -> 0 | R41: =Q43 -> 0 | ... BQ41: =BP43 -> 0
B42: Movement on other creditors | J42: 0
B43: Other creditors carried forward | J43: =SUM(J41:J42) -> 0 | K43: =SUM(K41:K42) -> 0 | L43: =SUM(L41:L42) -> 0 | M43: =SUM(M41:M42) -> 0 | N43: =SUM(N41:N42) -> 0 | O43: =SUM(O41:O42) -> 0 | P43: =SUM(P41:P42) -> 0 | Q43: =SUM(Q41:Q42) -> 0 | ... BQ43: =SUM(BQ41:BQ42) -> 0
B46: Corporation Tax
B47: Corporation tax brought forward | J47: 0 | K47: =J50 -> 2280.75 | L47: =K50 -> 11915.25 | M47: =L50 -> 3114.25 | N47: =M50 -> 2359.25 | O47: =N50 -> 0 | P47: =O50 -> 4351.5 | Q47: =P50 -> 11453.75 | R47: =Q50 -> 846.75 | ... BQ47: =BP50 -> 1938429.1
B48: Corporation tax charge | J48: ='Corporation tax'!J34 -> 2280.75 | K48: ='Corporation tax'!K34 -> 9634.5 | L48: ='Corporation tax'!L34 -> -8801 | M48: ='Corporation tax'!M34 -> -755 | N48: ='Corporation tax'!N34 -> -2359.25 | O48: ='Corporation tax'!O34 -> 4351.5 | P48: ='Corporation tax'!P34 -> 7102.25 | Q48: ='Corporation tax'!Q34 -> -10607 | ... BQ48: ='Corporation tax'!BQ34 -> 211992.4
B49: Corporation tax payment / (repayment) | AP49: =-AG50 -> 0 | BB49: =-AS50 -> -582159.54 | BN49: =-BE50 -> -1380497.9
B50: Corporation tax carried forward | J50: =SUM(J47:J49) -> 2280.75 | K50: =SUM(K47:K49) -> 11915.25 | L50: =SUM(L47:L49) -> 3114.25 | M50: =SUM(M47:M49) -> 2359.25 | N50: =SUM(N47:N49) -> 0 | O50: =SUM(O47:O49) -> 4351.5 | P50: =SUM(P47:P49) -> 11453.75 | Q50: =SUM(Q47:Q49) -> 846.75 | ... BQ50: =SUM(BQ47:BQ49) -> 2150421.5
B53: Other Taxation and Social Security
B55: PAYE, NIC & Pension liability
B56: PAYE, NIC & Pension balance brought forward | J56: 0 | K56: =J59 -> 0 | L56: =K59 -> 0 | M56: =L59 -> 0 | N56: =M59 -> 0 | O56: =N59 -> 0 | P56: =O59 -> 0 | Q56: =P59 -> 0 | R56: =Q59 -> 0 | ... BQ56: =BP59 -> 49500
B57: PAYE, NIC & Pension per monthly payroll | J57: ='Wages and Salaries'!J88 -> 0 | K57: ='Wages and Salaries'!K88 -> 0 | L57: ='Wages and Salaries'!L88 -> 0 | M57: ='Wages and Salaries'!M88 -> 0 | N57: ='Wages and Salaries'!N88 -> 0 | O57: ='Wages and Salaries'!O88 -> 0 | P57: ='Wages and Salaries'!P88 -> 0 | Q57: ='Wages and Salaries'!Q88 -> 0 | ... BQ57: ='Wages and Salaries'!BQ88 -> 49500
B58: HMRC payment | K58: =-J57 -> 0 | L58: =-K57 -> 0 | M58: =-L57 -> 0 | N58: =-M57 -> 0 | O58: =-N57 -> 0 | P58: =-O57 -> 0 | Q58: =-P57 -> 0 | R58: =-Q57 -> 0 | ... BQ58: =-BP57 -> -49500
B59: PAYE, NIC & Pension balance carried forward | J59: =SUM(J56:J58) -> 0 | K59: =SUM(K56:K58) -> 0 | L59: =SUM(L56:L58) -> 0 | M59: =SUM(M56:M58) -> 0 | N59: =SUM(N56:N58) -> 0 | O59: =SUM(O56:O58) -> 0 | P59: =SUM(P56:P58) -> 0 | Q59: =SUM(Q56:Q58) -> 0 | ... BQ59: =SUM(BQ56:BQ58) -> 49500
B61: VAT (Liability) / Recoverable
B62: VAT balance brought forward | J62: 0 | K62: =J67 -> 3460.4 | L62: =K67 -> 11425.2 | M62: =L67 -> 7553 | N62: =M67 -> 12993 | O62: =N67 -> 17147.98 | P62: =O67 -> 46741.15 | Q62: =P67 -> 52686.59 | R62: =Q67 -> 32914.87 | ... BQ62: =BP67 -> 707301.2
B63: Output VAT | J63: 3989 | K63: =K8+2367 -> 9117 | L63: =L8 -> 2924 | M63: =M8 -> 12484.6 | N63: =N8 -> 11954.8 | O63: =O8 -> 31546.8 | P63: =P8 -> 24746.4 | Q63: =Q8 -> 6925 | R63: =R8 -> 7650 | S63: =S8 -> 4670 | ... BQ63: =BQ8 -> 303534.55
B64: Input VAT | J64: =-J33 -> -528.6 | K64: =-K33 -> -1152.2 | L64: =-L33 -> -8964.8 | M64: =-M33 -> -12088.6 | N64: =-N33 -> -12946.8 | O64: =-O33 -> -26961 | P64: =-P33 -> -19064.6 | Q64: =-Q33 -> -15410.6 | ... BQ64: =-BQ33 -> -114188.05
B65: VAT (liability) / recoverable | J65: =SUM(J62:J64) -> 3460.4 | K65: =SUM(K62:K64) -> 11425.2 | L65: =SUM(L62:L64) -> 5384.4 | M65: =SUM(M62:M64) -> 7949 | N65: =SUM(N62:N64) -> 12001 | O65: =SUM(O62:O64) -> 21733.78 | P65: =SUM(P62:P64) -> 52422.95 | Q65: =SUM(Q62:Q64) -> 44200.99 | ... BQ65: =SUM(BQ62:BQ64) -> 896647.7
B66: HMRC payment / (receipt) | J66: 0 | O66: =-M65 -> -7949 | R66: =-P65 -> -52422.95 | U66: =-S65 -> 32351.48 | X66: =-V65 -> 24879.7 | AA66: =-Y65 -> -8072.55 | AD66: =-AB65 -> -41807.55 | AG66: =-AE65 -> -59962.55 | AJ66: =-AH65 -> -85919.3 | AM66: =-AK65 -> -124734.9 | AP66: =-AN65 -> -150460.05 | AS66: =-AQ65 -> -179342.45 | AV66: =-AT65 -> -221009.18 | AY66: =-AW65 -> -282327.71 | BB66: =-AZ65 -> -317856.02 | BE66: =-BC65 -> -356040.47 | BH66: =-BF65 -> -394676.77 | BK66: =-BI65 -> -435731.64 | BN66: =-BL65 -> -478249.76 | BQ66: =-BO65 -> -522970.08
B67: VAT balance carried forward | J67: =SUM(J65:J66) -> 3460.4 | K67: =SUM(K65:K66) -> 11425.2 | L67: 7553 | M67: 12993 | N67: 17147.98 | O67: 46741.15 | P67: 52686.59 | Q67: 32914.87 | R67: =SUM(R65:R66) -> -21037.68 | S67: =SUM(S65:S66) -> -32351.48 | T67: =SUM(T65:T66) -> -43176.88 | U67: =SUM(U65:U66) -> -17371.05 | V67: =SUM(V65:V66) -> -24879.7 | W67: =SUM(W65:W66) -> -31173.35 | X67: =SUM(X65:X66) -> -3048.55 | Y67: =SUM(Y65:Y66) -> 8072.55 | ... BQ67: =SUM(BQ65:BQ66) -> 373677.62
B69: Total Tax and Social Security | J69: =J59+J67 -> 3460.4 | K69: =K59+K67 -> 11425.2 | L69: =L59+L67 -> 7553 | M69: =M59+M67 -> 12993 | N69: =N59+N67 -> 17147.98 | O69: =O59+O67 -> 46741.15 | P69: =P59+P67 -> 52686.59 | Q69: =Q59+Q67 -> 32914.87 | ... BQ69: =BQ59+BQ67 -> 423177.62
B72: Accruals
B73: Accruals brought forward | J73: 0 | K73: =J75 -> 0 | L73: =K75 -> 0 | M73: =L75 -> 0 | N73: =M75 -> 0 | O73: =N75 -> 24500 | P73: =O75 -> 142987.03 | Q73: =P75 -> 156664.18 | R73: =Q75 -> 53690 | ... BQ73: =BP75 -> 0
B74: Movement on accruals | J74: 0 | N74: 24500 | O74: 118487.03 | P74: 13677.15 | Q74: -102974.18 | R74: -20000 | S74: -33690
B75: Accruals carried forward | J75: =SUM(J73:J74) -> 0 | K75: =SUM(K73:K74) -> 0 | L75: =SUM(L73:L74) -> 0 | M75: =SUM(M73:M74) -> 0 | N75: =SUM(N73:N74) -> 24500 | O75: =SUM(O73:O74) -> 142987.03 | P75: =SUM(P73:P74) -> 156664.18 | Q75: =SUM(Q73:Q74) -> 53690 | ... BQ75: =SUM(BQ73:BQ74) -> 0
B78: Provision for Liabilities
B79: Provision brought forward | J79: 0 | K79: =J81 -> 0 | L79: =K81 -> 0 | M79: =L81 -> 0 | N79: =M81 -> 0 | O79: =N81 -> 0 | P79: =O81 -> 0 | Q79: =P81 -> 0 | R79: =Q81 -> 0 | ... BQ79: =BP81 -> 0
B80: Movement on provision | J80: 0
B81: Provisions carried forward | J81: =SUM(J79:J80) -> 0 | K81: =SUM(K79:K80) -> 0 | L81: =SUM(L79:L80) -> 0 | M81: =SUM(M79:M80) -> 0 | N81: =SUM(N79:N80) -> 0 | O81: =SUM(O79:O80) -> 0 | P81: =SUM(P79:P80) -> 0 | Q81: =SUM(Q79:Q80) -> 0 | ... BQ81: =SUM(BQ79:BQ80) -> 0

Sheet Corporation tax
A1: Business 1
A2: Corporation tax | J2: =Timing!J2 -> 44986 | K2: =Timing!K2 -> 45017 | L2: =Timing!L2 -> 45047 | M2: =Timing!M2 -> 45078 | N2: =Timing!N2 -> 45108 | O2: =Timing!O2 -> 45139 | P2: =Timing!P2 -> 45170 | Q2: =Timing!Q2 -> 45200 | ... BQ2: =Timing!BQ2 -> 46784
J3: =Timing!J3 -> 45016 | K3: =Timing!K3 -> 45046 | L3: =Timing!L3 -> 45077 | M3: =Timing!M3 -> 45107 | N3: =Timing!N3 -> 45138 | O3: =Timing!O3 -> 45169 | P3: =Timing!P3 -> 45199 | Q3: =Timing!Q3 -> 45230 | ... BQ3: =Timing!BQ3 -> 46812
B6: EBT | J6: ='Financials Monthly'!J50 -> 9123 | K6: ='Financials Monthly'!K50 -> 38538 | L6: ='Financials Monthly'!L50 -> -35204 | M6: ='Financials Monthly'!M50 -> -3020 | N6: ='Financials Monthly'!N50 -> -9960 | O6: ='Financials Monthly'!O50 -> 17929 | P6: ='Financials Monthly'!P50 -> 28409 | Q6: ='Financials Monthly'!Q50 -> -42428 | ... BQ6: ='Financials Monthly'!BQ50 -> 847969.58
B8: Corporation tax | J8: =J6*Inputs!J27 -> 2280.75 | K8: =K6*Inputs!K27 -> 9634.5 | L8: =L6*Inputs!L27 -> -8801 | M8: =M6*Inputs!M27 -> -755 | N8: =N6*Inputs!N27 -> -2490 | O8: =O6*Inputs!O27 -> 4482.25 | P8: =P6*Inputs!P27 -> 7102.25 | Q8: =Q6*Inputs!Q27 -> -10607 | ... BQ8: =BQ6*Inputs!BQ27 -> 211992.4
B10: =B24 -> Current period taxable profits | J10: =J24 -> 9123 | K10: =K24 -> 38538 | L10: =L24 -> 0 | M10: =M24 -> 0 | N10: =N24 -> 0 | O10: =O24 -> 17929 | P10: =P24 -> 28409 | Q10: =Q24 -> 0 | ... BT10: =BT24 -> 0
B11: =B18 -> Losses b/f balance | J11: =J18 -> 0 | K11: =K18 -> 0 | L11: =L18 -> 0 | M11: =M18 -> 0 | N11: =N18 -> 0 | O11: =O18 -> 523 | P11: =P18 -> 0 | Q11: =Q18 -> 0 | ... BQ11: =BQ18 -> 3222.1667
B12: =B20 -> Use of Tax | J12: =MIN(J10,J11) -> 0 | K12: =MIN(K10,K11) -> 0 | L12: =MIN(L10,L11) -> 0 | M12: =MIN(M10,M11) -> 0 | N12: =MIN(N10,N11) -> 0 | O12: =MIN(O10,O11) -> 523 | P12: =MIN(P10,P11) -> 0 | Q12: =MIN(Q10,Q11) -> 0 | ... BQ12: =MIN(BQ10,BQ11) -> 3222.1667
B18: Losses b/f balance | J18: =I21 -> 0 | K18: =J21 -> 0 | L18: =K21 -> 0 | M18: =L21 -> 0 | N18: =M21 -> 0 | O18: =N21 -> 523 | P18: =O21 -> 0 | Q18: =P21 -> 0 | ... BQ18: =BP21 -> 3222.1667
A19: plus | B19: =B25 -> Current period losses | J19: =J25 -> 0 | K19: =K25 -> 0 | L19: =L25 -> 35204 | M19: =M25 -> 3020 | N19: =N25 -> 9960 | O19: =O25 -> 0 | P19: =P25 -> 0 | Q19: =Q25 -> 42428 | ... BQ19: =BQ25 -> 0
A20: less | B20: Use of Tax | J20: =J12 -> 0 | K20: =K12 -> 0 | L20: 35204 | M20: 3020 | N20: 9437 | O20: =O12 -> 523 | P20: =P12 -> 0 | Q20: 42428 | R20: 3387 | S20: =S12 -> 0 | T20: =T12 -> 0 | U20: =U12 -> 0 | V20: =V12 -> 0 | W20: =W12 -> 0 | X20: =X12 -> 0 | Y20: =Y12 -> 0 | Z20: =Z12 -> 6182.5833 | ... AG20: =AG12 -> 71216.333
B21: Tax loss cfwd balance | J21: =J18+J19-J20 -> 0 | K21: =K18+K19-K20 -> 0 | L21: =L18+L19-L20 -> 0 | M21: =M18+M19-M20 -> 0 | N21: =N18+N19-N20 -> 523 | O21: =O18+O19-O20 -> 0 | P21: =P18+P19-P20 -> 0 | Q21: =Q18+Q19-Q20 -> 0 | ... BR21: =BR18+BR19-BR20 -> 0
B23: Profit/loss | J23: =J6 -> 9123 | K23: =K6 -> 38538 | L23: =L6 -> -35204 | M23: =M6 -> -3020 | N23: =N6 -> -9960 | O23: =O6 -> 17929 | P23: =P6 -> 28409 | Q23: =Q6 -> -42428 | ... BQ23: =BQ6 -> 847969.58
B24: Current period taxable profits | J24: =MAX(J23,0) -> 9123 | K24: =MAX(K23,0) -> 38538 | L24: =MAX(L23,0) -> 0 | M24: =MAX(M23,0) -> 0 | N24: =MAX(N23,0) -> 0 | O24: =MAX(O23,0) -> 17929 | P24: =MAX(P23,0) -> 28409 | Q24: =MAX(Q23,0) -> 0 | ... BQ24: =MAX(BQ23,0) -> 847969.58
B25: Current period losses | J25: =MIN(J23,0)*-1 -> 0 | K25: =MIN(K23,0)*-1 -> 0 | L25: =MIN(L23,0)*-1 -> 35204 | M25: =MIN(M23,0)*-1 -> 3020 | N25: =MIN(N23,0)*-1 -> 9960 | O25: =MIN(O23,0)*-1 -> 0 | P25: =MIN(P23,0)*-1 -> 0 | Q25: =MIN(Q23,0)*-1 -> 42428 | ... BQ25: =MIN(BQ23,0)*-1 -> 0
B28: =B24 -> Current period taxable profits | J28: =J24 -> 9123 | K28: =K24 -> 38538 | L28: =L24 -> 0 | M28: =M24 -> 0 | N28: =N24 -> 0 | O28: =O24 -> 17929 | P28: =P24 -> 28409 | Q28: =Q24 -> 0 | ... BQ28: =BQ24 -> 847969.58 | BR28: 0 | BS28: 0 | BT28: 0
A29: less | B29: Use of Tax | J29: =J20 -> 0 | K29: =K20 -> 0 | L29: =L20 -> 35204 | M29: =M20 -> 3020 | N29: =N20 -> 9437 | O29: =O20 -> 523 | P29: =P20 -> 0 | Q29: =Q20 -> 42428 | ... BQ29: =BQ20 -> 0
B30: Income subject to tax | J30: =J28-J29 -> 9123 | K30: =K28-K29 -> 38538 | L30: =L28-L29 -> -35204 | M30: =M28-M29 -> -3020 | N30: =N28-N29 -> -9437 | O30: =O28-O29 -> 17406 | P30: =P28-P29 -> 28409 | Q30: =Q28-Q29 -> -42428 | ... BQ30: =BQ28-BQ29 -> 847969.58
B32: Corporation tax rate | J32: =Inputs!J27 -> 0.25 | K32: =Inputs!K27 -> 0.25 | L32: =Inputs!L27 -> 0.25 | M32: =Inputs!M27 -> 0.25 | N32: =Inputs!N27 -> 0.25 | O32: =Inputs!O27 -> 0.25 | P32: =Inputs!P27 -> 0.25 | Q32: =Inputs!Q27 -> 0.25 | ... BQ32: =Inputs!BQ27 -> 0.25
B33: =B30 -> Income subject to tax | J33: =J30 -> 9123 | K33: =K30 -> 38538 | L33: =L30 -> -35204 | M33: =M30 -> -3020 | N33: =N30 -> -9437 | O33: =O30 -> 17406 | P33: =P30 -> 28409 | Q33: =Q30 -> -42428 | ... BQ33: =BQ30 -> 847969.58
B34: Tax payments | J34: =J32*J33 -> 2280.75 | K34: =K32*K33 -> 9634.5 | L34: =L32*L33 -> -8801 | M34: =M32*M33 -> -755 | N34: =N32*N33 -> -2359.25 | O34: =O32*O33 -> 4351.5 | P34: =P32*P33 -> 7102.25 | Q34: =Q32*Q33 -> -10607 | ... BQ34: =BQ32*BQ33 -> 211992.4
